Workbook

Sheet Leia-me
A2: CORRELAÇÃO LEGISLATIVA CFTA
B3: Assembleias legislativas, Congresso Nacional e marco normativo do técnico agrícola
A5: Produzido por | B5: Belli Relações Governamentais para o Conselho Federal dos Técnicos Agrícolas
A6: Posição | B6: 12 de agosto de 2026
A8: O QUE É ESTA PLANILHA
B9: Reúne, em uma única base, as proposições legislativas que podem afetar as competências do técnico agrícola — nas assembleias legislativas e no Congresso Nacional — e as correlaciona com o marco normativo que sustenta a atuação do Conselho.
B10: A correlação é feita por eixo de competência. Quando uma proposição estadual e uma federal tocam o mesmo eixo, elas disputam o mesmo espaço normativo e devem ser lidas em conjunto — é isso que a aba Correlação por eixo mostra.
A12: ABAS
A13: Correlação por eixo | B13: Os 12 eixos de competência, as normas que os sustentam e a contagem de matérias correlacionadas em cada esfera.
A14: Assembleias | B14: Proposições estaduais selecionadas, com casa de origem, autoria, eixo, prioridade e motivo do interesse.
A15: Novas federais | B15: Matérias federais identificadas na varredura de agosto que ainda não constavam da carteira monitorada — candidatas a entrar no radar.
A16: Federais monitoradas | B16: As 56 matérias já cadastradas na plataforma Governor, com situação processual e eixo de competência.
A17: Marco normativo | B17: As normas correlacionadas, por eixo.
A18: Triagem | B18: O funil completo: quantos registros entraram, quantos foram descartados e por quê.
A20: COMO FOI FEITA A TRIAGEM
A21: Exclusão formal | B21: Foram descartadas moções, homenagens, votos de pesar e congratulação, denominações de logradouros e equipamentos, datas comemorativas, títulos de cidadão, sessões solenes, requerimentos de informação e pedidos de licença — matérias sem conteúdo legislativo material.
A22: Classificação | B22: Cada ementa foi confrontada com os termos de cada eixo de competência. O peso de cada termo reflete o grau de especificidade: 'técnico agrícola' pesa mais que 'assistência técnica', que pesa mais que 'agricultura familiar'.
A23: Corte de aderência | B23: Matérias com pontuação somada abaixo de 10 foram descartadas por aderência fraca. O corte foi auditado: nenhuma matéria de alta relevância ficou abaixo dele.
A24: Prioridade | B24: Muito alta a partir de 24 pontos, ou 18 pontos com dois ou mais eixos; alta a partir de 17; médio-alta a partir de 12; média abaixo disso. Na base consolidada de abril, a prioridade original atribuída na triagem foi preservada.
A26: LIMITES DECLARADOS
A27: Recorte temporal | B27: A varredura de 11/08/2026 cobre apenas proposições apresentadas em 2026. Matérias anteriores ainda em tramitação nas assembleias não estão nesse recorte — permanecem na base consolidada de abril, que cobre anos anteriores.
A28: Resoluções do CFTA | B28: O marco normativo aqui correlacionado reúne leis, decretos e instruções normativas federais. As resoluções próprias do Conselho ainda não foram incorporadas — quando a relação for fornecida, entram como uma quarta camada da correlação, sem alterar a estrutura.
A29: Validação pendente | B29: A seleção é uma proposta técnica. A entrada de cada matéria no radar permanente depende de validação do CFTA.

Sheet Correlação por eixo
A1: Eixo | B1: Competência | C1: O que abrange | D1: Marco normativo correlacionado | E1: Federais monitoradas | F1: Proposições estaduais | G1: Novas federais | H1: Total de matérias | I1: Casas legislativas
A2: E1 | B2: Exercício profissional e responsabilidade técnica | C2: Atribuições do técnico agrícola, emissão de ART/TRT e habilitação legal para assinar projetos, laudos e responsabilidades técnicas. | D2: Lei nº 5.524/1968 · Decreto nº 90.922/1985 · Lei nº 13.639/2018 · Lei nº 6.496/1977 · Lei nº 5.194/1966 | E2: =COUNTIF('Federais monitoradas'!$N:$N,"*|"&$A2&"|*") -> 17 | F2: =COUNTIF(Assembleias!$R:$R,"*|"&$A2&"|*") -> 9 | G2: =COUNTIF('Novas federais'!$R:$R,"*|"&$A2&"|*") -> 2 | H2: =SUM(E2:G2) -> 28 | I2: 7
A3: E2 | B3: Assistência técnica e extensão rural | C3: Política de ATER, composição de equipes técnicas e cobertura de assistência ao produtor rural. | D3: Lei nº 12.188/2010 · Lei nº 8.171/1991 | E3: =COUNTIF('Federais monitoradas'!$N:$N,"*|"&$A3&"|*") -> 3 | F3: =COUNTIF(Assembleias!$R:$R,"*|"&$A3&"|*") -> 82 | G3: =COUNTIF('Novas federais'!$R:$R,"*|"&$A3&"|*") -> 14 | H3: =SUM(E3:G3) -> 99 | I3: 10
A4: E3 | B4: Defesa agropecuária, inspeção e sanidade | C4: Inspeção industrial e sanitária, defesa sanitária vegetal e animal e fiscalização de produtos de origem animal e vegetal. | D4: Lei nº 1.283/1950 · Lei nº 9.712/1998 · Lei nº 7.889/1989 | E4: =COUNTIF('Federais monitoradas'!$N:$N,"*|"&$A4&"|*") -> 4 | F4: =COUNTIF(Assembleias!$R:$R,"*|"&$A4&"|*") -> 9 | G4: =COUNTIF('Novas federais'!$R:$R,"*|"&$A4&"|*") -> 9 | H4: =SUM(E4:G4) -> 22 | I4: 8
A5: E4 | B5: Agrotóxicos, bioinsumos e fertilizantes | C5: Registro, aplicação, fiscalização e receituário de agrotóxicos, bioinsumos, fertilizantes e corretivos, inclusive aplicação aeroagrícola. | D5: Lei nº 14.785/2023 · Decreto nº 12.858/2026 · IN MAPA nº 53/2013 | E5: =COUNTIF('Federais monitoradas'!$N:$N,"*|"&$A5&"|*") -> 4 | F5: =COUNTIF(Assembleias!$R:$R,"*|"&$A5&"|*") -> 4 | G5: =COUNTIF('Novas federais'!$R:$R,"*|"&$A5&"|*") -> 10 | H5: =SUM(E5:G5) -> 18 | I5: 3
A6: E5 | B6: Agroindústria e produção artesanal | C6: Agroindústria familiar, produtos artesanais, certificação e regularização de pequenas unidades de processamento. | D6: Lei nº 8.171/1991 · Lei nº 13.680/2018 · Lei nº 8.918/1994 | E6: =COUNTIF('Federais monitoradas'!$N:$N,"*|"&$A6&"|*") -> 5 | F6: =COUNTIF(Assembleias!$R:$R,"*|"&$A6&"|*") -> 6 | G6: =COUNTIF('Novas federais'!$R:$R,"*|"&$A6&"|*") -> 2 | H6: =SUM(E6:G6) -> 13 | I6: 4
A7: E6 | B7: Sementes, mudas e material propagativo | C7: Produção, comércio, multiplicação e fiscalização de sementes e mudas, incluindo cultivares locais e crioulas. | D7: Lei nº 10.711/2003 · Lei nº 9.456/1997 | E7: =COUNTIF('Federais monitoradas'!$N:$N,"*|"&$A7&"|*") -> 4 | F7: =COUNTIF(Assembleias!$R:$R,"*|"&$A7&"|*") -> 72 | G7: =COUNTIF('Novas federais'!$R:$R,"*|"&$A7&"|*") -> 1 | H7: =SUM(E7:G7) -> 77 | I7: 4
A8: E7 | B8: Regularização fundiária e georreferenciamento | C8: Reurb, registros públicos, cadastro rural, georreferenciamento e levantamentos planialtimétricos. | D8: Lei nº 13.465/2017 · Lei nº 6.015/1973 · Lei nº 11.952/2009 · Lei nº 10.267/2001 | E8: =COUNTIF('Federais monitoradas'!$N:$N,"*|"&$A8&"|*") -> 11 | F8: =COUNTIF(Assembleias!$R:$R,"*|"&$A8&"|*") -> 6 | G8: =COUNTIF('Novas federais'!$R:$R,"*|"&$A8&"|*") -> 3 | H8: =SUM(E8:G8) -> 20 | I8: 4
A9: E8 | B9: Meio ambiente aplicado à atividade rural | C9: Licenciamento ambiental, áreas de preservação, recursos hídricos e passivos ambientais com exigência de responsável técnico. | D9: Lei nº 12.651/2012 · Lei nº 6.938/1981 · Lei nº 9.433/1997 | E9: =COUNTIF('Federais monitoradas'!$N:$N,"*|"&$A9&"|*") -> 6 | F9: =COUNTIF(Assembleias!$R:$R,"*|"&$A9&"|*") -> 20 | G9: =COUNTIF('Novas federais'!$R:$R,"*|"&$A9&"|*") -> 8 | H9: =SUM(E9:G9) -> 34 | I9: 6
A10: E9 | B10: Formação, ensino técnico e qualificação profissional | C10: Educação profissional agrícola, escolas técnicas, estágio e programas de qualificação. | D10: Lei nº 9.394/1996 · Lei nº 11.892/2008 · Lei nº 11.788/2008 | E10: =COUNTIF('Federais monitoradas'!$N:$N,"*|"&$A10&"|*") -> 4 | F10: =COUNTIF(Assembleias!$R:$R,"*|"&$A10&"|*") -> 2 | G10: =COUNTIF('Novas federais'!$R:$R,"*|"&$A10&"|*") -> 5 | H10: =SUM(E10:G10) -> 11 | I10: 2
A11: E10 | B11: Conselhos profissionais, anuidades e fiscalização | C11: Regime jurídico, arrecadação, anuidades e poder de fiscalização dos conselhos de profissões regulamentadas. | D11: Lei nº 13.639/2018 · Lei nº 12.514/2011 · Lei nº 10.741/2003 | E11: =COUNTIF('Federais monitoradas'!$N:$N,"*|"&$A11&"|*") -> 11 | F11: =COUNTIF(Assembleias!$R:$R,"*|"&$A11&"|*") -> 0 | G11: =COUNTIF('Novas federais'!$R:$R,"*|"&$A11&"|*") -> 2 | H11: =SUM(E11:G11) -> 13 | I11: 0
A12: E11 | B12: Crédito rural, tributação e política agrícola | C12: Crédito, seguro rural, ITR e instrumentos de política agrícola que exigem laudo, projeto ou responsável técnico. | D12: Lei nº 8.171/1991 · Lei nº 9.393/1996 · Lei nº 8.629/1993 | E12: =COUNTIF('Federais monitoradas'!$N:$N,"*|"&$A12&"|*") -> 4 | F12: =COUNTIF(Assembleias!$R:$R,"*|"&$A12&"|*") -> 17 | G12: =COUNTIF('Novas federais'!$R:$R,"*|"&$A12&"|*") -> 39 | H12: =SUM(E12:G12) -> 60 | I12: 5
A13: E12 | B13: Produção animal, aquicultura e cadeias específicas | C13: Pecuária, aquicultura, apicultura e demais cadeias em que o técnico agrícola atua como responsável técnico. | D13: Lei nº 11.959/2009 · Lei nº 5.517/1968 | E13: =COUNTIF('Federais monitoradas'!$N:$N,"*|"&$A13&"|*") -> 4 | F13: =COUNTIF(Assembleias!$R:$R,"*|"&$A13&"|*") -> 119 | G13: =COUNTIF('Novas federais'!$R:$R,"*|"&$A13&"|*") -> 30 | H13: =SUM(E13:G13) -> 153 | I13: 13
B14: Total de vínculos eixo-matéria | E14: =SUM(E2:E13) -> 77 | F14: =SUM(F2:F13) -> 346 | G14: =SUM(G2:G13) -> 125 | H14: =SUM(H2:H13) -> 548
B16: Uma matéria pode integrar mais de um eixo; por isso a soma de vínculos supera o total de matérias selecionadas.

Sheet Assembleias
A1: Identificador | B1: Casa legislativa | C1: Tipo | D1: Autoria | E1: Partido | F1: UF | G1: Ano | H1: Data | I1: Eixo principal | J1: Eixos | K1: Prioridade | L1: Aderência | M1: Categoria | N1: Motivo do interesse para o CFTA | O1: Ação sugerida | P1: Base de origem | Q1: Ementa | R1: Chave
A2: IND 16341/2026 | B2: ALERO (RO) | C2: Indicação | D2: Cláudia de Jesus | G2: 2026 | I2: E2 | J2: E2, E1 | K2: Muito alta | L2: 42 | M2: Assistência técnica, extensão e carreira pública | N2: Afeta assistência técnica, extensão rural, formação técnica ou estrutura de carreira ligada ao setor agropecuário. | O2: Monitorar tramitação e avaliar posicionamento institucional. | P2: Consolidada · abr/2026 | Q2: INDICA ao Poder Executivo Estadual, extensivo à Casa Civil e à Entidade Autárquica de Assistência Técnica e Extensão Rural do Estado de Rondônia — EMATER, a necessidade de disponibilização de técnico agrícola ou agrônomo para o município de Pimenteiras do Oeste/RO. | R2: |E2|E1|
A3: IND 5620/2026 | B3: ALES (ES) | C3: Indicação | D3: João Coser | G3: 2026 | H3: 2026-03-30 | I3: E2 | J3: E2, E1, E12 | K3: Muito alta | L3: 42 | M3: Assistência técnica, extensão e carreira pública | N3: Afeta assistência técnica, extensão rural, formação técnica ou estrutura de carreira ligada ao setor agropecuário. | O3: Monitorar tramitação e avaliar posicionamento institucional. | P3: Consolidada · abr/2026 | Q3: O Deputado João Coser requer seja encaminhada ao Governador do Estado do Espírito Santo a seguinte Indicação Parlamentar: "Considerando as propostas de recomposição salarial de carreira no âmbito do Instituto Capixaba de Pesquisa, Assistência Técnica e Extensão Rural (Incaper) e da Secretaria de Estado de Gestão e Recursos Humanos (Seger), solicita-se: (i) Seja assegurada a manutenção da equiparação remuneratória dos servidores integrantes da carreira de Técnico de Suporte em Desenvolvimento Rural em relação aos Técnicos em Desenvolvimento Rural (técnicos em agropecuária); (ii) Alternativamente, seja analisada, de forma concreta, a possibilidade de enquadramento da carreira de Técnico de Suporte em Desenvolvimento Rural na carreira de Técnico em Desenvolvimento Rural, como medida de justiça funcional e de garantia de tratamento isonômico entre servidores que exercem funções de natureza equivalente". | R3: |E2|E1|E12|
A4: RQN 16855/2026 | B4: ALEMG (MG) | C4: Requerimento | D4: Comissão de Cultura | G4: 2026 | H4: 2026-03-24 | I4: E2 | J4: E2, E5, E12 | K4: Muito alta | L4: 40 | M4: Assistência técnica, extensão e carreira pública | N4: Afeta assistência técnica, extensão rural, formação técnica ou estrutura de carreira ligada ao setor agropecuário. | O4: Monitorar tramitação e avaliar posicionamento institucional. | P4: Consolidada · abr/2026 | Q4: Requer seja encaminhado à Empresa de Assistência Técnica e Extensão Rural do Estado de Minas Gerais, ao Instituto Mineiro de Agropecuária e ao Ministério da Agricultura e Pecuária pedido de providências para que, em parceria, realizem pesquisa para mapeamento da produção e dos produtores de cachaça artesanal nas comunidades quilombolas do Estado, com vistas ao desenvolvimento de políticas de proteção e certificação específicas para esse público. | R4: |E2|E5|E12|
A5: IND 15020/2026 | B5: ALEPE (PE) | C5: Indicação | D5: Romero Sales Filho | G5: 2026 | H5: 2026-02-03 | I5: E2 | J5: E2, E6, E12 | K5: Muito alta | L5: 37 | M5: Assistência técnica, extensão e carreira pública | N5: Afeta assistência técnica, extensão rural, formação técnica ou estrutura de carreira ligada ao setor agropecuário. | O5: Monitorar tramitação e avaliar posicionamento institucional. | P5: Consolidada · abr/2026 | Q5: Indicamos à Mesa, ouvido o Plenário e cumpridas as formalidades regimentais, que seja encaminhado apelo à Excelentíssima Senhora Raquel Lyra, Governadora do Estado de Pernambuco; ao Ilustríssimo Sr. Cícero Moraes Secretário de Desenvolvimento Agrário, Agricultura, Pecuária e Pesca; e ao Ilustríssimo Sr. Miguel Duque, Presidente Instituto Agronômico de Pernambuco (IPA), no sentido de viabilizar a inclusão do município de São José da Coroa Grande nos programas e ações previstas pelo órgão para o biênio 2025–2026, a saber: o Programa Terra Plantar; a Recuperação de Estradas Vicinais; o fortalecimento da estrutura da Prestação de Serviço de Assistência Técnica e Extensão Rural – ATER; e o Programa de Distribuição de Sementes – Safra 2025. | R5: |E2|E6|E12|
A6: IND 15485/2026 | B6: ALERO (RO) | C6: Indicação | D6: Cláudia de Jesus | G6: 2026 | I6: E2 | J6: E2, E5 | K6: Muito alta | L6: 37 | M6: Assistência técnica, extensão e carreira pública | N6: Afeta assistência técnica, extensão rural, formação técnica ou estrutura de carreira ligada ao setor agropecuário. | O6: Monitorar tramitação e avaliar posicionamento institucional. | P6: Consolidada · abr/2026 | Q6: INDICA ao Poder Executivo Estadual, extensivo à Casa Civil, à Secretaria de Estado da Agricultura – SEAGRI, ao Conselho de Desenvolvimento do Agronegócio Leite do Estado de Rondônia – CONDALRON, à Secretaria de Estado do Desenvolvimento Econômico – SEDEC e à Entidade Autárquica de Assistência Técnica e Extensão Rural do Estado de Rondônia – EMATER, a necessidade de adoção de providências para que, nas compras governamentais de leite e de derivados lácteos, seja priorizado o fornecimento por agroindústrias e cooperativas sediadas no Estado de Rondônia. | R6: |E2|E5|
A7: REQ 2428/2026 | B7: ALRN (RN) | C7: REQ | D7: DEPUTADA DIVANEIDE BASÍLIO | G7: 2026 | H7: 15/07/2026 | I7: E2 | J7: E2, E12 | K7: Muito alta | L7: 33 | P7: Varredura · ago/2026 | Q7: requer que seja encaminhado expediente à Secretaria de Estado do Desenvolvimento Rural e da Agricultura Familiar - SEDRAF, à Empresa de Assistência Técnica e Extensão Rural do Rio Grande do Norte - EMATER-RN, à Empresa de Pesquisa Agropecuária do Rio Grande do Norte - EMPARN e ao Instituto de Desenvolvimento Sustentável e Meio Ambiente do Rio Grande do Norte - IDEMA, solicitando o fortalecimento das iniciativas de bioeconomia e da cadeia produtiva das plantas medicinais. | R7: |E2|E12|
A8: IND 4799/2026 | B8: ALES (ES) | C8: Indicação | D8: Zé Preto | G8: 2026 | H8: 2026-03-25 | I8: E5 | J8: E5, E12, E11, E2 | K8: Alta | L8: 32 | M8: Crédito rural, seguro e financiamento | N8: Pode alterar instrumentos de crédito ou financiamento relevantes para produtores rurais e para a assistência técnica. | O8: Monitorar tramitação e mapear impacto para produtores e assistência técnica. | P8: Consolidada · abr/2026 | Q8: Indico, por intermédio da Secretaria de Estado da Agricultura, Abastecimento, Aquicultura e Pesca – SEAG, e dos demais órgãos competentes, a adoção de providências para a criação e estruturação de um Fundo Estadual de Apoio à Agricultura Familiar, destinado ao fortalecimento da produção rural, ao incentivo à agroindustrialização, à ampliação da comercialização dos produtos da agricultura familiar e ao desenvolvimento sustentável do meio rural no Estado do Espírito Santo. | R8: |E5|E12|E11|E2|
A9: IND 4800/2026 | B9: ALES (ES) | C9: Indicação | D9: Zé Preto | G9: 2026 | H9: 2026-03-25 | I9: E5 | J9: E5, E12, E11, E2 | K9: Médio-alta | L9: 32 | M9: Produção agropecuária e cadeias produtivas | N9: Incide sobre produção agropecuária, cadeias produtivas ou atividades de interesse direto das modalidades registradas no CFTA. | O9: Acompanhar tramitação e classificar impacto setorial para o CFTA. | P9: Consolidada · abr/2026 | Q9: Indico, por intermédio da Secretaria de Estado da Agricultura, Abastecimento, Aquicultura e Pesca – SEAG, e dos demais órgãos competentes, a adoção de providências para a implantação e fortalecimento de ações estaduais de incentivo à agroindústria familiar no Estado do Espírito Santo, com foco na regularização, capacitação, apoio técnico e ampliação da comercialização dos produtos oriundos da agricultura familiar capixaba. | R9: |E5|E12|E11|E2|
A10: IND 4552/2026 | B10: ALES (ES) | C10: Indicação | D10: Zé Preto | G10: 2026 | H10: 2026-03-23 | I10: E5 | J10: E5, E12, E11, E2 | K10: Médio-alta | L10: 32 | M10: Produção agropecuária e cadeias produtivas | N10: Incide sobre produção agropecuária, cadeias produtivas ou atividades de interesse direto das modalidades registradas no CFTA. | O10: Acompanhar tramitação e classificar impacto setorial para o CFTA. | P10: Consolidada · abr/2026 | Q10: Indica por meio da Secretaria de Estado da Agricultura, Abastecimento, Aquicultura e Pesca – SEAG, a implantação de programa estadual de incentivo à agroindustrialização da agricultura familiar no Município de Alfredo Chaves. | R10: |E5|E12|E11|E2|
A11: RQN 16853/2026 | B11: ALEMG (MG) | C11: Requerimento | D11: Comissão de Cultura | G11: 2026 | H11: 2026-03-24 | I11: E2 | J11: E2, E12 | K11: Muito alta | L11: 30 | M11: Assistência técnica, extensão e carreira pública | N11: Afeta assistência técnica, extensão rural, formação técnica ou estrutura de carreira ligada ao setor agropecuário. | O11: Monitorar tramitação e avaliar posicionamento institucional. | P11: Consolidada · abr/2026 | Q11: Requer seja encaminhado à Empresa de Assistência Técnica e Extensão Rural do Estado de Minas Gerais e ao Instituto Mineiro de Agropecuária pedido de providências para a criação de canal de comunicação específico para atendimento de produtores de cachaça de comunidades quilombolas, respeitando-se a cultura e os saberes tradicionais dessas comunidades. | R11: |E2|E12|
A12: RQN 16854/2026 | B12: ALEMG (MG) | C12: Requerimento | D12: Comissão de Cultura | G12: 2026 | H12: 2026-03-24 | I12: E2 | J12: E2, E12 | K12: Muito alta | L12: 30 | M12: Assistência técnica, extensão e carreira pública | N12: Afeta assistência técnica, extensão rural, formação técnica ou estrutura de carreira ligada ao setor agropecuário. | O12: Monitorar tramitação e avaliar posicionamento institucional. | P12: Consolidada · abr/2026 | Q12: Requer seja encaminhado à Empresa de Assistência Técnica e Extensão Rural do Estado de Minas Gerais e ao Instituto Mineiro de Agropecuária pedido de providências para a criação de campanhas de divulgação dos serviços de apoio técnico ofertados por essas entidades aos fabricantes de cachaça e outros produtos artesanais das comunidades quilombolas e indígenas e de outras comunidades tradicionais. | R12: |E2|E12|
A13: IND 16623/2026 | B13: ALEPE (PE) | C13: IND | D13: Nino de Enoque | E13: PL | F13: PE | G13: 2026 | H13: 04/08/2026 | I13: E6 | J13: E6, E7, E12 | K13: Muito alta | L13: 30 | P13: Varredura · ago/2026 | Q13: Indicamos à Mesa, ouvido o Plenário e cumpridas as formalidades regimentais, que seja feito um apelo à Excelentíssima Senhora Governadora do Estado de Pernambuco, Raquel Teixeira Lyra Lucena, e ao Excelentíssimo Senhor Secretário de Desenvolvimento Agrário, Agricultura, Pecuária e Pesca de Pernambuco, Cícero Vicente Marinho Xavier de Moraes, para que sejam adotadas as providências necessárias à regularização fundiária das áreas ocupadas pelas famílias assentadas e ao apoio à estruturação de banco de sementes comunitário, em benefício das comunidades rurais do município de Pesqueira – PE | R13: |E6|E7|E12|
A14: REQ 27591/2026 | B14: ALPB (PB) | C14: Requerimento | D14: — | G14: 2026 | I14: E2 | J14: E2, E7, E12 | K14: Muito alta | L14: 30 | M14: Assistência técnica, extensão e carreira pública | N14: Afeta assistência técnica, extensão rural, formação técnica ou estrutura de carreira ligada ao setor agropecuário. | O14: Monitorar tramitação e avaliar posicionamento institucional. | P14: Consolidada · abr/2026 | Q14: REQUEIRO que seja encaminhado apelo à Empresa Paraibana de Pesquisa, Extensão Rural e Regularização Fundiária – EMPAER, à Secretaria de Estado do Desenvolvimento da Agropecuária e da Pesca da Paraíba e ao Excelentíssimo Senhor Governador do Estado da Paraíba, solicitando a ampliação da assistência técnica rural com foco na agroecologia nos municípios do Brejo Paraibano. | R14: |E2|E7|E12|
A15: IND 15337/2026 | B15: ALERO (RO) | C15: Indicação | D15: Cláudia de Jesus | G15: 2026 | I15: E2 | J15: E2 | K15: Muito alta | L15: 28 | M15: Assistência técnica, extensão e carreira pública | N15: Afeta assistência técnica, extensão rural, formação técnica ou estrutura de carreira ligada ao setor agropecuário. | O15: Monitorar tramitação e avaliar posicionamento institucional. | P15: Consolidada · abr/2026 | Q15: INDICA ao Poder Executivo do Estado de Rondônia, com cópias à Casa Civil, à Secretaria de Estado da Agricultura – SEAGRI e à Entidade Autárquica de Assistência Técnica e Extensão Rural do Estado de Rondônia – EMATER-RO, a necessidade de adoção de providências administrativas visando à contratação ou disponibilização de especialista em produção de cacau, com atuação direcionada às propriedades da agricultura familiar do município de Candeias do Jamari, bem como à orientação técnica para prevenção, monitoramento e manejo da monilíase do cacaueiro.. | R15: |E2|
A16: IND 15484/2026 | B16: ALERO (RO) | C16: Indicação | D16: Cláudia de Jesus | G16: 2026 | I16: E2 | J16: E2 | K16: Muito alta | L16: 25 | M16: Assistência técnica, extensão e carreira pública | N16: Afeta assistência técnica, extensão rural, formação técnica ou estrutura de carreira ligada ao setor agropecuário. | O16: Monitorar tramitação e avaliar posicionamento institucional. | P16: Consolidada · abr/2026 | Q16: INDICA ao Poder Executivo Estadual, extensivo à Casa Civil, à Secretaria de Estado da Agricultura – SEAGRI, ao Conselho de Desenvolvimento do Agronegócio Leite do Estado de Rondônia – CONDALRON, à Secretaria de Estado do Desenvolvimento Econômico – SEDEC, à Secretaria de Estado de Finanças – SEFIN, à Procuradoria-Geral do Estado de Rondônia – PGE e à Entidade Autárquica de Assistência Técnica e Extensão Rural do Estado de Rondônia – EMATER, a necessidade de adoção, em caráter de máxima urgência, de providências técnicas, administrativas e jurídicas visando à decretação de estado de calamidade pública na cadeia produtiva do leite no Estado de Rondônia, como medida excepcional de proteção econômica, social e produtiva. | R16: |E2|
A17: IND 15649/2026 | B17: ALERO (RO) | C17: Indicação | D17: Pedro Fernandes | G17: 2026 | I17: E2 | J17: E2 | K17: Muito alta | L17: 25 | M17: Assistência técnica, extensão e carreira pública | N17: Afeta assistência técnica, extensão rural, formação técnica ou estrutura de carreira ligada ao setor agropecuário. | O17: Monitorar tramitação e avaliar posicionamento institucional. | P17: Consolidada · abr/2026 | Q17: INDICA ao Poder Executivo Estadual, extensivo à Secretaria de Estado da Agricultura — SEAGRI, ao Conselho de Desenvolvimento do Agronegócio Leite do Estado de Rondônia — CONDALRON, à Secretaria de Estado do Desenvolvimento Econômico — SEDEC, à Secretaria de Estado de Finanças — SEFIN, e à Entidade Autárquica de Assistência Técnica e Extensão Rural do Estado de Rondônia — EMATER, a necessidade urgente de decretação de Estado de Calamidade Pública Estadual na cadeia produtiva do leite no Estado de Rondônia, em razão do baixo preço do leite pago aos produtores. | R17: |E2|
A18: REQ 3547/2026 | B18: ALERO (RO) | C18: Requerimento | D18: Coletiva | G18: 2026 | I18: E2 | J18: E2 | K18: Muito alta | L18: 25 | M18: Assistência técnica, extensão e carreira pública | N18: Afeta assistência técnica, extensão rural, formação técnica ou estrutura de carreira ligada ao setor agropecuário. | O18: Monitorar tramitação e avaliar posicionamento institucional. | P18: Consolidada · abr/2026 | Q18: Requer ao Poder Executivo Estadual, extensivo à Casa Civil, à Secretaria de Estado da Agricultura - SEAGRI, ao Conselho de Desenvolvimento do Agronegócio Leite do Estado de Rondônia - CONDALRON, à Secretaria de Estado do Desenvolvimento Econômico - SEDEC, à Secretaria de Estado de Finanças - SEFIN, à Procuradoria-Geral do Estado de Rondônia - PGE e à Entidade Autárquica de Assistência Técnica e Extensão Rural do Estado de Rondônia - EMATER, que adotem, em caráter de máxima urgência, as providências técnicas, administrativas e jurídicas necessárias à decretação de estado de calamidade pública na cadeia produtiva do leite no Estado de Rondônia, como medida excepcional de proteção econômica, social e produtiva. | R18: |E2|
A19: REQ 28020/2026 | B19: ALPB (PB) | C19: Requerimento | D19: — | G19: 2026 | I19: E11 | J19: E11, E2, E12 | K19: Muito alta | L19: 25 | M19: Crédito rural, seguro e financiamento | N19: Pode alterar instrumentos de crédito ou financiamento relevantes para produtores rurais e para a assistência técnica. | O19: Monitorar tramitação e mapear impacto para produtores e assistência técnica. | P19: Consolidada · abr/2026 | Q19: Requeiro, na forma regimental e após ouvido o Plenário, que seja encaminhado expediente ao Governador do Estado da Paraíba, Excelentíssimo Senhor João Azevêdo Lins, bem como à Secretaria de Estado do Desenvolvimento da Agropecuária e da Pesca, solicitando a ampliação de programas de incentivo à agricultura familiar, garantindo assistência técnica, acesso ao crédito rural, apoio logístico e políticas de comercialização da produção agrícola. | R19: |E11|E2|E12|
A20: PL 70/2026 | B20: ALEAM (AM) | C20: Projeto de lei | D20: Cristiano D’Angelo | G20: 2026 | I20: E3 | J20: E3, E4 | K20: Média | L20: 24 | M20: Agrotóxicos, fiscalização e biossegurança | N20: Relaciona-se à fiscalização, biossegurança, fitossanidade e execução técnica em ambiente regulado. | O20: Priorizar monitoramento e avaliar nota técnica regulatória. | P20: Consolidada · abr/2026 | Q20: REVOGA a LEI Nº 6.173, DE 29 DE DEZEMBRO DE 2022 que dispõe sobre as Taxas dos Serviços de Defesa Animal e Vegetal, Inspeção Animal, Agrotóxicos, Insumos Veterinários, Organismos Aquáticos, Taxa de Defesa Animal, Taxa de Defesa Sanitária e Taxa de Indenização, no Estado do Amazonas, e dá outras providências. | R20: |E3|E4|
A21: REQ 218/2026 | B21: ALMT (MT) | C21: Requerimento | D21: Gilberto Cattani | G21: 2026 | I21: E3 | J21: E3, E12 | K21: Muito alta | L21: 23 | M21: Agrotóxicos, fiscalização e biossegurança | N21: Relaciona-se à fiscalização, biossegurança, fitossanidade e execução técnica em ambiente regulado. | O21: Priorizar monitoramento e avaliar nota técnica regulatória. | P21: Consolidada · abr/2026 | Q21: REQUER AO PRESIDENTE DO INSTITUTO DE DEFESA AGROPECUÁRIA DO ESTADO DE MATO GROSSO – INDEA/MT INFORMAÇÕES E DOCUMENTOS ACERCA DA APURAÇÃO DE DENÚNCIA DE SUPOSTO ABATE CLANDESTINO DE OVINOS COM COMERCIALIZAÇÃO NO MUNICÍPIO DE LUCAS DO RIO VERDE - MT. | R21: |E3|E12|
A22: IND 756/2026 | B22: ALEAC (AC) | C22: IND | D22: Afonso Fernandes | E22: SD | F22: AC | G22: 2026 | H22: 04/08/2026 | I22: E3 | J22: E3, E12 | K22: Alta | L22: 17 | P22: Varredura · ago/2026 | Q22: Indico à Mesa Diretora, com fulcro no art. 169 da Resolução nº 86/1990, Regimento Interno da Assembleia Legislativa do Estado do Acre, que seja encaminhado expediente à Excelentíssima Senhora Mailza Assis Cameli, Governadora do Estado do Acre, com cópia à Secretaria de Estado de Agricultura - SEAGRI, à Secretaria de Estado de Planejamento - SEPLAN e ao Instituto de Defesa Agropecuária e Florestal do Acre - IDAF/AC, solicitando a realização de estudo de viabilidade e a estruturação do Projeto-Piloto Frio a Bordo, destinado a testar soluções de conservação pós-captura do pescado artesanal entre a captura e o desembarque, com eventual execução material a partir do exercício de 2027, observadas as exigências técnicas, sanitárias, ambientais, jurídicas, orçamentárias, eleitorais e de segurança da navegação. | R22: |E3|E12|
A23: IND 16427/2026 | B23: ALERO (RO) | C23: Indicação | D23: CIRONE DEIRÓ, ALEX REDANO | G23: 2026 | I23: E3 | J23: E3, E12 | K23: Muito alta | L23: 17 | M23: Agrotóxicos, fiscalização e biossegurança | N23: Relaciona-se à fiscalização, biossegurança, fitossanidade e execução técnica em ambiente regulado. | O23: Priorizar monitoramento e avaliar nota técnica regulatória. | P23: Consolidada · abr/2026 | Q23: INDICA ao Poder Executivo do Estado de Rondônia, com cópias à Casa Civil e a Agência de Defesa Sanitária Agrosilvopastoril do Estado de Rondônia - IDARON a adoção de providências visando à alteração da Lei Complementar Estadual nº 665, de 21 de maio de 2012, para adequação da sistemática de cálculo do Adicional de Desempenho da Defesa Agropecuária. | R23: |E3|E12|
A24: MGOV 27/2026 | B24: ALERR (RR) | C24: Proposição | D24: — | G24: 2026 | I24: E3 | J24: E3, E12 | K24: Muito alta | L24: 17 | M24: Agrotóxicos, fiscalização e biossegurança | N24: Relaciona-se à fiscalização, biossegurança, fitossanidade e execução técnica em ambiente regulado. | O24: Priorizar monitoramento e avaliar nota técnica regulatória. | P24: Consolidada · abr/2026 | Q24: Encaminha Projeto de Lei que "Altera a Lei nº 644, de 8 de abril de 2008, que dispõe sobre a criação da Agência de Defesa Agropecuária, e dá outras providências". | R24: |E3|E12|
A25: PL 58/2026 | B25: ALERR (RR) | C25: Projeto de lei | D25: — | G25: 2026 | I25: E3 | J25: E3, E12 | K25: Muito alta | L25: 17 | M25: Agrotóxicos, fiscalização e biossegurança | N25: Relaciona-se à fiscalização, biossegurança, fitossanidade e execução técnica em ambiente regulado. | O25: Priorizar monitoramento e avaliar nota técnica regulatória. | P25: Consolidada · abr/2026 | Q25: Altera a Lei nº 644, de 8 de abril de 2008 que dispõe sobre a criação da Agência de Defesa Agropecuária, e dá outras providências. | R25: |E3|E12|
A26: ORAC 17547/2026 | B26: ALES (ES) | C26: ORAC | D26: Adilson Espindula | E26: PP | F26: ES | G26: 2026 | H26: 04/08/2026 | I26: E12 | J26: E12, E11 | K26: Alta | L26: 17 | P26: Varredura · ago/2026 | Q26: Encaminho, na forma do art. 67, XVI do Regimento Interno desta Casa de Leis, o Relatório Mensal dos trabalhos da Comissão de Agricultura, de Silvicultura, de Aquicultura e Pesca, de Abastecimento, e de Reforma Agrária, referente o mês de JULHO/2026. | R26: |E12|E11|
A27: IND 17323/2026 | B27: ALES (ES) | C27: IND | D27: Adilson Espindula | E27: PP | F27: ES | G27: 2026 | H27: 03/08/2026 | I27: E12 | J27: E12, E11 | K27: Alta | L27: 17 | P27: Varredura · ago/2026 | Q27: I N D I C A Ç Ã O, para solicitar ao Governo do Estado do Espírito Santo, por meio da Secretaria de Estado da Agricultura, Abastecimento, Aquicultura e Pesca – SEAG, a realização de estudos técnicos e a execução das obras de duplicação da Estrada Rodolfo Nicolau Douro, no Município de Marechal Floriano/ES. | R27: |E12|E11|
A28: IND 17273/2026 | B28: ALES (ES) | C28: IND | D28: Coronel Weliton | E28: DC | F28: ES | G28: 2026 | H28: 30/07/2026 | I28: E12 | J28: E12, E11 | K28: Alta | L28: 17 | P28: Varredura · ago/2026 | Q28: O Deputado abaixo assinado, no uso de suas atribuições legais e regimentais, requer a Vossa Excelência, com fundamento nos artigos 141, inciso VIII e 174 do Regimento Interno da Assembleia Legislativa do Estado do Espírito Santo, que seja encaminhada ao EXCELENTÍSSIMO SENHOR GOVERNADOR DO ESTADO DO ESPÍRITO SANTO, por intermédio da Secretaria de Estado da Agricultura, Abastecimento, Aquicultura e Pesca, a INDICAÇÃO PARLAMENTAR da seguinte matéria: PAVIMENTAÇÃO COM BLOCOS INTERTRAVADOS OU APLICAÇÃO DE REVSOL NAS MARGENS DA RODOVIA (ES-185) EM FRENTE AOS EMPREENDIMENTOS DE GALPÕES, SITUADOS NA SAÍDA DA CIDADE DE IBITIRAMA/ES EM DIREÇÃO Á COMUNIDADE DE SÃO FRANCISCO. | R28: |E12|E11|
A29: REQ 130/2026 | B29: ALETO (TO) | C29: Requerimento | D29: WISTON GOMES | G29: 2026 | H29: 2026-02-24 | I29: E3 | J29: E3, E12 | K29: Muito alta | L29: 17 | M29: Agrotóxicos, fiscalização e biossegurança | N29: Relaciona-se à fiscalização, biossegurança, fitossanidade e execução técnica em ambiente regulado. | O29: Priorizar monitoramento e avaliar nota técnica regulatória. | P29: Consolidada · abr/2026 | Q29: Requer o envio de expediente ao Senhor Governador do Estado do Tocantins, com cópia à Agência de Defesa Agropecuária – ADAPEC para solicitar a Reforma do prédio onde funciona a Barreira fixa da ADAPEC no município de Pau D’arco. | R29: |E3|E12|
A30: REQ 28367/2026 | B30: ALPB (PB) | C30: Requerimento | D30: — | G30: 2026 | I30: E3 | J30: E3, E12 | K30: Muito alta | L30: 17 | M30: Agrotóxicos, fiscalização e biossegurança | N30: Relaciona-se à fiscalização, biossegurança, fitossanidade e execução técnica em ambiente regulado. | O30: Priorizar monitoramento e avaliar nota técnica regulatória. | P30: Consolidada · abr/2026 | Q30: Requerimento e apelo ao Excelentíssimo Senhor Governador do Estado da Paraíba, com cópia à Secretaria de Estado do Desenvolvimento da Agropecuária e da Pesca- SEDAP, à Secretaria de Estado da Administração e à Casa Civil, solicitando o enquadramento no quadro funcional da SEDAP, dos médicos veterinários aprovados no Concurso Público regido pelo Edital nº 02/2006- CPS/SEAD, bem como daqueles admitidos antes da Constituição Federal de 1988, além da inclusão desses profissionais nos Projetos de Lei encaminhados a esta Casa Legislativa que tratam da criação da Agência de Defesa Agropecuária do Estado da Paraíba (ADAP-PB) e da instituição do Plano de Cargos, Carreira e Remuneração da área. | R30: |E3|E12|
A31: IND 15738/2026 | B31: ALEPE (PE) | C31: Indicação | D31: Álvaro Porto | G31: 2026 | H31: 2026-03-19 | I31: E6 | J31: E6, E12, E2 | K31: Alta | L31: 15 | M31: Produção agropecuária e cadeias produtivas | N31: Incide sobre produção agropecuária, cadeias produtivas ou atividades de interesse direto das modalidades registradas no CFTA. | O31: Acompanhar tramitação e classificar impacto setorial para o CFTA. | P31: Consolidada · abr/2026 | Q31: Indicamos à Mesa, ouvido o Plenário e cumpridas as formalidades regimentais, que seja enviado um veemente apelo à Excelentíssima Sra. Governadora do Estado de Pernambuco, Raquel Lyra, ao Excelentíssimo Sr. Secretário de Desenvolvimento Agrário, Agricultura, Pecuária e Pesca do Estado de Pernambuco, Cícero Moraes, e ao Ilustríssimo Sr. Presidente do Instituto de Pesquisas Agronômicas de Pernambuco, Miguel Duque, no sentido de promoverem a distribuição de sementes aos agricultores da agricultura familiar do Município de Vertentes. | R31: |E6|E12|E2|
A32: IND 14981/2026 | B32: ALEPE (PE) | C32: Indicação | D32: Romero Sales Filho | G32: 2026 | H32: 2026-02-03 | I32: E6 | J32: E6, E12, E2 | K32: Alta | L32: 15 | M32: Produção agropecuária e cadeias produtivas | N32: Incide sobre produção agropecuária, cadeias produtivas ou atividades de interesse direto das modalidades registradas no CFTA. | O32: Acompanhar tramitação e classificar impacto setorial para o CFTA. | P32: Consolidada · abr/2026 | Q32: Indicamos à Mesa, ouvido o Plenário e cumpridas as formalidades regimentais, que seja encaminhado apelo à Excelentíssima Senhora Raquel Lyra, Governadora do Estado de Pernambuco, ao Ilustríssimo Senhor Cícero Moraes, Secretário de Desenvolvimento Agrário, Agricultura, Pecuária e Pesca do Estado de Pernambuco, e ao Ilustríssimo Senhor Miguel Arcanjo Ferraz Duque, Diretor-Presidente do Instituto Agronômico de Pernambuco – IPA, no sentido de viabilizar a aquisição de sementes para compor o Banco Municipal de Sementes da Agricultura Familiar no município de Tamandaré, por meio do Programa Sementes Crioulas. | R32: |E6|E12|E2|
A33: REQ 4816/2026 | B33: ALEPE (PE) | C33: Requerimento | D33: Romero Albuquerque | G33: 2026 | H33: 2026-03-03 | I33: E8 | J33: E8 | K33: Médio-alta | L33: 15 | M33: Produção agropecuária e cadeias produtivas | N33: Incide sobre produção agropecuária, cadeias produtivas ou atividades de interesse direto das modalidades registradas no CFTA. | O33: Acompanhar tramitação e classificar impacto setorial para o CFTA. | P33: Consolidada · abr/2026 | Q33: Requeremos à Mesa, nos termos do art. 246, inciso I, c/c art. 244, §1º, ambos da Resolução nº 1.891/2023 (Regimento Interno da Assembleia Legislativa do Estado de Pernambuco), que seja encaminhado Pedido de Informações ao Exmo. Sr. Túlio Frederico Tenório Vilaça Rodrigues, Secretário da Casa Civil do Estado de Pernambuco, acerca da implantação de plantas de produção de hidrogênio verde (H2V) e seus derivados, como o e-metanol, no âmbito do Complexo Industrial Portuário de Suape e da recém-criada Zona de Processamento de Exportação (ZPE). I – INFORMAÇÕES GERAIS SOBRE OS PROJETOS Considerando as informações públicas sobre a existência de, pelo menos, dois projetos em curso (European Energy e GoVerde Holding) , solicitamos: Relação completa e formal de todos os projetos de produção de hidrogênio verde (H2V) e derivados (como e-metanol e combustível sustentável de aviação - SAF) que estejam em qualquer estágio de negociação, aprovação ou implantação no âmbito do Complexo de Suape e/ou da ZPE. Para cada um dos projetos identificados (incluindo, mas não se limitando, aos da European Energy e GoVerde Holding), especificar: 2.1. Nome da empresa ou consórcio responsável e seu controle societário. 2.2. Estágio atual do projeto (protocolo de intenções, contrato de arrendamento assinado, licenciamento prévio obtido, licença de instalação, obras iniciadas, operação). 2.3. Produto final a ser gerado (ex: hidrogênio verde, e-metanol, SAF) e capacidade produtiva estimada (em toneladas/ano ou m³/dia). 2.4. Valor total do investimento previsto por projeto e a origem dos capitais (nacional/estrangeiro). 2.5. Área (em hectares) concedida para cada empreendimento e valor do contrato de arrendamento. 2.6. Cronograma atualizado com prazo estimado para início das obras e para o início da operação comercial (considerando as projeções para 2026, 2027 e 2028) . II – INCENTIVOS, CONTRAPARTIDAS E INFRAESTRUTURA DO CLUSTER Tendo em vista a criação do "Cluster Suape para Combustíveis de Baixo Carbono" e os investimentos previstos em infraestrutura compartilhada , questionamos: Detalhar todos os incentivos fiscais, creditícios, fundiários ou de infraestrutura concedidos ou em negociação para viabilizar os empreendimentos de H2V, especificando por projeto: 3.1. Tipo de incentivo concedido. 3.2. Base legal que autoriza a concessão do benefício. 3.3. Valor estimado do benefício fiscal ou financeiro, quando aplicável. 3.4. Prazo de vigência dos incentivos. 3.5. Contrapartidas exigidas das empresas (geração de empregos, investimentos mínimos, índice de conteúdo local, metas ambientais e de descarbonização). Informar se os projetos estão vinculados aos benefícios da Zona de Processamento de Exportação (ZPE) de Suape e quais as vantagens competitivas específicas oferecidas por este regime . Detalhar o plano de investimentos públicos e compartilhados para a estruturação do "Cluster Suape", no valor estimado de R$ 1,2 bilhão , incluindo: 5.1. Cronograma físico-financeiro das obras de infraestrutura (rede de dutos, tancagens, adequações portuárias, sistemas energéticos e hídricos). 5.2. Fontes dos recursos (estaduais, federais, parcerias público-privadas) e a parcela a ser custeada pelo setor privado. 5.3. Modelo de gestão e acesso compartilhado a essa infraestrutura pelas empresas do cluster. III – LICENCIAMENTO E IMPACTO AMBIENTAL Considerando a Licença Prévia (LP) já emitida para um dos empreendimentos , solicitamos: Para cada projeto em andamento, informar: 6.1. Situação atual do licenciamento ambiental (Licença Prévia - LP, Licença de Instalação - LI, ou Licença de Operação - LO). 6.2. Órgão responsável pelo licenciamento (CPRH ou IBAMA). 6.3. Exigência e, em caso positivo, existência de Estudo de Impacto Ambiental e Relatório de Impacto ao Meio Ambiente (EIA/RIMA) para cada planta. 6.4. Medidas de mitigação e compensação ambiental previstas, inclusive as relacionadas à captação de água e emissões. 6.5. Demanda estimada de recursos hídricos (consumo de água) e a matriz energética que será utilizada para a produção de hidrogênio verde, assegurando sua efetiva origem renovável. Informar se há uma avaliação ambiental estratégica para o cluster como um todo, considerando o efeito cumulativo dos múltiplos empreendimentos na região. IV – FINANCIAMENTO, PARCERIAS E INSERÇÃO EM POLÍTICAS PÚBLICAS Considerando as linhas de crédito federais e a agenda de eventos sobre o tema , perguntamos: Informar se há participação ou pleito junto a instituições financeiras públicas ou privadas para financiamento dos projetos, inclusive eventual financiamento do Banco Nacional de Desenvolvimento Econômico e Social (BNDES), Finep, ou de organismos internacionais. Esclarecer se os projetos estão formalmente inseridos na Estratégia Pernambucana para o Hidrogênio Verde e em políticas estruturantes como o Plano Pernambucano de Mudança Econômico-Ecológica (PerMeie) e a Política Estadual de Mudanças Climáticas. Informar sobre parcerias para pesquisa, desenvolvimento e inovação, como o "TecHub de Transição Energética" mencionado em parceria com o SENAI-PE, detalhando seu estágio de implementação e fontes de financiamento . V – IMPACTO SOCIOECONÔMICO E MÃO DE OBRA Para o conjunto dos projetos do cluster, informar a estimativa atualizada: 11.1. Número de empregos diretos e indiretos a serem gerados, discriminados por fase (implantação e operação). 11.2. Programas de capacitação e qualificação de mão de obra local vinculados aos projetos, com públicos-alvo e parcerias (ex: com o SENAI, IPA e universidades estaduais - UPE, UFRPE) . 11.3. Impacto estimado na arrecadação estadual e municipal (ICMS, ISS, etc.) com a maturação dos projetos, contrapondo com os incentivos fiscais eventualmente concedidos. | R33: |E8|
A34: IND 590/2026 | B34: ALMT (MT) | C34: Indicação | D34: Chico Guarnieri | G34: 2026 | I34: E6 | J34: E6, E12, E2 | K34: Alta | L34: 15 | M34: Produção agropecuária e cadeias produtivas | N34: Incide sobre produção agropecuária, cadeias produtivas ou atividades de interesse direto das modalidades registradas no CFTA. | O34: Acompanhar tramitação e classificar impacto setorial para o CFTA. | P34: Consolidada · abr/2026 | Q34: INDICO AO EXCELENTÍSSIMO SENHOR GOVERNADOR DO ESTADO, COM CÓPIA À SECRETARIA DE ESTADO DE AGRICULTURA FAMILIAR DE MATO GROSSO – SEAF/MT, A NECESSIDADE DE DESTINAÇÃO DE RECURSOS PARA A CONSTRUÇÃO DE UM BARRACÃO EQUIPADO COM CÂMARA FRIA PARA ARMAZENAMENTO E ESTOCAGEM DE SEMENTES, DESTINADO À COOPERATIVA AGROPECUÁRIA DO POVO INDÍGENA (COOPIPARÉSI), NO MUNICÍPIO DE CAMPO NOVO DO PARECIS/MT. | R34: |E6|E12|E2|
A35: REQ 28218/2026 | B35: ALPB (PB) | C35: Requerimento | D35: — | G35: 2026 | I35: E11 | J35: E11, E2 | K35: Muito alta | L35: 15 | M35: Crédito rural, seguro e financiamento | N35: Pode alterar instrumentos de crédito ou financiamento relevantes para produtores rurais e para a assistência técnica. | O35: Monitorar tramitação e mapear impacto para produtores e assistência técnica. | P35: Consolidada · abr/2026 | Q35: Requeiro, na forma regimental, que seja encaminhado APELO ao Governo do Estado da Paraíba, por meio dos órgãos competentes, no sentido de adotar políticas públicas de incentivo à agricultura familiar no município de Camalaú/PB, com a ampliação de programas de apoio técnico, distribuição de insumos agrícolas e acesso a crédito rural. | R35: |E11|E2|
A36: REQ 28369/2026 | B36: ALPB (PB) | C36: Requerimento | D36: — | G36: 2026 | I36: E11 | J36: E11, E2 | K36: Muito alta | L36: 15 | M36: Crédito rural, seguro e financiamento | N36: Pode alterar instrumentos de crédito ou financiamento relevantes para produtores rurais e para a assistência técnica. | O36: Monitorar tramitação e mapear impacto para produtores e assistência técnica. | P36: Consolidada · abr/2026 | Q36: Requeiro, na forma regimental, que seja encaminhado APELO ao Governo do Estado da Paraíba, por meio dos órgãos competentes, no sentido de adotar políticas públicas de incentivo à agricultura familiar no município de Massaranduba/PB, com a ampliação de programas de apoio técnico, distribuição de insumos agrícolas e acesso a crédito rural. | R36: |E11|E2|
A37: REQ 28571/2026 | B37: ALPB (PB) | C37: Requerimento | D37: — | G37: 2026 | I37: E11 | J37: E11, E2 | K37: Muito alta | L37: 15 | M37: Crédito rural, seguro e financiamento | N37: Pode alterar instrumentos de crédito ou financiamento relevantes para produtores rurais e para a assistência técnica. | O37: Monitorar tramitação e mapear impacto para produtores e assistência técnica. | P37: Consolidada · abr/2026 | Q37: Requeiro, na forma regimental, que seja encaminhado APELO ao Governo do Estado da Paraíba, por meio dos órgãos competentes, no sentido de adotar políticas públicas de incentivo à agricultura familiar no município de Ouro Velho/PB, com a ampliação de programas de apoio técnico, distribuição de insumos agrícolas e acesso a crédito rural. | R37: |E11|E2|
A38: REQ 28728/2026 | B38: ALPB (PB) | C38: Requerimento | D38: — | G38: 2026 | I38: E11 | J38: E11, E2 | K38: Muito alta | L38: 15 | M38: Crédito rural, seguro e financiamento | N38: Pode alterar instrumentos de crédito ou financiamento relevantes para produtores rurais e para a assistência técnica. | O38: Monitorar tramitação e mapear impacto para produtores e assistência técnica. | P38: Consolidada · abr/2026 | Q38: Requeiro, na forma regimental, que seja encaminhado APELO ao Governo do Estado da Paraíba, por meio dos órgãos competentes, no sentido de adotar políticas públicas de incentivo à agricultura familiar no município de São Miguel de Taipu/PB, com a ampliação de programas de apoio técnico, distribuição de insumos agrícolas e acesso a crédito rural. | R38: |E11|E2|
A39: REQ 28756/2026 | B39: ALPB (PB) | C39: Requerimento | D39: — | G39: 2026 | I39: E11 | J39: E11, E2 | K39: Muito alta | L39: 15 | M39: Crédito rural, seguro e financiamento | N39: Pode alterar instrumentos de crédito ou financiamento relevantes para produtores rurais e para a assistência técnica. | O39: Monitorar tramitação e mapear impacto para produtores e assistência técnica. | P39: Consolidada · abr/2026 | Q39: Requeiro, na forma regimental, que seja encaminhado APELO ao Governo do Estado da Paraíba, por meio dos órgãos competentes, no sentido de adotar políticas públicas de incentivo à agricultura familiar no município de Alagoa Nova/PB, com a ampliação de programas de apoio técnico, distribuição de insumos agrícolas e acesso a crédito rural. | R39: |E11|E2|
A40: REQ 28073/2026 | B40: ALPB (PB) | C40: Requerimento | D40: — | G40: 2026 | I40: E6 | J40: E6, E12, E2 | K40: Alta | L40: 15 | M40: Produção agropecuária e cadeias produtivas | N40: Incide sobre produção agropecuária, cadeias produtivas ou atividades de interesse direto das modalidades registradas no CFTA. | O40: Acompanhar tramitação e classificar impacto setorial para o CFTA. | P40: Consolidada · abr/2026 | Q40: REQUEIRO, a Vossa Excelência, nos termos do art. 112 do Regimento Interno desta Casa, que seja oficiada manifestação de apelo ao Senhor Rafael Lopes de Oliveira, Secretário Executivo da Agropecuária, para ampliação do programa de distribuição de sementes selecionadas (feijão, milho, sorgo) no Município de Alagoa Grande-PB, como reforço para o pequeno e médio produtor rural da agricultura familiar. | R40: |E6|E12|E2|
A41: REQ 28098/2026 | B41: ALPB (PB) | C41: Requerimento | D41: — | G41: 2026 | I41: E6 | J41: E6, E12, E2 | K41: Alta | L41: 15 | M41: Produção agropecuária e cadeias produtivas | N41: Incide sobre produção agropecuária, cadeias produtivas ou atividades de interesse direto das modalidades registradas no CFTA. | O41: Acompanhar tramitação e classificar impacto setorial para o CFTA. | P41: Consolidada · abr/2026 | Q41: REQUEIRO, a Vossa Excelência, nos termos do art. 112 do Regimento Interno desta Casa, que seja oficiada manifestação de apelo ao Senhor Rafael Lopes de Oliveira, Secretário Executivo da Agropecuária, para ampliação do programa de distribuição de sementes selecionadas (feijão, milho, sorgo) no Município de Lagoa de Roça-PB, como reforço para o pequeno e médio produtor rural da agricultura familiar. | R41: |E6|E12|E2|
A42: REQ 28106/2026 | B42: ALPB (PB) | C42: Requerimento | D42: — | G42: 2026 | I42: E6 | J42: E6, E12, E2 | K42: Alta | L42: 15 | M42: Produção agropecuária e cadeias produtivas | N42: Incide sobre produção agropecuária, cadeias produtivas ou atividades de interesse direto das modalidades registradas no CFTA. | O42: Acompanhar tramitação e classificar impacto setorial para o CFTA. | P42: Consolidada · abr/2026 | Q42: REQUEIRO, a Vossa Excelência, nos termos do art. 112 do Regimento Interno desta Casa, que seja oficiada manifestação de apelo ao Senhor Rafael Lopes de Oliveira, Secretário Executivo da Agropecuária, que o mesmo considere a necessidade de ampliação do programa de distribuição de sementes selecionadas (feijão, milho, sorgo) no Município de Cuité-PB, como forma de garantir o reforço de acesso ao pequeno e médio produtor rural da agricultura familiar. | R42: |E6|E12|E2|
A43: REQ 28258/2026 | B43: ALPB (PB) | C43: Requerimento | D43: — | G43: 2026 | I43: E6 | J43: E6, E12, E2 | K43: Alta | L43: 15 | M43: Produção agropecuária e cadeias produtivas | N43: Incide sobre produção agropecuária, cadeias produtivas ou atividades de interesse direto das modalidades registradas no CFTA. | O43: Acompanhar tramitação e classificar impacto setorial para o CFTA. | P43: Consolidada · abr/2026 | Q43: REQUEIRO, a Vossa Excelência, nos termos do art. 112 do Regimento Interno desta Casa, que seja oficiada manifestação de apelo ao Senhor Rafael Lopes de Oliveira, Secretário Executivo da Agropecuária, para ampliação do programa de distribuição de sementes selecionadas (feijão, milho, sorgo) no Município de Boa Ventura-PB, como reforço para o pequeno e médio produtor rural da agricultura familiar. | R43: |E6|E12|E2|
A44: REQ 28271/2026 | B44: ALPB (PB) | C44: Requerimento | D44: — | G44: 2026 | I44: E6 | J44: E6, E12, E2 | K44: Alta | L44: 15 | M44: Produção agropecuária e cadeias produtivas | N44: Incide sobre produção agropecuária, cadeias produtivas ou atividades de interesse direto das modalidades registradas no CFTA. | O44: Acompanhar tramitação e classificar impacto setorial para o CFTA. | P44: Consolidada · abr/2026 | Q44: REQUEIRO, a Vossa Excelência, nos termos do art. 112 do Regimento Interno desta Casa, que seja oficiada manifestação de apelo ao Senhor Rafael Lopes de Oliveira, Secretário Executivo da Agropecuária, para ampliação do programa de distribuição de sementes selecionadas (feijão, milho, sorgo) no Município de Esperança-PB, como reforço para o pequeno e médio produtor rural da agricultura familiar. | R44: |E6|E12|E2|
A45: REQ 28281/2026 | B45: ALPB (PB) | C45: Requerimento | D45: — | G45: 2026 | I45: E6 | J45: E6, E12, E2 | K45: Alta | L45: 15 | M45: Produção agropecuária e cadeias produtivas | N45: Incide sobre produção agropecuária, cadeias produtivas ou atividades de interesse direto das modalidades registradas no CFTA. | O45: Acompanhar tramitação e classificar impacto setorial para o CFTA. | P45: Consolidada · abr/2026 | Q45: REQUEIRO, a Vossa Excelência, nos termos do art. 112 do Regimento Interno desta Casa, que seja oficiada manifestação de apelo ao Senhor Rafael Lopes de Oliveira, Secretário Executivo da Agropecuária, para ampliação do programa de distribuição de sementes selecionadas (feijão, milho, sorgo) no Município de Barra de São Miguel-PB, como reforço para o pequeno e médio produtor rural da agricultura familiar. | R45: |E6|E12|E2|
... A54: REQ 28883/2026 | B54: ALPB (PB) | C54: Requerimento | D54: — | G54: 2026 | I54: E6 | J54: E6, E12, E2 | K54: Alta | L54: 15 | M54: Produção agropecuária e cadeias produtivas | N54: Incide sobre produção agropecuária, cadeias produtivas ou atividades de interesse direto das modalidades registradas no CFTA. | O54: Acompanhar tramitação e classificar impacto setorial para o CFTA. | P54: Consolidada · abr/2026 | Q54: REQUEIRO, a Vossa Excelência, nos termos do art. 112 do Regimento Interno desta Casa, que seja oficiada manifestação de apelo ao Senhor Rafael Lopes de Oliveira, Secretário Executivo da Agropecuária, que o mesmo considere a necessidade de ampliação do programa de distribuição de sementes selecionadas (feijão, milho, sorgo) no Município de Caiçara-PB, como forma de garantir o reforço de acesso ao pequeno e médio produtor rural da agricultura familiar. | R54: |E6|E12|E2|
A55: IND 320/2026 | B55: ALEMA (MA) | C55: Indicação | D55: JUNIOR FRAN�A | G55: 2026 | H55: 2026-04-09 | I55: E1 | J55: E1, E2 | K55: Alta | L55: 13 | M55: Produção agropecuária e cadeias produtivas | N55: Incide sobre produção agropecuária, cadeias produtivas ou atividades de interesse direto das modalidades registradas no CFTA. | O55: Acompanhar tramitação e classificar impacto setorial para o CFTA. | P55: Consolidada · abr/2026 | Q55: NA FORMA ESTABELECIDA NO REGIMENTO INTERNO DESTA CASA, EM SEU ART. 152, REQUEIRO A V. EXA. QUE, AP�S OUVIDA A MESA, SEJA ENCAMINHADO OF�CIO AO EXCELENT�SSIMO GOVERNADOR, SR. CARLOS ORLEANS BRAND�O J�NIOR, AO EXMO. SECRET�RIO DE ESTADO EXTRAORDIN�RIO DE ASSUNTOS MUNICIPALISTAS (SEAM), SR. ORLEANS BRAND�O, AO EXMO. SECRET�RIO DE ESTADO DE GOVERNO (SEGOV) SR. M�RCIO MACHADO, AO EXMO. SENHOR SECRET�RIO ESTADUAL DA AGRICULTURA, PECU�RIA E PESCA (SAGRIMA), SR. F�BIO GENTIL, AO EXMO. SR. SECRET�RIO DE ESTADO DA AGRICULTURA FAMILIAR (SAF), SR. BIRA DO PINDAR�, � EXMA. PRESIDENTE DA AG�NCIA ESTADUAL DE PESQUISA AGROPECU�RIA E EXTENS�O RURAL (AGERP), SRA. FRAN�A DO MACAQUINHO, SOLICITANDO A DOA��O DE UM TRATOR COM IMPLEMENTOS AGR�COLAS PARA O ASSENTAMENTO DA ASSOCIACAO DE MORADORES DA LOCALIDADE GROSSAR E ARREDORES - CNPJ N.� 02.358.411/0001-89 NO MUNIC�PIO DE S�TIO NOVO, A FIM DE BENEFICIAR V�RIAS FAM�LIAS L� EXISTENTES. JUNIOR FRAN�A Diretoria da Mesa Proposi��o Encaminhada ENCAMINHADA AO DESTINAT�RIO POR E-MAIL PELO SERVIDOR ELI�ZER MONTEIRO EM 09/04/2026. - 09/04/2026 Não há | R55: |E1|E2|
A56: IND 308/2026 | B56: ALEMA (MA) | C56: Indicação | D56: JUNIOR FRAN�A | G56: 2026 | H56: 2026-03-19 | I56: E1 | J56: E1, E2 | K56: Médio-alta | L56: 13 | M56: Produção agropecuária e cadeias produtivas | N56: Incide sobre produção agropecuária, cadeias produtivas ou atividades de interesse direto das modalidades registradas no CFTA. | O56: Acompanhar tramitação e classificar impacto setorial para o CFTA. | P56: Consolidada · abr/2026 | Q56: SENHORA PRESIDENTE: NA FORMA ESTABELECIDA NO REGIMENTO INTERNO DESTA CASA, EM SEU ART. 152, REQUEIRO A V. EXA. QUE, AP�S OUVIDA A MESA, SEJA ENCAMINHADO OF�CIO AO EXCELENT�SSIMO GOVERNADOR, SR. CARLOS ORLEANS BRAND�O J�NIOR, AO EXMO. SECRET�RIO DE ESTADO EXTRAORDIN�RIO DE ASSUNTOS MUNICIPALISTAS (SEAM), SR. ORLEANS BRAND�O, AO EXMO. SECRET�RIO DE ESTADO DE GOVERNO (SEGOV) SR. M�RCIO MACHADO, AO EXMO. SENHOR SECRET�RIO ESTADUAL DA AGRICULTURA, PECU�RIA E PESCA (SAGRIMA), SR. F�BIO GENTIL, AO EXMO. SR. SECRET�RIO DE ESTADO DA AGRICULTURA FAMILIAR (SAF), SR. BIRA DO PINDAR�, � EXMA. PRESIDENTE DA AG�NCIA ESTADUAL DE PESQUISA AGROPECU�RIA E EXTENS�O RURAL (AGERP), SRA. FRAN�A DO MACAQUINHO, SOLICITANDO A DOA��O DE UM TRATOR DE ARADO PARA A ASSOCIACAO DOS MORADORES REMANESCENTES DE QUILOMBO DO POVOADO SANTANINHA DO AGUIAR-AMRQPSA - CNPJ 59.352.457/0001-08 NO MUNIC�PIO DE VIANA, A FIM DE BENEFICIAR V�RIAS FAM�LIAS L� EXISTENTES. JUNIOR FRAN�A Diretoria da Mesa Proposi��o Encaminhada ENCAMINHADO AO DESTINAT�RIO POR E-MAIL PELO SERVIDOR ALEX BRUNO CANELA VILELA - 19/03/2026 Não há | R56: |E1|E2|
A57: RQN 17209/2026 | B57: ALEMG (MG) | C57: Requerimento | D57: Deputado Leleco Pimentel PT | G57: 2026 | H57: 2026-04-13 | I57: E11 | J57: E11, E12, E2 | K57: Médio-alta | L57: 13 | M57: Produção agropecuária e cadeias produtivas | N57: Incide sobre produção agropecuária, cadeias produtivas ou atividades de interesse direto das modalidades registradas no CFTA. | O57: Acompanhar tramitação e classificar impacto setorial para o CFTA. | P57: Consolidada · abr/2026 | Q57: Requer seja encaminhado ao Ministério da Agricultura e Pecuária, ao Ministério da Educação e à Companhia Nacional de Abastecimento pedido de providências para que promovam estudos visando a elevação do valor máximo por cadastro no Cadastro Nacional da Agricultura Familiar. | R57: |E11|E12|E2|
A58: RQC 20536/2026 | B58: ALEMG (MG) | C58: Requerimento | D58: Deputado Leleco Pimentel PT | G58: 2026 | H58: 2026-04-07 | I58: E11 | J58: E11, E12, E2 | K58: Médio-alta | L58: 13 | M58: Produção agropecuária e cadeias produtivas | N58: Incide sobre produção agropecuária, cadeias produtivas ou atividades de interesse direto das modalidades registradas no CFTA. | O58: Acompanhar tramitação e classificar impacto setorial para o CFTA. | P58: Consolidada · abr/2026 | Q58: Requer seja encaminhado aos Ministérios da Agricultura e Pecuária e da Educação e à Companhia Nacional de Abastecimento pedido de providências para que promovam estudos visando à elevação do valor máximo por unidade familiar inscrita no Cadastro Nacional da Agricultura Familiar - CAF -, atualmente fixado em R$ 40.000,00, considerado insuficiente e limitador para os agricultores familiares que comercializam com a rede estadual de educação, dificultando a aquisição em percentual superior aos 45% previstos na Lei Federal nº 15.226, de 30/9/2025. | R58: |E11|E12|E2|
A59: IND 14948/2026 | B59: ALEPE (PE) | C59: Indicação | D59: Romero Sales Filho | G59: 2026 | H59: 2026-02-03 | I59: E8 | J59: E8, E12, E2 | K59: Médio-alta | L59: 13 | M59: Produção agropecuária e cadeias produtivas | N59: Incide sobre produção agropecuária, cadeias produtivas ou atividades de interesse direto das modalidades registradas no CFTA. | O59: Acompanhar tramitação e classificar impacto setorial para o CFTA. | P59: Consolidada · abr/2026 | Q59: Indicamos à Mesa, ouvido o Plenário e cumpridas as formalidades regimentais, que seja encaminhado apelo à Excelentíssima Senhora Raquel Lyra, Governadora do Estado de Pernambuco; ao Ilustríssimo Sr. Cícero Moraes, Secretário de Desenvolvimento Agrário, Agricultura, Pecuária e Pesca; e ao Ilustríssimo Sr. Miguel Duque, Presidente Instituto Agronômico de Pernambuco (IPA), no sentido de construir uma adutora com água tratada na barragem do Povoado de Santa Rita, localizado no município de Jupi-PE, por meio do Programa de Aquisição de Maquinário e no Programa Terra Plantar, como medida de fortalecimento da agricultura familiar local. | R59: |E8|E12|E2|
A60: IND 994/2026 | B60: ALPB (PB) | C60: Indicação | D60: — | G60: 2026 | I60: E2 | J60: E2 | K60: Muito alta | L60: 13 | M60: Assistência técnica, extensão e carreira pública | N60: Afeta assistência técnica, extensão rural, formação técnica ou estrutura de carreira ligada ao setor agropecuário. | O60: Monitorar tramitação e avaliar posicionamento institucional. | P60: Consolidada · abr/2026 | Q60: Indico, com fundamento no art. 111, I do Regimento Interno da Assembleia Legislativa do Estado de Paraíba (Resolução de Nº: 1578/2012), que seja encaminhada manifestação desta Casa Legislativa, ao Excelentíssimo Senhor João Azevedo Lins Filho, Governador do Estado, a fim de alterar a lei nº 6.379 de 02 de dezembro de 1996, que “dispõe sobre o imposto sobre circulação de mercadorias e serviços e dá outras providências.”, para isentar os representantes comerciais e os profissionais de assistência técnica, extensão rural e assessoramento ao setor agropecuário de ICMS na aquisição de veículo automotor, no estado da Paraíba. | R60: |E2|
A61: RQC 23098/2026 | B61: ALEMG (MG) | C61: RQC | D61: Deputada Bella Gonçalves PT | G61: 2026 | H61: 04/08/2026 | I61: E7 | J61: E7 | K61: Médio-alta | L61: 12 | P61: Varredura · ago/2026 | Q61: Requer seja encaminhado ao Tribunal de Justiça pedido de providências para que, por intermédio do Centro Judiciário de Solução de Conflitos e Cidadania, realize mediação institucional entre a Prefeitura Municipal de Uberlândia e a Companhia Energética de Minas Gerais para viabilizar a conclusão da regularização fundiária da Ocupação Fidel Castro e a ligação de energia elétrica nas residências dessa ocupação e dos Assentamentos Maná e Santa Clara, no Município de Uberlândia. | R61: |E7|
A62: RQC 23108/2026 | B62: ALEMG (MG) | C62: RQC | D62: Deputada Bella Gonçalves PT | G62: 2026 | H62: 04/08/2026 | I62: E7 | J62: E7 | K62: Médio-alta | L62: 12 | P62: Varredura · ago/2026 | Q62: Requer seja encaminhado à Prefeitura Municipal de Uberlândia pedido de providências para que adote as medidas administrativas, técnicas e urbanísticas necessárias à continuidade e à conclusão do processo de regularização fundiária da Ocupação Fidel Castro, bem como à implantação da infraestrutura urbana e à oferta dos serviços públicos essenciais à comunidade. | R62: |E7|
A63: RQC 22939/2026 | B63: ALEMG (MG) | C63: RQC | D63: Deputada Beatriz Cerqueira PT | G63: 2026 | H63: 14/07/2026 | I63: E9 | J63: E9 | K63: Médio-alta | L63: 12 | P63: Varredura · ago/2026 | Q63: Requer seja encaminhado à Secretaria de Estado de Educação pedido de providências para que seja assegurada a manutenção da oferta de turmas da educação de jovens e adultos e do Programa de Educação Profissional na Escola Estadual de Ouro Preto, nesse município, com autorização para abertura de novas turmas no segundo semestre de 2026. | R63: |E9|
A64: IND 16632/2026 | B64: ALEPE (PE) | C64: IND | D64: France Hacker | E64: PP | F64: PE | G64: 2026 | H64: 05/08/2026 | I64: E7 | J64: E7 | K64: Médio-alta | L64: 12 | P64: Varredura · ago/2026 | Q64: Indicamos à Mesa, ouvido o Plenário e cumpridas às formalidades regimentais, que seja enviado um apelo à Governadora de Pernambuco, Exma. Sra. Raquel Teixeira Lyra Lucena, e à Secretário de Desenvolvimento Urbano e Habitação de Pernambuco (SEDUH), Sr. Rodrigo Ribeiro de Queiroz, para que adotem as providências necessárias visando incluir o Município de Tamandaré/PE entre os municípios contemplados pelo Programa Morar Bem Pernambuco, em suas diversas modalidades, especialmente as destinadas à construção de unidades habitacionais de interesse social, concessão do benefício Entrada Garantida, melhorias habitacionais e regularização fundiária, visto que, as últimas moradias fruto de programas sociais que foram entregues a população carente do município, ocorreram na gestão do ex-prefeito Hildo Hacker, no ano de 2016, que proporcionou a construção e entrega de 332 moradias ao povo carente dediverdiTamandaré. | R64: |E7|
A65: IND 16456/2026 | B65: ALES (ES) | C65: IND | D65: Dr. Bruno Resende | E65: UNI | F65: ES | G65: 2026 | H65: 15/07/2026 | I65: E9 | J65: E9 | K65: Médio-alta | L65: 12 | P65: Varredura · ago/2026 | Q65: Sugere ao Excelentíssimo Senhor Governador do Estado do Espírito Santo, que determine à Secretaria de Estado da Ciência, Tecnologia, Inovação e Educação Profissional (SECTI), em conjunto com a Secretaria de Estado de Direitos Humanos (SEDH), a Secretaria de Estado do Trabalho, Assistência e Desenvolvimento Social (SETADES) e demais órgãos competentes, a realização de estudos técnicos e de viabilidade visando à criação do Programa Estadual de Inclusão Digital e Tecnologias Assistivas para Jovens Empreendedores com Deficiência, com o objetivo de ampliar o acesso às tecnologias, fomentar o empreendedorismo inclusivo e promover a autonomia econômica das pessoas com deficiência no Estado do Espírito Santo. | R65: |E9|
A66: PL 0543/2026 | B66: ALESC (SC) | C66: PL | D66: Alex Brasil | G66: 2026 | H66: 04/08/2026 | I66: E4 | J66: E4 | K66: Médio-alta | L66: 12 | P66: Varredura · ago/2026 | Q66: Institui o Programa Selo SC Sem Agrotóxicos, destinado a identificar produtos agrícolas obtidos em sistemas produtivos sem aplicação intencional de agrotóxicos, e dá outras providências. | R66: |E4|
A67: REQ 311/2026 | B67: ALETO (TO) | C67: Requerimento | D67: JAIR FARIAS | G67: 2026 | H67: 2026-03-24 | I67: E1 | J67: E1 | K67: Muito alta | L67: 12 | M67: Assistência técnica, extensão e carreira pública | N67: Afeta assistência técnica, extensão rural, formação técnica ou estrutura de carreira ligada ao setor agropecuário. | O67: Monitorar tramitação e avaliar posicionamento institucional. | P67: Consolidada · abr/2026 | Q67: Requer o envio de expediente ao Excelentíssimo Senhor Governador, Wanderlei Barbosa Castro, com cópia à Secretaria da Administração do Estado do Tocantins (SECAD) e a Secretaria do Planejamento e Orçamento (SEPLAN), solicitando a realização de estudo de viabilidade técnica, jurídica, administrativa e orçamentária para declaração de desnecessidade dos cargos de Técnico Agrícola e Técnico Agropecuário no Quadro Geral do Estado do Tocantins, com a respectiva colocação em extinção e o aproveitamento dos servidores atualmente lotados no NATURATINS, RURALTINS e ADAPEC nos quadros setoriais dos respectivos órgãos. | R67: |E1|
A68: IND 02213/2026 | B68: ALMS (MS) | C68: IND | D68: Zé Teixeira | E68: PL | F68: MS | G68: 2026 | H68: 05/08/2026 | I68: E5 | J68: E5 | K68: Médio-alta | L68: 12 | P68: Varredura · ago/2026 | Q68: Solicita a realização de estudos de viabilidade técnica para a implantação de redutor de velocidade, do tipo lombada eletrônica e/ou quebra-molas, na Rodovia MS-276, na altura do Km 8, no Distrito de Indápolis, trecho de acesso à Lar Cooperativa Agroindustrial, no Município de Dourados. | R68: |E5|
A69: PL 89/2026 | B69: ALMT (MT) | C69: Projeto de lei | D69: Júlio Campos | G69: 2026 | I69: E4 | J69: E4 | K69: Muito alta | L69: 12 | M69: Agrotóxicos, fiscalização e biossegurança | N69: Relaciona-se à fiscalização, biossegurança, fitossanidade e execução técnica em ambiente regulado. | O69: Priorizar monitoramento e avaliar nota técnica regulatória. | P69: Consolidada · abr/2026 | Q69: INSTITUI O PROGRAMA ESTADUAL DE MONITORAMENTO E REDUÇÃO DA EXPOSIÇÃO A AGROTÓXICOS, COM A FINALIDADE DE PREVENIR RISCOS À SAÚDE HUMANA E AO MEIO AMBIENTE, PROMOVER TRANSPARÊNCIA DE DADOS, PROTEGER POPULAÇÕES VULNERÁVEIS E INCENTIVAR PRÁTICAS AGRÍCOLAS DE MENOR RISCO NO ESTADO DE MATO GROSSO. | R69: |E4|
A70: REQ 27280/2026 | B70: ALPB (PB) | C70: Requerimento | D70: — | G70: 2026 | I70: E6 | J70: E6, E12 | K70: Médio-alta | L70: 12 | M70: Produção agropecuária e cadeias produtivas | N70: Incide sobre produção agropecuária, cadeias produtivas ou atividades de interesse direto das modalidades registradas no CFTA. | O70: Acompanhar tramitação e classificar impacto setorial para o CFTA. | P70: Consolidada · abr/2026 | Q70: Requeiro nos termos do art. 112 do Regimento interno desta Casa Legislativa, que seja encaminhada manifestação de apelo ao senhor Secretário de Estado do Desenvolvimento da Agropecuária e da Pesca, no sentido de ampliar o programa de distribuição de sementes no município de Nova Olinda/PB. | R70: |E6|E12|
A71: REQ 27301/2026 | B71: ALPB (PB) | C71: Requerimento | D71: — | G71: 2026 | I71: E6 | J71: E6, E12 | K71: Médio-alta | L71: 12 | M71: Produção agropecuária e cadeias produtivas | N71: Incide sobre produção agropecuária, cadeias produtivas ou atividades de interesse direto das modalidades registradas no CFTA. | O71: Acompanhar tramitação e classificar impacto setorial para o CFTA. | P71: Consolidada · abr/2026 | Q71: Requeiro nos termos do art. 112 do Regimento interno desta Casa Legislativa, que seja encaminhada manifestação de apelo ao senhor Secretário de Estado do Desenvolvimento da Agropecuária e da Pesca, no sentido de ampliar o programa de distribuição de sementes no município de Igaracy/PB. | R71: |E6|E12|
A72: REQ 27335/2026 | B72: ALPB (PB) | C72: Requerimento | D72: — | G72: 2026 | I72: E6 | J72: E6, E12 | K72: Médio-alta | L72: 12 | M72: Produção agropecuária e cadeias produtivas | N72: Incide sobre produção agropecuária, cadeias produtivas ou atividades de interesse direto das modalidades registradas no CFTA. | O72: Acompanhar tramitação e classificar impacto setorial para o CFTA. | P72: Consolidada · abr/2026 | Q72: Requerendo ao Excelentíssimo Senhor Governador do Estado e ao Ilustríssimo Secretário de Desenvolvimento da Agropecuária e Pesca, solicitando distribuição de sementes para os agricultores e produtores rurais do município de Bonito de Santa Fé. | R72: |E6|E12|
A73: REQ 27336/2026 | B73: ALPB (PB) | C73: Requerimento | D73: — | G73: 2026 | I73: E6 | J73: E6, E12 | K73: Médio-alta | L73: 12 | M73: Produção agropecuária e cadeias produtivas | N73: Incide sobre produção agropecuária, cadeias produtivas ou atividades de interesse direto das modalidades registradas no CFTA. | O73: Acompanhar tramitação e classificar impacto setorial para o CFTA. | P73: Consolidada · abr/2026 | Q73: Requerendo ao Excelentíssimo Senhor Governador do Estado e ao Ilustríssimo Secretário de Desenvolvimento da Agropecuária e Pesca, solicitando distribuição de sementes para os agricultores e produtores rurais do município de Nova Olinda. | R73: |E6|E12|
A74: REQ 27338/2026 | B74: ALPB (PB) | C74: Requerimento | D74: — | G74: 2026 | I74: E6 | J74: E6, E12 | K74: Médio-alta | L74: 12 | M74: Produção agropecuária e cadeias produtivas | N74: Incide sobre produção agropecuária, cadeias produtivas ou atividades de interesse direto das modalidades registradas no CFTA. | O74: Acompanhar tramitação e classificar impacto setorial para o CFTA. | P74: Consolidada · abr/2026 | Q74: Requerendo ao Excelentíssimo Senhor Governador do Estado e ao Ilustríssimo Secretário de Desenvolvimento da Agropecuária e Pesca, solicitando distribuição de sementes para os agricultores e produtores rurais do município de Pedra Branca. | R74: |E6|E12|
A75: REQ 27341/2026 | B75: ALPB (PB) | C75: Requerimento | D75: — | G75: 2026 | I75: E6 | J75: E6, E12 | K75: Médio-alta | L75: 12 | M75: Produção agropecuária e cadeias produtivas | N75: Incide sobre produção agropecuária, cadeias produtivas ou atividades de interesse direto das modalidades registradas no CFTA. | O75: Acompanhar tramitação e classificar impacto setorial para o CFTA. | P75: Consolidada · abr/2026 | Q75: Requerendo ao Excelentíssimo Senhor Governador do Estado e ao Ilustríssimo Secretário de Desenvolvimento da Agropecuária e Pesca, solicitando distribuição de sementes para os agricultores e produtores rurais do município de Monte Horebe. | R75: |E6|E12|
A76: REQ 27343/2026 | B76: ALPB (PB) | C76: Requerimento | D76: — | G76: 2026 | I76: E6 | J76: E6, E12 | K76: Médio-alta | L76: 12 | M76: Produção agropecuária e cadeias produtivas | N76: Incide sobre produção agropecuária, cadeias produtivas ou atividades de interesse direto das modalidades registradas no CFTA. | O76: Acompanhar tramitação e classificar impacto setorial para o CFTA. | P76: Consolidada · abr/2026 | Q76: Requerendo ao Excelentíssimo Senhor Governador do Estado e ao Ilustríssimo Secretário de Desenvolvimento da Agropecuária e Pesca, solicitando distribuição de sementes para os agricultores e produtores rurais do município de Bom Sucesso. | R76: |E6|E12|
A77: REQ 27346/2026 | B77: ALPB (PB) | C77: Requerimento | D77: — | G77: 2026 | I77: E6 | J77: E6, E12 | K77: Médio-alta | L77: 12 | M77: Produção agropecuária e cadeias produtivas | N77: Incide sobre produção agropecuária, cadeias produtivas ou atividades de interesse direto das modalidades registradas no CFTA. | O77: Acompanhar tramitação e classificar impacto setorial para o CFTA. | P77: Consolidada · abr/2026 | Q77: Requerendo ao Excelentíssimo Senhor Governador do Estado e ao Ilustríssimo Secretário de Desenvolvimento da Agropecuária e Pesca, solicitando distribuição de sementes para os agricultores e produtores rurais do município de Manaíra. | R77: |E6|E12|
A78: REQ 27349/2026 | B78: ALPB (PB) | C78: Requerimento | D78: — | G78: 2026 | I78: E6 | J78: E6, E12 | K78: Médio-alta | L78: 12 | M78: Produção agropecuária e cadeias produtivas | N78: Incide sobre produção agropecuária, cadeias produtivas ou atividades de interesse direto das modalidades registradas no CFTA. | O78: Acompanhar tramitação e classificar impacto setorial para o CFTA. | P78: Consolidada · abr/2026 | Q78: Requerendo ao Excelentíssimo Senhor Governador do Estado e ao Ilustríssimo Secretário de Desenvolvimento da Agropecuária e Pesca, solicitando distribuição de sementes para os agricultores e produtores rurais do município de Curral Velho. | R78: |E6|E12|
A79: REQ 27351/2026 | B79: ALPB (PB) | C79: Requerimento | D79: — | G79: 2026 | I79: E6 | J79: E6, E12 | K79: Médio-alta | L79: 12 | M79: Produção agropecuária e cadeias produtivas | N79: Incide sobre produção agropecuária, cadeias produtivas ou atividades de interesse direto das modalidades registradas no CFTA. | O79: Acompanhar tramitação e classificar impacto setorial para o CFTA. | P79: Consolidada · abr/2026 | Q79: Requerendo ao Excelentíssimo Senhor Governador do Estado e ao Ilustríssimo Secretário de Desenvolvimento da Agropecuária e Pesca, solicitando distribuição de sementes para os agricultores e produtores rurais do município de Santana de Mangueira. | R79: |E6|E12|
A80: REQ 27353/2026 | B80: ALPB (PB) | C80: Requerimento | D80: — | G80: 2026 | I80: E6 | J80: E6, E12 | K80: Médio-alta | L80: 12 | M80: Produção agropecuária e cadeias produtivas | N80: Incide sobre produção agropecuária, cadeias produtivas ou atividades de interesse direto das modalidades registradas no CFTA. | O80: Acompanhar tramitação e classificar impacto setorial para o CFTA. | P80: Consolidada · abr/2026 | Q80: Requerendo ao Excelentíssimo Senhor Governador do Estado e ao Ilustríssimo Secretário de Desenvolvimento da Agropecuária e Pesca, solicitando distribuição de sementes para os agricultores e produtores rurais do município de Lucena. | R80: |E6|E12|
... A120: REQ 28842/2026 | B120: ALPB (PB) | C120: Requerimento | D120: — | G120: 2026 | I120: E6 | J120: E6, E12 | K120: Médio-alta | L120: 12 | M120: Produção agropecuária e cadeias produtivas | N120: Incide sobre produção agropecuária, cadeias produtivas ou atividades de interesse direto das modalidades registradas no CFTA. | O120: Acompanhar tramitação e classificar impacto setorial para o CFTA. | P120: Consolidada · abr/2026 | Q120: REQUER QUE SEJA ENCAMINHADA MANIFESTAÇÃO DE APELO AO EXCELENTÍSSIMO SENHOR GOVERNADOR DO ESTADO DA PARAÍBA E AO SENHOR SECRETÁRIO DE DESENVOLVIMENTO DA AGROPECUÁRIA E DA PESCA, NO SENTIDO DE QUE SEJAM TOMADAS PROVIDÊNCIAS NECESSÁRIAS PARA VIABILIZAR A DISTRIBUIÇÃO DE MUDAS DE PLANTAS FRUTÍFERAS PARA O MUNICÍPIO DE SALGADINHO. | R120: |E6|E12|
A121: IND 10852/2026 | B121: CLDF (DF) | C121: IND | D121: Deputado Iolando | G121: 2026 | H121: 29/07/2026 | I121: E7 | J121: E7 | K121: Médio-alta | L121: 12 | P121: Varredura · ago/2026 | Q121: Sugere ao Poder Executivo do Distrito Federal, por intermédio da Secretaria de Estado de Desenvolvimento Urbano e Habitação – SEDUH a constituição de Grupo de Trabalho destinado a PRIORIZAR os estudos técnicos sobre a viabilidade da implementação do modelo de Termo Territorial Coletivo (TTC), nas comunidades do Setor Capãozinho, Setor Chapadinha e Região da DF-435 em Brazlândia como instrumento complementar da política de regularização fundiária no Distrito Federal, bem como a realização de audiências públicas para discussão da matéria com a sociedade civil. | R121: |E7|
A122: MSG 75/2026 | B122: ALECE (CE) | C122: MSG | D122: MINISTÉRIO PÚBLICO | G122: 2026 | H122: 06/08/2026 | I122: E1 | J122: E1 | K122: Média | L122: 10 | P122: Varredura · ago/2026 | Q122: PROJETO DE LEI ORIUNDO DA MENSAGEM N .º 03/2026 - ALTERA A REDAÇÃO DO ART. 12 DA LEI 14.043, DE 21 DE DEZEMBRO DE 2007, QUE DISPÕE SOBRE O PLANO DE CARGOS, CARREIRAS E VENCIMENTOS DOS SERVIDORES DO MINISTÉRIO PÚBLICO DO ESTADO DO CEARÁ, E REVOGA DISPOSITIVOS ESPECÍFICOS INCLUÍDOS PELA LEI N.º 18.317/2023 E PELA LEI N.º 19.528/2025. Descrição: | R122: |E1|
A123: IND 442/2026 | B123: ALEMA (MA) | C123: IND | D123: Daniella | E123: MDB | F123: MA | G123: 2026 | H123: 15/07/2026 | I123: E1 | J123: E1 | K123: Média | L123: 10 | P123: Varredura · ago/2026 | Q123: SENHORA PRESIDENTE, NOS TERMOS DO ART. 152 DO REGIMENTO INTERNO DA ASSEMBLEIA LEGISLATIVA DO ESTADO DO MARANH�O, SOLICITA-SE QUE, AP�S APRECIA��O DA MESA DIRETORA, A PRESENTE INDICA��O SEJA ENCAMINHADA AO EXCELENT�SSIMO SENHOR GOVERNADOR DO ESTADO DO MARANH�O, CARLOS BRAND�O, AO SECRET�RIO DE ESTADO DA SA�DE, TIAGO FERNANDES, E � SECRET�RIA DE ESTADO DA MULHER, BR�GIDA SANTOS DE ALBUQUERQUE, PARA QUE ADOTEM AS PROVID�NCIAS NECESS�RIAS VISANDO � ADAPTA��O DA CARRETA DA MULHER MARANHENSE, COM A IMPLEMENTA��O DE EQUIPAMENTOS E DE ESTRUTURA ACESS�VEIS QUE GARANTAM O ATENDIMENTO ADEQUADO �S MULHERES COM DEFICI�NCIA F�SICA, ESPECIALMENTE �S USU�RIAS DE CADEIRA DE RODAS E �QUELAS COM MOBILIDADE REDUZIDA. DANIELLA Diretoria da Mesa Proposi��o Encaminhada Encaminhada por e-mail pelo servidor Alex Bruno em 15/07/2026. - 15/07/2026 Não há | R123: |E1|
A124: RQC 22948/2026 | B124: ALEMG (MG) | C124: RQC | D124: Deputada Bella Gonçalves PT | G124: 2026 | H124: 14/07/2026 | I124: E8 | J124: E8 | K124: Média | L124: 10 | P124: Varredura · ago/2026 | Q124: Requer seja realizada audiência pública, para a qual seja convocado o secretário de Estado de Desenvolvimento Social, para debater a violação de direitos humanos e a ausência de consulta livre, prévia e informada da comunidade tradicional quilombola de Queimadas, no Município de Serro, em relação ao processo de licenciamento ambiental da Herculano Mineração. | R124: |E8|
A125: PL 191/2026 | B125: ALEPA (PA) | C125: Projeto de lei | D125: DEP. CARLOS BORDALO | G125: 2026 | H125: 2026-03-17 | I125: E6 | J125: E6, E2 | K125: Alta | L125: 10 | M125: Produção agropecuária e cadeias produtivas | N125: Incide sobre produção agropecuária, cadeias produtivas ou atividades de interesse direto das modalidades registradas no CFTA. | O125: Acompanhar tramitação e classificar impacto setorial para o CFTA. | P125: Consolidada · abr/2026 | Q125: Institui a Política Estadual de Corredores Agroecológicos para promoção da produção de alimentos, multiplicação de sementes crioulas e fortalecimento de agricultura familiar e da soberania alimentar no Estado do Pará. | R125: |E6|E2|
A126: PL 4251/2026 | B126: ALEPE (PE) | C126: PL | D126: RAQUEL TEIXEIRA LYRA LUCENA | G126: 2026 | H126: 06/08/2026 | I126: E8 | J126: E8 | K126: Média | L126: 10 | P126: Varredura · ago/2026 | Q126: Autoriza a supressão de segmento de vegetação em Área de Preservação Permanente na área que especifica. | R126: |E8|
A127: PL 4252/2026 | B127: ALEPE (PE) | C127: PL | D127: RAQUEL TEIXEIRA LYRA LUCENA | G127: 2026 | H127: 06/08/2026 | I127: E8 | J127: E8 | K127: Média | L127: 10 | P127: Varredura · ago/2026 | Q127: Autoriza a supressão de segmento de vegetação em Área de Preservação Permanente na área que especifica. | R127: |E8|
A128: IND 16624/2026 | B128: ALEPE (PE) | C128: IND | D128: Jarbas Filho | E128: PSD | F128: PE | G128: 2026 | H128: 04/08/2026 | I128: E8 | J128: E8, E11 | K128: Média | L128: 10 | P128: Varredura · ago/2026 | Q128: Indicamos à Mesa, ouvido o Plenário e cumpridas às formalidades regimentais, seja enviado um veemente Apelo ao Excelentíssimo Senhor José Almir Cirilo, Secretário de Recursos Hídricos e Saneamento do Estado de Pernambuco, e ao Excelentíssimo Senhor Douglas Balduíno Guedes da Nóbrega, Diretor-Presidente da Companhia Pernambucana de Saneamento – Compesa, para que sejam adotadas providências necessárias à implantação do sistema de abastecimento de água na Associação dos Agricultores de São Jorge, localizada no município de Cabrobó. | R128: |E8|E11|
A129: IND 16619/2026 | B129: ALEPE (PE) | C129: IND | D129: Nino de Enoque | E129: PL | F129: PE | G129: 2026 | H129: 04/08/2026 | I129: E8 | J129: E8, E11 | K129: Média | L129: 10 | P129: Varredura · ago/2026 | Q129: Indicamos à Mesa, ouvido o Plenário e cumpridas as formalidades regimentais, que seja feito um apelo à Excelentíssima Senhora Governadora do Estado de Pernambuco, Raquel Teixeira Lyra Lucena, e ao Excelentíssimo Senhor Secretário de Recursos Hídricos do Estado de Pernambuco, José Almir Cirilo, para que seja dada prioridade à execução de ações de segurança hídrica no município de Pesqueira – PE, notadamente a ampliação da frequência de abastecimento de água potável por carros-pipa, a recuperação estrutural da Barragem do Rio Ipojuca, o desassoreamento, a ampliação e a limpeza de barreiros e barragens comunitárias, a perfuração e estruturação de poços artesianos, e a adoção de medidas voltadas à perenização do Rio Ipojuca, em atendimento às comunidades rurais de Pau-Ferro I e II, São João e Tiogó. | R129: |E8|E11|
A130: PL 308075/2026 | B130: ALERJ (RJ) | C130: PL | D130: Guilherme Schleder | E130: PSD | F130: RJ | G130: 2026 | H130: 06/08/2026 | I130: E1 | J130: E1 | K130: Média | L130: 10 | P130: Varredura · ago/2026 | Q130: ALTERA O ART. 1º DA LEI Nº 9.490, DE 29 DE NOVEMBRO DE 2021, E O ART. 14 DO DECRETO-LEI Nº 138, DE 23 DE JUNHO DE 1975, PARA DESTINAR OS PRÊMIOS NÃO RECLAMADOS E PARTE DOS LUCROS LÍQUIDOS DA LOTERIA DO ESTADO DO RIO DE JANEIRO AO COMITÊ BRASILEIRO DE CLUBES PARALÍMPICOS - CBCP, E DÁ OUTRAS PROVIDÊNCIAS. | R130: |E1|
A131: MSV 1616/2026 | B131: ALESC (SC) | C131: Proposição | D131: Governador do Estado | G131: 2026 | H131: 2026-01-23 | I131: E4 | J131: E4 | K131: Alta | L131: 10 | M131: Produção agropecuária e cadeias produtivas | N131: Incide sobre produção agropecuária, cadeias produtivas ou atividades de interesse direto das modalidades registradas no CFTA. | O131: Acompanhar tramitação e classificar impacto setorial para o CFTA. | P131: Consolidada · abr/2026 | Q131: Veto Total ao Projeto de Lei nº 132/2024, de autoria do Senhor Deputado Marquito, que "Dispõe sobre a Política Estadual de Bioinsumos, disciplinando a produção comercial e a produção para uso próprio de bioinsumos na agricultura convencional, orgânica, agroecológica e outras finalidades agrícolas". | R131: |E4|
A132: PL 161/2026 | B132: ALESE (SE) | C132: PL | D132: — | G132: 2026 | H132: 10/07/2026 | I132: E1 | J132: E1 | K132: Média | L132: 10 | P132: Varredura · ago/2026 | Q132: DISPÕE SOBRE A TRANSFORMAÇÃO DE CARGOS EFETIVOS NO ÂMBITO DO PODER JUDICIÁRIO DO ESTADO DE SERGIPE; ACRESCENTA INCISO AO ART. 3º DA LEI N° 7.520, DE 27 DE DEZEMBRO DE 2012, PARA CRIAR A DIVISÃO DE INOVAÇÃO E TECNOLOGIA DA ESCOLA JUDICIAL DO ESTADO DE SERGIPE (EJUSE); REVOGA O ART. 56 DA LEI Nº 6.124, DE 21 DE MARÇO DE 2007, E DÁ PROVIDÊNCIAS CORRELATAS. | R132: |E1|
A133: IND 00186/2026 | B133: ALMS (MS) | C133: Indicação | D133: Gleice Jane | G133: 2026 | H133: 2026-02-19 | I133: E8 | J133: E8, E2 | K133: Médio-alta | L133: 10 | M133: Produção agropecuária e cadeias produtivas | N133: Incide sobre produção agropecuária, cadeias produtivas ou atividades de interesse direto das modalidades registradas no CFTA. | O133: Acompanhar tramitação e classificar impacto setorial para o CFTA. | P133: Consolidada · abr/2026 | Q133: Solicita à AGRAER e ao Município de Corguinho/MS a adoção de providências urgentes para instalação de manilhas, construção de vazante e apoio com fornecimento de óleo diesel no Projeto de Crédito Fundiário da Agrovila Serra Negra, às margens da MS-244, visando garantir acesso, recuperação ambiental e continuidade das atividades da agricultura familiar diante da situação de emergência decretada em razão das chuvas intensas. | R133: |E8|E2|
A134: REQ 2501/2026 | B134: ALRN (RN) | C134: REQ | D134: DEPUTADA DIVANEIDE BASÍLIO | G134: 2026 | H134: 20/07/2026 | I134: E8 | J134: E8, E11 | K134: Média | L134: 10 | P134: Varredura · ago/2026 | Q134: Requer que seja encaminhado ofícios ao Governo do Estado do RN e a Secretaria de Estado do Meio Ambiente e dos Recursos Hídricos do RN SEMARH, solicitando a perfuração e instalação de um poço artesiano na Escola Estadual Júlia Auta de Oliveira, localizada na Comunidade Rural de Redenção, no município de Santo Antônio/RN, com vistas a assegurar o abastecimento regular de água à unidade escolar. | R134: |E8|E11|
A135: IND 10894/2026 | B135: CLDF (DF) | C135: IND | D135: Deputada Jaqueline Silva | G135: 2026 | H135: 05/08/2026 | I135: E8 | J135: E8 | K135: Média | L135: 10 | P135: Varredura · ago/2026 | Q135: Sugere ao Poder Executivo que, por intermédio da Secretaria de Estado de Educação do Distrito Federal – SEEDF, promova a construção de um Centro de Ensino Especial na Região Administrativa do Sol Nascente/Pôr do Sol – RA XXXII. | R135: |E8|
A136: IND 10814/2026 | B136: CLDF (DF) | C136: IND | D136: Deputado Joaquim Roriz Neto | G136: 2026 | H136: 21/07/2026 | I136: E8 | J136: E8 | K136: Média | L136: 10 | P136: Varredura · ago/2026 | Q136: Sugere ao Poder Executivo a implantação de faixas de pedestres na via princial do Trecho 3 do Sol Nascente. | R136: |E8|
A137: IND 10792/2026 | B137: CLDF (DF) | C137: IND | D137: Deputado Joaquim Roriz Neto | G137: 2026 | H137: 15/07/2026 | I137: E8 | J137: E8 | K137: Média | L137: 10 | P137: Varredura · ago/2026 | Q137: Sugere ao Poder Executivo que promova a implantação de tampa em bueiro aberto em frente à quadra poliesportiva da Chácara 75, no Sol Nascente. | R137: |E8|
A138: IND 10765/2026 | B138: CLDF (DF) | C138: IND | D138: Deputado Joaquim Roriz Neto | G138: 2026 | H138: 13/07/2026 | I138: E3 | J138: E3 | K138: Média | L138: 10 | P138: Varredura · ago/2026 | Q138: Sugere ao Poder Executivo que seja realizado serviço de inspeção e readequação de fios e cabos soltos nos postes do Conjunto C da QNO 15, na Ceilândia. | R138: |E3|
A139: IND 15013/2026 | B139: ALEPE (PE) | C139: Indicação | D139: Romero Sales Filho | G139: 2026 | H139: 2026-02-03 | I139: E12 | J139: E12, E2 | K139: Alta | L139: 8 | M139: Assistência técnica, extensão e carreira pública | N139: Afeta assistência técnica, extensão rural, formação técnica ou estrutura de carreira ligada ao setor agropecuário. | O139: Monitorar tramitação e avaliar posicionamento institucional. | P139: Consolidada · abr/2026 | Q139: Indicamos à Mesa, ouvido o Plenário e cumpridas as formalidades regimentais, que seja encaminhado apelo à Excelentíssima Senhora Raquel Lyra, Governadora do Estado de Pernambuco; ao Ilustríssimo Sr. Cícero Moraes, Secretário de Desenvolvimento Agrário, Agricultura, Pecuária e Pesca; e ao Ilustríssimo Sr. Miguel Duque, Presidente Instituto Agronômico de Pernambuco (IPA), no sentido de viabilizar a aquisição e entrega de 01 (um) trator agrícola ao Município de São José da Coroa Grande/PE, como forma de fortalecer a agricultura familiar e impulsionar o desenvolvimento rural local. | R139: |E12|E2|
A140: IND 15125/2026 | B140: ALEPE (PE) | C140: Indicação | D140: Romero Sales Filho | G140: 2026 | H140: 2026-02-04 | I140: E12 | J140: E12, E2 | K140: Médio-alta | L140: 8 | M140: Produção agropecuária e cadeias produtivas | N140: Incide sobre produção agropecuária, cadeias produtivas ou atividades de interesse direto das modalidades registradas no CFTA. | O140: Acompanhar tramitação e classificar impacto setorial para o CFTA. | P140: Consolidada · abr/2026 | Q140: Indicamos à Mesa, ouvido o Plenário e cumpridas as formalidades regimentais, que seja encaminhado apelo à Excelentíssima Senhora Raquel Lyra, Governadora do Estado de Pernambuco; ao Ilustríssimo Sr. Cícero Moraes, Secretário de Desenvolvimento Agrário, Agricultura, Pecuária e Pesca; e ao Ilustríssimo Sr. Miguel Duque, Presidente Instituto Agronômico de Pernambuco (IPA), no sentido de viabilizar a inclusão do Município de Venturosa no Programa de Aquisição de Maquinário e no Programa Terra Plantar, para a aquisição de 1 (UMA) Lona, para a conclusão do Programa Água Doce no Povoado de Ingazeira e demais localidades, promovidos por aquele Instituto, como medida de fortalecimento da agricultura familiar local. | R140: |E12|E2|
A141: IND 15127/2026 | B141: ALEPE (PE) | C141: Indicação | D141: Romero Sales Filho | G141: 2026 | H141: 2026-02-04 | I141: E12 | J141: E12, E2 | K141: Médio-alta | L141: 8 | M141: Produção agropecuária e cadeias produtivas | N141: Incide sobre produção agropecuária, cadeias produtivas ou atividades de interesse direto das modalidades registradas no CFTA. | O141: Acompanhar tramitação e classificar impacto setorial para o CFTA. | P141: Consolidada · abr/2026 | Q141: Indicamos à Mesa, ouvido o Plenário e cumpridas as formalidades regimentais, que seja encaminhado apelo à Excelentíssima Senhora Raquel Lyra, Governadora do Estado de Pernambuco; ao Ilustríssimo Sr. Cícero Moraes, Secretário de Desenvolvimento Agrário, Agricultura, Pecuária e Pesca; e ao Ilustríssimo Sr. Miguel Duque, Presidente do Instituto Agronômico de Pernambuco (IPA), no sentido de viabilizar a inclusão do Município de Venturosa no Programa de Aquisição de Maquinário, a fim de disponibilizar 1 (UM) dessalinizador, promovidos por aquele Instituto, como medida de fortalecimento da agricultura familiar local. | R141: |E12|E2|
A142: IND 15154/2026 | B142: ALEPE (PE) | C142: Indicação | D142: Romero Sales Filho | G142: 2026 | H142: 2026-02-04 | I142: E12 | J142: E12, E2 | K142: Médio-alta | L142: 8 | M142: Produção agropecuária e cadeias produtivas | N142: Incide sobre produção agropecuária, cadeias produtivas ou atividades de interesse direto das modalidades registradas no CFTA. | O142: Acompanhar tramitação e classificar impacto setorial para o CFTA. | P142: Consolidada · abr/2026 | Q142: Indicamos à Mesa, ouvido o Plenário e cumpridas as formalidades regimentais, que seja encaminhado apelo à Excelentíssima Senhora Raquel Lyra, Governadora do Estado de Pernambuco; ao Ilustríssimo Sr. Cícero Moraes, Secretário de Desenvolvimento Agrário, Agricultura, Pecuária e Pesca; e ao Ilustríssimo Sr. Miguel Duque, Presidente Instituto Agronômico de Pernambuco (IPA), no sentido de viabilizar a inclusão do Município de São José do Belmonte - especificamente no Sítios Alto e no Sítio Baixo; no Sítio Caldeirão e no Sítio Caititu - no Programa de Aquisição de Maquinário, promovido por aquele Instituto, como medida de fortalecimento da agricultura familiar local. | R142: |E12|E2|
A143: IND 15157/2026 | B143: ALEPE (PE) | C143: Indicação | D143: Romero Sales Filho | G143: 2026 | H143: 2026-02-04 | I143: E12 | J143: E12, E2 | K143: Médio-alta | L143: 8 | M143: Produção agropecuária e cadeias produtivas | N143: Incide sobre produção agropecuária, cadeias produtivas ou atividades de interesse direto das modalidades registradas no CFTA. | O143: Acompanhar tramitação e classificar impacto setorial para o CFTA. | P143: Consolidada · abr/2026 | Q143: Indicamos à Mesa, ouvido o Plenário e cumpridas as formalidades regimentais, que seja encaminhado apelo à Excelentíssima Senhora Raquel Lyra, Governadora do Estado de Pernambuco; ao Ilustríssimo Sr. Cícero Moraes, Secretário de Desenvolvimento Agrário, Agricultura, Pecuária e Pesca; e ao Ilustríssimo Sr. Miguel Duque, Presidente Instituto Agronômico de Pernambuco (IPA), no sentido de viabilizar a construção de uma passagem molhada para o Sítio Malhada Vermelha e uma passagem molhada para o Sítio Mata Redonda, no Município de São José do Belmonte, por meio do Programa de Aquisição de Maquinário e no Programa Terra Plantar, promovidos por aquele Instituto, como medida de fortalecimento da agricultura familiar local. | R143: |E12|E2|
A144: IND 15163/2026 | B144: ALEPE (PE) | C144: Indicação | D144: Romero Sales Filho | G144: 2026 | H144: 2026-02-04 | I144: E12 | J144: E12, E2 | K144: Médio-alta | L144: 8 | M144: Produção agropecuária e cadeias produtivas | N144: Incide sobre produção agropecuária, cadeias produtivas ou atividades de interesse direto das modalidades registradas no CFTA. | O144: Acompanhar tramitação e classificar impacto setorial para o CFTA. | P144: Consolidada · abr/2026 | Q144: Indicamos à Mesa, ouvido o Plenário e cumpridas as formalidades regimentais, que seja encaminhado apelo à Excelentíssima Senhora Raquel Lyra, Governadora do Estado de Pernambuco; ao Ilustríssimo Sr. Cícero Moraes, Secretário de Desenvolvimento Agrário, Agricultura, Pecuária e Pesca; e ao Ilustríssimo Sr. Miguel Duque, Presidente Instituto Agronômico de Pernambuco (IPA), no sentido de viabilizar a inclusão do Município de São José do Belmonte no Programa de Aquisição de Maquinário e no Programa Terra Plantar - para adiquirir, especificamente, 1 (UMA) retroescavadeira e 1 (UM) trator completo - promovidos por aquele Instituto, como medida de fortalecimento da agricultura familiar local. | R144: |E12|E2|
A145: IND 15165/2026 | B145: ALEPE (PE) | C145: Indicação | D145: Romero Sales Filho | G145: 2026 | H145: 2026-02-04 | I145: E12 | J145: E12, E2 | K145: Médio-alta | L145: 8 | M145: Produção agropecuária e cadeias produtivas | N145: Incide sobre produção agropecuária, cadeias produtivas ou atividades de interesse direto das modalidades registradas no CFTA. | O145: Acompanhar tramitação e classificar impacto setorial para o CFTA. | P145: Consolidada · abr/2026 | Q145: Indicamos à Mesa, ouvido o Plenário e cumpridas as formalidades regimentais, que seja encaminhado apelo à Excelentíssima Senhora Raquel Lyra, Governadora do Estado de Pernambuco; ao Ilustríssimo Sr. Cícero Moraes, Secretário de Desenvolvimento Agrário, Agricultura, Pecuária e Pesca; e ao Ilustríssimo Sr. Miguel Duque, Presidente Instituto Agronômico de Pernambuco (IPA), no sentido de viabilizar a inclusão do Município de São José do Belmonte no Programa de Aquisição de Maquinário, a fim de disponibilizar 1 (UM) dessalinizador, promovidos por aquele Instituto, como medida de fortalecimento da agricultura familiar local e do tratamento de água salobra possibilitando sua utilização. | R145: |E12|E2|
A146: IND 14972/2026 | B146: ALEPE (PE) | C146: Indicação | D146: Romero Sales Filho | G146: 2026 | H146: 2026-02-03 | I146: E12 | J146: E12, E2 | K146: Médio-alta | L146: 8 | M146: Produção agropecuária e cadeias produtivas | N146: Incide sobre produção agropecuária, cadeias produtivas ou atividades de interesse direto das modalidades registradas no CFTA. | O146: Acompanhar tramitação e classificar impacto setorial para o CFTA. | P146: Consolidada · abr/2026 | Q146: Indicamos à Mesa, ouvido o Plenário e cumpridas as formalidades regimentais, que seja encaminhado apelo à Excelentíssima Senhora Raquel Lyra, Governadora do Estado de Pernambuco, ao Ilustríssimo Senhor Cícero Moraes, Secretário de Desenvolvimento Agrário, Agricultura, Pecuária e Pesca do Estado de Pernambuco, e ao Ilustríssimo Senhor Miguel Arcanjo Ferraz Duque, Diretor-Presidente do Instituto Agronômico de Pernambuco – IPA, no sentido de viabilizar a realização de mutirão para emissão do Cadastro Nacional da Agricultura Familiar – CAF, a fim de atender à crescente demanda existente no município de Tamandaré e no território do Litoral Sul. | R146: |E12|E2|
A147: IND 15016/2026 | B147: ALEPE (PE) | C147: Indicação | D147: Romero Sales Filho | G147: 2026 | H147: 2026-02-03 | I147: E12 | J147: E12, E2 | K147: Médio-alta | L147: 8 | M147: Produção agropecuária e cadeias produtivas | N147: Incide sobre produção agropecuária, cadeias produtivas ou atividades de interesse direto das modalidades registradas no CFTA. | O147: Acompanhar tramitação e classificar impacto setorial para o CFTA. | P147: Consolidada · abr/2026 | Q147: Indicamos à Mesa, ouvido o Plenário e cumpridas as formalidades regimentais, que seja encaminhado apelo à Excelentíssima Senhora Raquel Lyra, Governadora do Estado de Pernambuco; ao Ilustríssimo Sr. Cícero Moraes, Secretário de Desenvolvimento Agrário, Agricultura, Pecuária e Pesca; e ao Ilustríssimo Sr. Miguel Duque, Presidente Instituto Agronômico de Pernambuco (IPA), no sentido de viabilizar a inclusão do Município de São José da Coroa Grande no Programa de Aquisição de Maquinário e no Programa Terra Plantar, promovidos pelo IPA, como medida de fortalecimento da agricultura familiar local. | R147: |E12|E2|
...

Sheet Novas federais
A1: Identificador | B1: Casa legislativa | C1: Tipo | D1: Autoria | E1: Partido | F1: UF | G1: Ano | H1: Data | I1: Eixo principal | J1: Eixos | K1: Prioridade | L1: Aderência | M1: Categoria | N1: Motivo do interesse para o CFTA | O1: Ação sugerida | P1: Base de origem | Q1: Ementa | R1: Chave
A2: PL 4517/2026 | B2: Câmara dos Deputados | C2: PL | D2: — | G2: 2026 | H2: 17/07/2026 | I2: E5 | J2: E5, E12, E2 | K2: Muito alta | L2: 31 | P2: Varredura · ago/2026 | Q2: Institui o Programa Nacional de Miniagroindústrias Comunitárias – PROMIC, destinado ao fortalecimento do beneficiamento local da produção comunitária, da agricultura familiar, da pesca artesanal, do extrativismo e da sociobiodiversidade, com foco na agregação de valor, geração de renda e desenvolvimento regional sustentável. | R2: |E5|E12|E2|
A3: PL 4297/2026 | B3: Câmara dos Deputados | C3: PL | D3: — | G3: 2026 | H3: 17/07/2026 | I3: E2 | J3: E2 | K3: Muito alta | L3: 28 | P3: Varredura · ago/2026 | Q3: Institui a Política Nacional de Fortalecimento Econômico e Proteção Territorial das Comunidades Quilombolas; altera a Lei nº 12.188, de 11 de janeiro de 2010, para fortalecer o atendimento prioritário às comunidades remanescentes de quilombos no âmbito da Política Nacional de Assistência Técnica e Extensão Rural para a Agricultura Familiar e Reforma Agrária; e estabelece diretrizes para inclusão produtiva, infraestrutura, conectividade e segurança territorial. | R3: |E2|
A4: PL 4738/2026 | B4: Câmara dos Deputados | C4: PL | D4: — | G4: 2026 | H4: 21/07/2026 | I4: E2 | J4: E2 | K4: Muito alta | L4: 28 | P4: Varredura · ago/2026 | Q4: Altera o art. 4º da Lei n° 12.188, de 11 de janeiro de 2010, para incluir objetivo na Política Nacional de Assistência Técnica e Extensão Rural para a Agricultura Familiar e Reforma Agrária (Pnater) voltado ao fomento da autonomia econômica e produtiva de mulheres negras agricultoras familiares, mulheres quilombolas e mulheres integrantes de povos e comunidades tradicionais. | R4: |E2|
A5: PL 104/2026 | B5: Câmara dos Deputados | C5: Projeto de lei | D5: — | G5: 2026 | H5: 2026-02-02 | I5: E7 | J5: E7, E11 | K5: Média | L5: 24 | M5: Crédito rural, seguro e financiamento | N5: Pode alterar instrumentos de crédito ou financiamento relevantes para produtores rurais e para a assistência técnica. | O5: Monitorar tramitação e mapear impacto para produtores e assistência técnica. | P5: Consolidada · abr/2026 | Q5: Altera a Lei nº 13.465, de 11 de julho de 2017, para instituir Certidão Provisória de Regularização Fundiária Rural – CPRF para fins de acesso a crédito rural nos casos que especifica. | R5: |E7|E11|
A6: PL 742/2026 | B6: Câmara dos Deputados | C6: Projeto de lei | D6: — | G6: 2026 | H6: 2026-02-25 | I6: E4 | J6: E4, E8 | K6: Média | L6: 23 | M6: Agrotóxicos, fiscalização e biossegurança | N6: Relaciona-se à fiscalização, biossegurança, fitossanidade e execução técnica em ambiente regulado. | O6: Priorizar monitoramento e avaliar nota técnica regulatória. | P6: Consolidada · abr/2026 | Q6: Proíbe a pulverização aérea de agrotóxicos em todo o território nacional, estabelece medidas de proteção à saúde humana, ao meio ambiente, aos recursos hídricos e às comunidades expostas, e dá outras providências. | R6: |E4|E8|
A7: PDL 4/2026 | B7: Câmara dos Deputados | C7: Projeto de decreto legislativo | D7: — | G7: 2026 | H7: 2026-02-02 | I7: E3 | J7: E3, E11, E12 | K7: Muito alta | L7: 22 | M7: Agrotóxicos, fiscalização e biossegurança | N7: Relaciona-se à fiscalização, biossegurança, fitossanidade e execução técnica em ambiente regulado. | O7: Priorizar monitoramento e avaliar nota técnica regulatória. | P7: Consolidada · abr/2026 | Q7: Susta a Instrução Normativa nº 125, de 23 de março de 2021, da Secretaria de Defesa Agropecuária do Ministério da Agricultura, Pecuária e Abastecimento, que atualiza os requisitos fitossanitários para a importação de amêndoas fermentadas e secas de cacau produzidas na Costa do Marfim. | R7: |E3|E11|E12|
A8: REQ 1/2026 | B8: Câmara dos Deputados | C8: Requerimento | D8: — | G8: 2026 | H8: 2026-02-05 | I8: E4 | J8: E4, E11, E12 | K8: Muito alta | L8: 22 | M8: Agrotóxicos, fiscalização e biossegurança | N8: Relaciona-se à fiscalização, biossegurança, fitossanidade e execução técnica em ambiente regulado. | O8: Priorizar monitoramento e avaliar nota técnica regulatória. | P8: Consolidada · abr/2026 | Q8: Requer a realização de audiência pública, no âmbito da Comissão de Agricultura, Pecuária, Abastecimento e Desenvolvimento Rural – CAPADR, para debater os impactos regulatórios, econômicos e concorrenciais da Portaria MAPA/SDA nº 805/2025, do Programa Nacional de Rastreabilidade de Produtos Agrotóxicos e Afins – PNRA, e da Portaria SDI/MAPA nº 739/2025, bem como da Instrução Normativa Conjunta SPA/SDI/SE-MAPA nº 001/2025, que tratam do credenciamento e da certificação obrigatória no setor de grãos. | R8: |E4|E11|E12|
A9: REQ 1285/2026 | B9: Câmara dos Deputados | C9: Requerimento | D9: — | G9: 2026 | H9: 2026-03-04 | I9: E3 | J9: E3, E11, E12 | K9: Muito alta | L9: 22 | M9: Agrotóxicos, fiscalização e biossegurança | N9: Relaciona-se à fiscalização, biossegurança, fitossanidade e execução técnica em ambiente regulado. | O9: Priorizar monitoramento e avaliar nota técnica regulatória. | P9: Consolidada · abr/2026 | Q9: Requer, nos termos do artigo 155 do Regimento Interno da Câmara dos Deputados, que seja incluído automaticamente na Ordem do Dia o PDL 330/2022, que “Susta a Instrução Normativa nº 125, de 23 de março de 2021, da Secretaria de Defesa Agropecuária do Ministério da Agricultura, Pecuária e Abastecimento, que atualiza os requisitos fitossanitários para a importação de amêndoas fermentadas e secas de cacau produzidas na Costa do Marfim”. | R9: |E3|E11|E12|
A10: REQ 44/2026 | B10: Câmara dos Deputados | C10: Requerimento | D10: — | G10: 2026 | H10: 2026-02-02 | I10: E3 | J10: E3, E11, E12 | K10: Muito alta | L10: 22 | M10: Agrotóxicos, fiscalização e biossegurança | N10: Relaciona-se à fiscalização, biossegurança, fitossanidade e execução técnica em ambiente regulado. | O10: Priorizar monitoramento e avaliar nota técnica regulatória. | P10: Consolidada · abr/2026 | Q10: Requer a inclusão do PDL 330/2022 que susta a Instrução Normativa nº 125, de 23 de março de 2021, da Secretaria de Defesa Agropecuária do Ministério da Agricultura, Pecuária e Abastecimento, que atualiza os requisitos fitossanitários para a importação de amêndoas fermentadas e secas de cacau produzidas na Costa do Marfim, na Ordem do Dia | R10: |E3|E11|E12|
A11: REQ 66/2026 | B11: Câmara dos Deputados | C11: Requerimento | D11: — | G11: 2026 | H11: 2026-02-02 | I11: E3 | J11: E3, E11, E12 | K11: Muito alta | L11: 22 | M11: Agrotóxicos, fiscalização e biossegurança | N11: Relaciona-se à fiscalização, biossegurança, fitossanidade e execução técnica em ambiente regulado. | O11: Priorizar monitoramento e avaliar nota técnica regulatória. | P11: Consolidada · abr/2026 | Q11: Requer urgência para o PDL 330/2022 que susta a Instrução Normativa nº 125, de 23 de março de 2021, da Secretaria de Defesa Agropecuária do Ministério da Agricultura, Pecuária e Abastecimento, que atualiza os requisitos fitossanitários para a importação de amêndoas fermentadas e secas de cacau produzidas na Costa do Marfim. | R11: |E3|E11|E12|
A12: PL 3692/2026 | B12: Câmara dos Deputados | C12: PL | D12: — | G12: 2026 | H12: 14/07/2026 | I12: E10 | J12: E10, E1 | K12: Muito alta | L12: 19 | P12: Varredura · ago/2026 | Q12: Institui o Estatuto Nacional dos Guias de Turismo, cria o Sistema Federal de Fiscalização da Profissão de Guia de Turismo – SIFGT, o Conselho Federal dos Guias de Turismo – CFGT e os Conselhos Regionais dos Guias de Turismo – CRGT, dispõe sobre o exercício da profissão de Guia de Turismo, altera a Lei nº 8.623, de 28 de janeiro de 1993. | R12: |E10|E1|
A13: PL 3933/2026 | B13: Câmara dos Deputados | C13: PL | D13: — | G13: 2026 | H13: 17/07/2026 | I13: E6 | J13: E6 | K13: Alta | L13: 19 | P13: Varredura · ago/2026 | Q13: Altera a Lei nº 14.119, de 13 de janeiro de 2021, para incluir as atividades de produção de sementes e mudas nativas destinadas à restauração ecológica entre as ações elegíveis para incentivos e pagamentos por serviços ambientais. | R13: |E6|
A14: INC 22/2026 | B14: Câmara dos Deputados | C14: Indicação | D14: — | G14: 2026 | H14: 2026-02-02 | I14: E3 | J14: E3, E12 | K14: Muito alta | L14: 17 | M14: Agrotóxicos, fiscalização e biossegurança | N14: Relaciona-se à fiscalização, biossegurança, fitossanidade e execução técnica em ambiente regulado. | O14: Priorizar monitoramento e avaliar nota técnica regulatória. | P14: Consolidada · abr/2026 | Q14: Sugere ao Ministério da Agricultura e Pecuária a revisão da Instrução Normativa nº 125, de 23 de março de 2021, da Secretaria de Defesa Agropecuária, que atualiza os requisitos fitossanitários para a importação de amêndoas fermentadas e secas de cacau produzidas na Costa do Marfim. | R14: |E3|E12|
A15: INC 381/2026 | B15: Câmara dos Deputados | C15: Indicação | D15: — | G15: 2026 | H15: 2026-03-19 | I15: E3 | J15: E3, E12 | K15: Muito alta | L15: 17 | M15: Agrotóxicos, fiscalização e biossegurança | N15: Relaciona-se à fiscalização, biossegurança, fitossanidade e execução técnica em ambiente regulado. | O15: Priorizar monitoramento e avaliar nota técnica regulatória. | P15: Consolidada · abr/2026 | Q15: Sugere ao Ministério da Agricultura e Pecuária a revisão da Instrução Normativa nº 125, de 23 de março de 2021, da Secretaria de Defesa Agropecuária, que atualiza os requisitos fitossanitários para a importação de amêndoas fermentadas e secas de cacau produzidas na Costa do Marfim. | R15: |E3|E12|
A16: PL 1389/2026 | B16: Senado Federal | C16: Projeto de lei | D16: Angelo Coronel | G16: 2026 | H16: 2026-03-24 | I16: E11 | J16: E11 | K16: Muito alta | L16: 17 | M16: Crédito rural, seguro e financiamento | N16: Pode alterar instrumentos de crédito ou financiamento relevantes para produtores rurais e para a assistência técnica. | O16: Monitorar tramitação e mapear impacto para produtores e assistência técnica. | P16: Consolidada · abr/2026 | Q16: Estabelece diretrizes para a aplicação de recursos do crédito rural e de instrumentos de gestão de risco no âmbito da política agrícola, com foco no semiárido brasileiro. | R16: |E11|
A17: PL 1393/2026 | B17: Senado Federal | C17: Projeto de lei | D17: Angelo Coronel | G17: 2026 | H17: 2026-03-24 | I17: E11 | J17: E11 | K17: Muito alta | L17: 17 | M17: Crédito rural, seguro e financiamento | N17: Pode alterar instrumentos de crédito ou financiamento relevantes para produtores rurais e para a assistência técnica. | O17: Monitorar tramitação e mapear impacto para produtores e assistência técnica. | P17: Consolidada · abr/2026 | Q17: Institui regime jurídico complementar de estabilização financeira aplicável às operações de crédito rural em situações de emergência decorrentes de eventos climáticos adversos no semiárido, em complemento aos instrumentos de gestão de risco da política agrícola. | R17: |E11|
A18: PL 4292/2026 | B18: Câmara dos Deputados | C18: PL | D18: — | G18: 2026 | H18: 17/07/2026 | I18: E11 | J18: E11, E7 | K18: Alta | L18: 17 | P18: Varredura · ago/2026 | Q18: Altera a Lei nº 8.629, de 25 de fevereiro de 1993, para estabelecer a obrigatoriedade de co-titularidade da mulher nos instrumentos de alienação, concessão, doação ou titulação de terras rurais e em contratos de crédito rural, dispondo sobre condições de preferência em programas públicos. | R18: |E11|E7|
A19: PL 738/2026 | B19: Câmara dos Deputados | C19: Projeto de lei | D19: — | G19: 2026 | H19: 2026-02-25 | I19: E11 | J19: E11, E12 | K19: Muito alta | L19: 17 | M19: Crédito rural, seguro e financiamento | N19: Pode alterar instrumentos de crédito ou financiamento relevantes para produtores rurais e para a assistência técnica. | O19: Monitorar tramitação e mapear impacto para produtores e assistência técnica. | P19: Consolidada · abr/2026 | Q19: Dispõe sobre a prorrogação excepcional de parcelas de operações de crédito rural em situações de impacto econômico significativo sobre cadeias produtivas agropecuárias, institui incentivos fiscais para o setor leiteiro, promove alterações na legislação tributária e regula o rótulo de produtos lácteos reconstituídos com leite em pó. | R19: |E11|E12|
A20: REQ 1/2026 | B20: Senado Federal | C20: Requerimento | D20: Zequinha Marinho | G20: 2026 | H20: 2026-02-01 | I20: E3 | J20: E3, E12 | K20: Muito alta | L20: 17 | M20: Agrotóxicos, fiscalização e biossegurança | N20: Relaciona-se à fiscalização, biossegurança, fitossanidade e execução técnica em ambiente regulado. | O20: Priorizar monitoramento e avaliar nota técnica regulatória. | P20: Consolidada · abr/2026 | Q20: Requeiro, nos termos do art. 58, § 2º, II, da Constituição Federal e do art. 93, II, do Regimento Interno do Senado Federal, a realização de audiência pública, com o objetivo de averiguar, debater e esclarecer os procedimentos adotados quanto ao tratamento, guarda, possíveis maus-tratos e destinação de gado apreendido em operações de fiscalização ambiental conduzidas pelo Instituto Brasileiro do Meio Ambiente e dos Recursos Naturais Renováveis (IBAMA), especialmente no estado do Pará. Proponho para a audiência a presença dos seguintes convidados: • Presidente do Instituto Brasileiro do Meio Ambiente e dos Recursos Naturais Renováveis (IBAMA); • Presidente da Agência de Defesa Agropecuária do Estado do Pará (ADEPARÁ); • Presidente da Entidade representativa da sociedade protetora dos animais; • Presidente da Associação dos Produtores Rurais (APRIA); • Representante do Ministério Público. | R20: |E3|E12|
A21: REQ 29/2026 | B21: Câmara dos Deputados | C21: Requerimento | D21: — | G21: 2026 | H21: 2026-03-16 | I21: E3 | J21: E3, E12 | K21: Muito alta | L21: 17 | M21: Agrotóxicos, fiscalização e biossegurança | N21: Relaciona-se à fiscalização, biossegurança, fitossanidade e execução técnica em ambiente regulado. | O21: Priorizar monitoramento e avaliar nota técnica regulatória. | P21: Consolidada · abr/2026 | Q21: Requer a realização de Audiência Pública para discutir o Projeto de Lei Complementar nº 95, de 2024, e a necessidade de impedir o contingenciamento das despesas destinadas à defesa agropecuária | R21: |E3|E12|
A22: REQ 38/2026 | B22: Câmara dos Deputados | C22: Requerimento | D22: — | G22: 2026 | H22: 2026-04-07 | I22: E11 | J22: E11, E12 | K22: Muito alta | L22: 17 | M22: Crédito rural, seguro e financiamento | N22: Pode alterar instrumentos de crédito ou financiamento relevantes para produtores rurais e para a assistência técnica. | O22: Monitorar tramitação e mapear impacto para produtores e assistência técnica. | P22: Consolidada · abr/2026 | Q22: Requer ao Ministro de Estado da Agricultura e Pecuária informações acerca dos impactos, da operacionalização e da compatibilidade jurídica da Resolução nº 5.268, de 2025, do Conselho Monetário Nacional, especialmente quanto à utilização de sistemas de monitoramento remoto como critério para concessão de crédito rural. | R22: |E11|E12|
A23: REQ 41/2026 | B23: Câmara dos Deputados | C23: Requerimento | D23: — | G23: 2026 | H23: 2026-04-08 | I23: E11 | J23: E11, E12 | K23: Muito alta | L23: 17 | M23: Crédito rural, seguro e financiamento | N23: Pode alterar instrumentos de crédito ou financiamento relevantes para produtores rurais e para a assistência técnica. | O23: Monitorar tramitação e mapear impacto para produtores e assistência técnica. | P23: Consolidada · abr/2026 | Q23: Requer a realização de audiência pública, em conjunto com a Comissão de Meio Ambiente e Desenvolvimento Sustentável (CMADS), para debater o seguinte tema: “Preservação ambiental e fomento da produção agropecuária: impactos da alteração do Manual de Crédito Rural”. | R23: |E11|E12|
A24: REQ 5/2026 | B24: Câmara dos Deputados | C24: Requerimento | D24: — | G24: 2026 | H24: 2026-02-10 | I24: E3 | J24: E3, E12 | K24: Muito alta | L24: 17 | M24: Agrotóxicos, fiscalização e biossegurança | N24: Relaciona-se à fiscalização, biossegurança, fitossanidade e execução técnica em ambiente regulado. | O24: Priorizar monitoramento e avaliar nota técnica regulatória. | P24: Consolidada · abr/2026 | Q24: Requer o encaminhamento de indicação ao Excelentíssimo Senhor Ministro da Agricultura e Pecuária para sugerir a revisão da Instrução Normativa nº 125, de 23 de março de 2021, da Secretaria de Defesa Agropecuária, que atualiza os requisitos fitossanitários para a importação de amêndoas fermentadas e secas de cacau produzidas na Costa do Marfim. | R24: |E3|E12|
A25: REQ 7/2026 | B25: Câmara dos Deputados | C25: Requerimento | D25: — | G25: 2026 | H25: 2026-03-10 | I25: E11 | J25: E11, E12 | K25: Muito alta | L25: 17 | M25: Crédito rural, seguro e financiamento | N25: Pode alterar instrumentos de crédito ou financiamento relevantes para produtores rurais e para a assistência técnica. | O25: Monitorar tramitação e mapear impacto para produtores e assistência técnica. | P25: Consolidada · abr/2026 | Q25: Requer a realização de audiência pública no âmbito da Comissão de Meio Ambiente e Desenvolvimento Sustentável para debater o seguinte tema: “Preservação ambiental e fomento da produção agropecuária: impactos da alteração do Manual de Crédito Rural”. | R25: |E11|E12|
A26: RIC 726/2026 | B26: Câmara dos Deputados | C26: Requerimento de informação | D26: — | G26: 2026 | H26: 2026-03-31 | I26: E11 | J26: E11, E12 | K26: Muito alta | L26: 17 | M26: Crédito rural, seguro e financiamento | N26: Pode alterar instrumentos de crédito ou financiamento relevantes para produtores rurais e para a assistência técnica. | O26: Monitorar tramitação e mapear impacto para produtores e assistência técnica. | P26: Consolidada · abr/2026 | Q26: Requer ao Ministro de Estado da Agricultura e Pecuária informações acerca dos impactos, da operacionalização e da compatibilidade jurídica da Resolução nº 5.268, de 2025, do Conselho Monetário Nacional, especialmente quanto à utilização de sistemas de monitoramento remoto como critério para concessão de crédito rural. | R26: |E11|E12|
A27: RIC 727/2026 | B27: Câmara dos Deputados | C27: Requerimento de informação | D27: — | G27: 2026 | H27: 2026-03-31 | I27: E11 | J27: E11, E12 | K27: Muito alta | L27: 17 | M27: Crédito rural, seguro e financiamento | N27: Pode alterar instrumentos de crédito ou financiamento relevantes para produtores rurais e para a assistência técnica. | O27: Monitorar tramitação e mapear impacto para produtores e assistência técnica. | P27: Consolidada · abr/2026 | Q27: Requer informações ao Ministério da Agricultura e Pecuária (MAPA), acerca da aplicação das Resoluções nº 5.268/2025 e nº 5.193/2024, que tratam da concessão de crédito rural a produtores com áreas desmatadas irregularmente. | R27: |E11|E12|
A28: PDL 173/2026 | B28: Câmara dos Deputados | C28: Projeto de decreto legislativo | D28: — | G28: 2026 | H28: 2026-03-31 | I28: E11 | J28: E11, E8 | K28: Média | L28: 16 | M28: Crédito rural, seguro e financiamento | N28: Pode alterar instrumentos de crédito ou financiamento relevantes para produtores rurais e para a assistência técnica. | O28: Monitorar tramitação e mapear impacto para produtores e assistência técnica. | P28: Consolidada · abr/2026 | Q28: Susta os efeitos das Resoluções nº 5.268/2025 e nº 5.193/2024 do Conselho Monetário Nacional, que estabelecem restrições à concessão de crédito rural com base em dados de desmatamento irregular. | R28: |E11|E8|
A29: PL 1062/2026 | B29: Câmara dos Deputados | C29: Projeto de lei | D29: — | G29: 2026 | H29: 2026-03-10 | I29: E11 | J29: E11, E2 | K29: Muito alta | L29: 15 | M29: Crédito rural, seguro e financiamento | N29: Pode alterar instrumentos de crédito ou financiamento relevantes para produtores rurais e para a assistência técnica. | O29: Monitorar tramitação e mapear impacto para produtores e assistência técnica. | P29: Consolidada · abr/2026 | Q29: Cria linha especial de crédito rural para os apicultores e os meliponicultores, com foco em fortalecer a cadeia produtiva, especialmente no âmbito da agricultura familiar. | R29: |E11|E2|
A30: PL 4514/2026 | B30: Câmara dos Deputados | C30: PL | D30: — | G30: 2026 | H30: 17/07/2026 | I30: E12 | J30: E12, E2 | K30: Médio-alta | L30: 15 | P30: Varredura · ago/2026 | Q30: Institui o Programa Nacional de Armazenagem e Cadeia Fria da Agricultura Familiar – PRONACAF, destinado à redução de perdas produtivas, ampliação da renda rural, fortalecimento da segurança alimentar e estruturação logística da agricultura familiar, da pesca artesanal e da produção comunitária. | R30: |E12|E2|
A31: PL 854/2026 | B31: Câmara dos Deputados | C31: Projeto de lei | D31: — | G31: 2026 | H31: 2026-03-02 | I31: E11 | J31: E11, E2 | K31: Médio-alta | L31: 15 | M31: Produção agropecuária e cadeias produtivas | N31: Incide sobre produção agropecuária, cadeias produtivas ou atividades de interesse direto das modalidades registradas no CFTA. | O31: Acompanhar tramitação e classificar impacto setorial para o CFTA. | P31: Consolidada · abr/2026 | Q31: Institui a Linha de Crédito Especial Pronaf Cacau no âmbito do Programa Nacional de Fortalecimento da Agricultura Familiar; estabelece condições diferenciadas de acesso para produtores detentores do Selo Verde Cacau; e dá outras providências. | R31: |E11|E2|
A32: PL 894/2026 | B32: Câmara dos Deputados | C32: Projeto de lei | D32: — | G32: 2026 | H32: 2026-03-03 | I32: E11 | J32: E11, E2 | K32: Médio-alta | L32: 15 | M32: Produção agropecuária e cadeias produtivas | N32: Incide sobre produção agropecuária, cadeias produtivas ou atividades de interesse direto das modalidades registradas no CFTA. | O32: Acompanhar tramitação e classificar impacto setorial para o CFTA. | P32: Consolidada · abr/2026 | Q32: Institui a Linha de Crédito Especial Pronaf Cacau no âmbito do Programa Nacional de Fortalecimento da Agricultura Familiar; estabelece condições diferenciadas de acesso para produtores detentores do Selo Verde Cacau; e dá outras providências. | R32: |E11|E2|
A33: REQ 1723/2026 | B33: Câmara dos Deputados | C33: Requerimento | D33: — | G33: 2026 | H33: 2026-03-26 | I33: E11 | J33: E11, E2 | K33: Médio-alta | L33: 15 | M33: Produção agropecuária e cadeias produtivas | N33: Incide sobre produção agropecuária, cadeias produtivas ou atividades de interesse direto das modalidades registradas no CFTA. | O33: Acompanhar tramitação e classificar impacto setorial para o CFTA. | P33: Consolidada · abr/2026 | Q33: Requer urgência para a tramitação do Projeto de Lei 894/26, que Institui a Linha de Crédito Especial Pronaf Cacau no âmbito do Programa Nacional de Fortalecimento da Agricultura Familiar; estabelece condições diferenciadas de acesso para produtores detentores do Selo Verde Cacau; e dá outras providências. | R33: |E11|E2|
A34: PL 1683/2026 | B34: Senado Federal | C34: Projeto de lei | D34: Jader Barbalho | G34: 2026 | H34: 2026-04-07 | I34: E11 | J34: E11, E12 | K34: Média | L34: 14 | M34: Produção agropecuária e cadeias produtivas | N34: Incide sobre produção agropecuária, cadeias produtivas ou atividades de interesse direto das modalidades registradas no CFTA. | O34: Acompanhar tramitação e classificar impacto setorial para o CFTA. | P34: Consolidada · abr/2026 | Q34: Altera a Lei nº 8.171, de 17 de janeiro de 1991, para instituir diretrizes de regionalização, transparência digital e comunicação direta no Programa de Garantia da Atividade Agropecuária (Proagro). | R34: |E11|E12|
A35: PL 4289/2026 | B35: Câmara dos Deputados | C35: PL | D35: — | G35: 2026 | H35: 17/07/2026 | I35: E8 | J35: E8 | K35: Médio-alta | L35: 14 | P35: Varredura · ago/2026 | Q35: Dispõe sobre a alteração da Lei nº 12.651, de 25 de maio de 2012 (Código Florestal), para aumentar a faixa de Área de Preservação Permanente (APP) dos cursos d’água de vazão e largura reduzidas, denominados igarapés ou similares, no Bioma Amazônia, e dá outras providências. | R35: |E8|
A36: RIC 209/2026 | B36: Câmara dos Deputados | C36: Requerimento de informação | D36: — | G36: 2026 | H36: 2026-02-12 | I36: E11 | J36: E11, E12 | K36: Alta | L36: 14 | M36: Crédito rural, seguro e financiamento | N36: Pode alterar instrumentos de crédito ou financiamento relevantes para produtores rurais e para a assistência técnica. | O36: Monitorar tramitação e mapear impacto para produtores e assistência técnica. | P36: Consolidada · abr/2026 | Q36: Requer informações ao Ministério do Planejamento e Orçamento sobre a fundamentação técnica e econômica dos Vetos Presidenciais á LDO 2026 e a LOA 2026 que incidem sobre Seguro Rural, Defesa e Pesquisa Agropecuária e Irrigação no Nordeste. | R36: |E11|E12|
A37: PL 4108/2026 | B37: Câmara dos Deputados | C37: PL | D37: — | G37: 2026 | H37: 17/07/2026 | I37: E9 | J37: E9 | K37: Médio-alta | L37: 13 | P37: Varredura · ago/2026 | Q37: Altera o Decreto-Lei nº 5.452, de 1º de maio de 1943 (Consolidação das Leis do Trabalho), para disciplinar a aprendizagem profissional em áreas rurais, ribeirinhas e territórios de difícil acesso, mediante programas territorializados de formação profissional. | R37: |E9|
A38: INC 1442/2026 | B38: Câmara dos Deputados | C38: INC | D38: — | G38: 2026 | H38: 09/07/2026 | I38: E11 | J38: E11 | K38: Médio-alta | L38: 12 | P38: Varredura · ago/2026 | Q38: Sugere ao Banco Central do Brasil a adoção de providências, no âmbito de suas competências, voltadas à preservação do crédito rural e da capacidade financeira dos agricultores familiares atingidos pela estiagem na safra de milho 2025/2026. | R38: |E11|
A39: INC 1454/2026 | B39: Câmara dos Deputados | C39: INC | D39: — | G39: 2026 | H39: 15/07/2026 | I39: E11 | J39: E11 | K39: Médio-alta | L39: 12 | P39: Varredura · ago/2026 | Q39: Sugere ao Ministério da Fazenda a adoção de providências, no âmbito do Conselho Monetário Nacional e do Banco Central do Brasil, para a normatização do art. 6º da Lei nº 15.399, de 4 de maio de 2026, que assegura aos pescadores artesanais, no âmbito do Pronaf, os mesmos encargos financeiros das operações do Grupo "A". | R39: |E11|
A40: MPV 1376/2026 | B40: Câmara dos Deputados | C40: MPV | D40: — | G40: 2026 | H40: 15/07/2026 | I40: E11 | J40: E11 | K40: Médio-alta | L40: 12 | P40: Varredura · ago/2026 | Q40: Autoriza a criação de linhas de crédito para composição de dívidas para liquidação ou amortização de operações de crédito rural e de Cédulas de Produto Rural e autoriza a participação da União em fundo garantidor destinado à cobertura de operações de crédito rural contratadas por produtores rurais afetados por eventos climáticos adversos. | R40: |E11|
A41: MPV 1376/2026 | B41: Congresso Nacional | C41: MPV | D41: Presidência da República | G41: 2026 | H41: 14/07/2026 | I41: E11 | J41: E11 | K41: Médio-alta | L41: 12 | P41: Varredura · ago/2026 | Q41: Autoriza a criação de linhas de crédito para composição de dívidas para liquidação ou amortização de operações de crédito rural e de Cédulas de Produto Rural e autoriza a participação da União em fundo garantidor destinado à cobertura de operações de crédito rural contratadas por produtores rurais afetados por eventos climáticos adversos. | R41: |E11|
A42: PDL 168/2026 | B42: Câmara dos Deputados | C42: Projeto de decreto legislativo | D42: — | G42: 2026 | H42: 2026-03-30 | I42: E11 | J42: E11 | K42: Média | L42: 12 | M42: Crédito rural, seguro e financiamento | N42: Pode alterar instrumentos de crédito ou financiamento relevantes para produtores rurais e para a assistência técnica. | O42: Monitorar tramitação e mapear impacto para produtores e assistência técnica. | P42: Consolidada · abr/2026 | Q42: Susta os efeitos da Resolução nº 5.268, de 2025, do Conselho Monetário Nacional, que “Altera normas da Seção 9 (Impedimentos Sociais, Ambientais e Climáticos) do Capítulo 2 (Condições Básicas) do Manual de Crédito Rural – MCR”. | R42: |E11|
A43: PDL 169/2026 | B43: Câmara dos Deputados | C43: Projeto de decreto legislativo | D43: — | G43: 2026 | H43: 2026-03-31 | I43: E11 | J43: E11 | K43: Média | L43: 12 | M43: Crédito rural, seguro e financiamento | N43: Pode alterar instrumentos de crédito ou financiamento relevantes para produtores rurais e para a assistência técnica. | O43: Monitorar tramitação e mapear impacto para produtores e assistência técnica. | P43: Consolidada · abr/2026 | Q43: Susta dispositivos das Resoluções nº 5.268 de 18 de dezembro de 2025 e nº 5.193, de 19 de dezembro de 2024, do Conselho Monetário Nacional, que tratam de condicionantes ambientais para concessão de crédito no Manual de Crédito Rural. | R43: |E11|
A44: PDL 176/2026 | B44: Senado Federal | C44: Projeto de decreto legislativo | D44: Jaime Bagattoli | G44: 2026 | H44: 2026-03-31 | I44: E11 | J44: E11 | K44: Média | L44: 12 | M44: Crédito rural, seguro e financiamento | N44: Pode alterar instrumentos de crédito ou financiamento relevantes para produtores rurais e para a assistência técnica. | O44: Monitorar tramitação e mapear impacto para produtores e assistência técnica. | P44: Consolidada · abr/2026 | Q44: Susta dispositivos das Resoluções nº 5.268 de 18 de dezembro de 2025 e nº 5.193, de 19 de dezembro de 2024, do Conselho Monetário Nacional, que tratam de condicionantes ambientais para concessão de crédito rural. | R44: |E11|
A45: PDL 178/2026 | B45: Câmara dos Deputados | C45: Projeto de decreto legislativo | D45: — | G45: 2026 | H45: 2026-04-01 | I45: E11 | J45: E11 | K45: Média | L45: 12 | M45: Crédito rural, seguro e financiamento | N45: Pode alterar instrumentos de crédito ou financiamento relevantes para produtores rurais e para a assistência técnica. | O45: Monitorar tramitação e mapear impacto para produtores e assistência técnica. | P45: Consolidada · abr/2026 | Q45: Susta dispositivos das Resoluções nº 5.268 de 18 de dezembro de 2025 e nº 5.193, de 19 de dezembro de 2024, do Conselho Monetário Nacional, que tratam de condicionantes ambientais para concessão de crédito rural. | R45: |E11|
A46: PDL 181/2026 | B46: Câmara dos Deputados | C46: Projeto de decreto legislativo | D46: — | G46: 2026 | H46: 2026-04-06 | I46: E11 | J46: E11 | K46: Média | L46: 12 | M46: Crédito rural, seguro e financiamento | N46: Pode alterar instrumentos de crédito ou financiamento relevantes para produtores rurais e para a assistência técnica. | O46: Monitorar tramitação e mapear impacto para produtores e assistência técnica. | P46: Consolidada · abr/2026 | Q46: Susta os efeitos da Resolução CMN nº 5.193, de 19 de dezembro de 2024, que altera normas da Seção 9 (Impedimentos Sociais, Ambientais e Climáticos) do Capítulo 2 (Condições Básicas) do Manual de Crédito Rural – MCR. | R46: |E11|
A47: PL 1194/2026 | B47: Câmara dos Deputados | C47: Projeto de lei | D47: — | G47: 2026 | H47: 2026-03-17 | I47: E11 | J47: E11 | K47: Média | L47: 12 | M47: Crédito rural, seguro e financiamento | N47: Pode alterar instrumentos de crédito ou financiamento relevantes para produtores rurais e para a assistência técnica. | O47: Monitorar tramitação e mapear impacto para produtores e assistência técnica. | P47: Consolidada · abr/2026 | Q47: Institui mecanismo automático de prorrogação de operações de crédito rural em caso de ocorrência de eventos climáticos adversos e dá outras providências. | R47: |E11|
A48: PL 3719/2026 | B48: Câmara dos Deputados | C48: PL | D48: — | G48: 2026 | H48: 15/07/2026 | I48: E10 | J48: E10 | K48: Médio-alta | L48: 12 | P48: Varredura · ago/2026 | Q48: Dispõe sobre a obrigatoriedade de sistema de consulta eletrônica ao registro no Conselho Regional de Medicina (CRM) dos médicos em atividade nos estabelecimentos hospitalares públicos e privados e dá outras providências. | R48: |E10|
A49: PL 3785/2026 | B49: Câmara dos Deputados | C49: PL | D49: — | G49: 2026 | H49: 17/07/2026 | I49: E9 | J49: E9 | K49: Médio-alta | L49: 12 | P49: Varredura · ago/2026 | Q49: Institui o Programa Conecta Trabalho (CONECTA), com a finalidade de ampliar o acesso à educação profissional e tecnológica e ao mercado de trabalho. | R49: |E9|
A50: PL 3886/2026 | B50: Câmara dos Deputados | C50: PL | D50: — | G50: 2026 | H50: 17/07/2026 | I50: E9 | J50: E9 | K50: Médio-alta | L50: 12 | P50: Varredura · ago/2026 | Q50: Institui a Política Nacional de Permanência na Educação Profissional e Tecnológica, autoriza a União a instituir a Bolsa Nacional de Permanência Técnica e altera as Leis nºs 9.394, de 20 de dezembro de 1996, e 12.513, de 26 de outubro de 2011. | R50: |E9|
A51: PL 3924/2026 | B51: Câmara dos Deputados | C51: PL | D51: — | G51: 2026 | H51: 17/07/2026 | I51: E9 | J51: E9 | K51: Médio-alta | L51: 12 | P51: Varredura · ago/2026 | Q51: Altera a Lei nº 9.394, de 20 de dezembro de 1996, para estabelecer diretrizes de integração da educação de jovens e adultos à educação profissional e tecnológica, à certificação progressiva de competências e à inclusão produtiva, e dá outras providências. | R51: |E9|
A52: PL 4600/2026 | B52: Câmara dos Deputados | C52: PL | D52: — | G52: 2026 | H52: 17/07/2026 | I52: E7 | J52: E7 | K52: Médio-alta | L52: 12 | P52: Varredura · ago/2026 | Q52: Institui a Política Nacional de Mutirão Assistido de Regularização Fundiária Urbana Popular – MORAR LEGAL, estabelece mecanismos de apoio técnico e jurídico simplificado para famílias de baixa renda e dá outras providências. | R52: |E7|
A53: PL 4608/2026 | B53: Câmara dos Deputados | C53: PL | D53: — | G53: 2026 | H53: 17/07/2026 | I53: E9 | J53: E9 | K53: Médio-alta | L53: 12 | P53: Varredura · ago/2026 | Q53: Institui a Política Nacional de Ensino Técnico Territorializado em Manutenção, Energia e Logística no Interior, com prioridade para a Amazônia Legal e regiões de baixa densidade econômica e educacional, integrada à Rede Federal de Educação Profissional, Científica e Tecnológica, e dá outras providências. | R53: |E9|
A54: PL 4704/2026 | B54: Câmara dos Deputados | C54: PL | D54: — | G54: 2026 | H54: 17/07/2026 | I54: E5 | J54: E5 | K54: Médio-alta | L54: 12 | P54: Varredura · ago/2026 | Q54: Institui a Política Nacional de Produção Energética Renovável da Amazônia Legal – AMAZÔNIA COMBUSTÍVEL DO FUTURO, cria o Sistema Nacional de Competitividade dos Combustíveis Renováveis Estratégicos da Amazônia Legal, estabelece instrumentos de incentivo à produção, agroindustrialização, certificação, comercialização, financiamento, garantia de crédito, compras públicas e acesso a mercados, e dá outras providências. | R54: |E5|
A55: PL 4721/2026 | B55: Câmara dos Deputados | C55: PL | D55: — | G55: 2026 | H55: 20/07/2026 | I55: E12 | J55: E12 | K55: Médio-alta | L55: 12 | P55: Varredura · ago/2026 | Q55: Consolida, em lei federal o Programa Nacional de Certificação e Rastreabilidade da Pesca Artesanal Sustentável e cria o Selo Nacional da Pesca Artesanal Brasileira. | R55: |E12|
A56: PL 4746/2026 | B56: Câmara dos Deputados | C56: PL | D56: — | G56: 2026 | H56: 21/07/2026 | I56: E12 | J56: E12 | K56: Médio-alta | L56: 12 | P56: Varredura · ago/2026 | Q56: Institui o Programa Povos da Pesca Artesanal. | R56: |E12|
A57: PL 4749/2026 | B57: Câmara dos Deputados | C57: PL | D57: — | G57: 2026 | H57: 21/07/2026 | I57: E12 | J57: E12 | K57: Médio-alta | L57: 12 | P57: Varredura · ago/2026 | Q57: Institui o Programa Nacional de Desenvolvimento Sustentável da Aquicultura (ProAqui). | R57: |E12|
A58: PL 4867/2026 | B58: Câmara dos Deputados | C58: PL | D58: — | G58: 2026 | H58: 03/08/2026 | I58: E11 | J58: E11 | K58: Médio-alta | L58: 12 | P58: Varredura · ago/2026 | Q58: Institui o Programa Nacional de Crédito Rural Assistido para Profissionais de Segurança Pública - PNCR-SEG; estabelece diretrizes gerais para a concessão de crédito rural a integrantes de órgãos de segurança pública; e dispõe sobre ações de promoção da saúde ocupacional e da qualidade de vida desses profissionais. | R58: |E11|
A59: PL 523/2026 | B59: Câmara dos Deputados | C59: Projeto de lei | D59: — | G59: 2026 | H59: 2026-02-11 | I59: E11 | J59: E11 | K59: Média | L59: 12 | M59: Crédito rural, seguro e financiamento | N59: Pode alterar instrumentos de crédito ou financiamento relevantes para produtores rurais e para a assistência técnica. | O59: Monitorar tramitação e mapear impacto para produtores e assistência técnica. | P59: Consolidada · abr/2026 | Q59: Altera a Lei nº 4.829, de 5 de novembro de 1965, para vedar a prática de venda casada na contratação de crédito rural. | R59: |E11|
A60: PL 828/2026 | B60: Câmara dos Deputados | C60: Projeto de lei | D60: — | G60: 2026 | H60: 2026-03-02 | I60: E11 | J60: E11 | K60: Muito alta | L60: 12 | M60: Crédito rural, seguro e financiamento | N60: Pode alterar instrumentos de crédito ou financiamento relevantes para produtores rurais e para a assistência técnica. | O60: Monitorar tramitação e mapear impacto para produtores e assistência técnica. | P60: Consolidada · abr/2026 | Q60: Altera a Lei nº 4.829, de 5 de novembro de 1965; o Decreto-Lei nº 167, de 14 de fevereiro de 1967; a Lei nº 13.986, de 7 de abril de 2020; a Lei nº 8.929, de 22 de agosto de 1994; a Lei nº 13.476, de 28 de agosto de 2017; e a Lei nº 14.711, de 30 de outubro de 2023, para vedar a utilização da alienação fiduciária como modalidade de garantia nas operações de crédito rural e revogar dispositivos que fragilizam a proteção do produtor rural. | R60: |E11|
A61: PL 950/2026 | B61: Câmara dos Deputados | C61: Projeto de lei | D61: — | G61: 2026 | H61: 2026-03-04 | I61: E11 | J61: E11 | K61: Muito alta | L61: 12 | M61: Crédito rural, seguro e financiamento | N61: Pode alterar instrumentos de crédito ou financiamento relevantes para produtores rurais e para a assistência técnica. | O61: Monitorar tramitação e mapear impacto para produtores e assistência técnica. | P61: Consolidada · abr/2026 | Q61: Institui o Programa de Securitização das Dívidas Rurais – PSDR, destinado à reestruturação de operações de crédito rural de produtores afetados por crises sistêmicas no setor agropecuário, e dá outras providências | R61: |E11|
A62: REQ 44/2026 | B62: Câmara dos Deputados | C62: Requerimento | D62: — | G62: 2026 | H62: 2026-04-06 | I62: E4 | J62: E4 | K62: Muito alta | L62: 12 | M62: Agrotóxicos, fiscalização e biossegurança | N62: Relaciona-se à fiscalização, biossegurança, fitossanidade e execução técnica em ambiente regulado. | O62: Priorizar monitoramento e avaliar nota técnica regulatória. | P62: Consolidada · abr/2026 | Q62: Requer a realização de Audiência Pública para debater a implementação do Programa Nacional de Redução de Agrotóxicos (PRONARA) em Minas Gerais e a recomposição do Grupo Executivo Permanente (GEP), com a atualização e implementação do Plano de Ação (PLANERA), da Estratégia Intersetorial de Redução do Uso de Agrotóxicos e Apoio à Agroecologia e à Produção Orgânica em Minas Gerais. | R62: |E4|
A63: RIC 2209/2026 | B63: Câmara dos Deputados | C63: RIC | D63: — | G63: 2026 | H63: 15/07/2026 | I63: E11 | J63: E11 | K63: Médio-alta | L63: 12 | P63: Varredura · ago/2026 | Q63: Requer informações ao Senhor Ministro de Estado da Fazenda sobre as providências e os prazos para a normatização, pelo Conselho Monetário Nacional e pelo Banco Central do Brasil, das condições de crédito do Pronaf asseguradas aos pescadores artesanais pelo art. 6º da Lei nº 15.399, de 4 de maio de 2026. | R63: |E11|
A64: RIC 2227/2026 | B64: Câmara dos Deputados | C64: RIC | D64: — | G64: 2026 | H64: 17/07/2026 | I64: E12 | J64: E12 | K64: Médio-alta | L64: 12 | P64: Varredura · ago/2026 | Q64: Requer informações ao Ministro de Estado da Pesca e Aquicultura acerca dos procedimentos de recebimento, registro, tramitação, preservação e localização de documentos administrativos no âmbito do Ministério da Pesca e Aquicultura e dos órgãos que o antecederam. | R64: |E12|
A65: RIC 2307/2026 | B65: Câmara dos Deputados | C65: RIC | D65: — | G65: 2026 | H65: 05/08/2026 | I65: E12 | J65: E12 | K65: Médio-alta | L65: 12 | P65: Varredura · ago/2026 | Q65: Requer informações ao Excelentíssimo Senhor Ministro de Estado da Pesca e Aquicultura acerca da concessão de acesso do IBAMA à base de dados do sistema PesqBrasil – Mapa de Bordo e do uso desse instrumento de gestão estatística para a aplicação de multas ambientais automatizadas contra pescadores artesanais no Estado de Santa Catarina. | R65: |E12|
A66: PDL 785/2026 | B66: Câmara dos Deputados | C66: PDL | D66: — | G66: 2026 | H66: 10/07/2026 | I66: E8 | J66: E8 | K66: Média | L66: 10 | P66: Varredura · ago/2026 | Q66: Aprova o ato que renova a outorga conferida à Nascente Comunicações Ltda. para executar serviço de radiodifusão sonora em frequência modulada, no Município de Bertioga, Estado de São Paulo. | R66: |E8|
A67: PL 1214/2026 | B67: Câmara dos Deputados | C67: Projeto de lei | D67: — | G67: 2026 | H67: 2026-03-17 | I67: E8 | J67: E8, E12 | K67: Média | L67: 10 | M67: Produção agropecuária e cadeias produtivas | N67: Incide sobre produção agropecuária, cadeias produtivas ou atividades de interesse direto das modalidades registradas no CFTA. | O67: Acompanhar tramitação e classificar impacto setorial para o CFTA. | P67: Consolidada · abr/2026 | Q67: Altera a Lei nº 9.433/1997 para ampliar a definição de uso insignificante de recursos hídricos na atividade agropecuária. | R67: |E8|E12|
A68: PL 3643/2026 | B68: Câmara dos Deputados | C68: PL | D68: — | G68: 2026 | H68: 10/07/2026 | I68: E4 | J68: E4 | K68: Média | L68: 10 | P68: Varredura · ago/2026 | Q68: Altera o Código Penal e a legislação penal especial para estabelecer causas de aumento de pena aos crimes praticados com emprego de aeronave remotamente pilotada, veículo aéreo não tripulado ou sistema remoto equivalente. | R68: |E4|
A69: PL 3664/2026 | B69: Câmara dos Deputados | C69: PL | D69: — | G69: 2026 | H69: 13/07/2026 | I69: E8 | J69: E8 | K69: Média | L69: 10 | P69: Varredura · ago/2026 | Q69: Institui a Lei App Seguro e Proteção Imediata em Acidentes, estabelece o Regime Nacional de Proteção dos Entregadores e Motoristas de Aplicativo em Acidentes Relacionados ao Serviço, dispõe sobre seguro obrigatório, assistência emergencial, comunicação de sinistros, prevenção de riscos, transparência, vedação a bloqueios indevidos e mecanismos de recolocação e recuperação profissional, e dá outras providências. | R69: |E8|
A70: PL 4637/2026 | B70: Câmara dos Deputados | C70: PL | D70: — | G70: 2026 | H70: 17/07/2026 | I70: E8 | J70: E8 | K70: Média | L70: 10 | P70: Varredura · ago/2026 | Q70: Institui regime jurídico de transparência integral de preço em plataformas digitais de intermediação de consumo - Lei do Preço Real no App, veda práticas de preço isca em contextos de sobrecusto logístico regional, e dá outras providências. | R70: |E8|
A71: REQ 3/2026 | B71: Senado Federal | C71: Requerimento | D71: Hamilton Mourão | G71: 2026 | H71: 2026-02-19 | I71: E11 | J71: E11, E12 | K71: Médio-alta | L71: 10 | M71: Produção agropecuária e cadeias produtivas | N71: Incide sobre produção agropecuária, cadeias produtivas ou atividades de interesse direto das modalidades registradas no CFTA. | O71: Acompanhar tramitação e classificar impacto setorial para o CFTA. | P71: Consolidada · abr/2026 | Q71: Requeiro, nos termos do art. 58, § 2º, II, da Constituição Federal e do art. 93, II, do Regimento Interno do Senado Federal, a realização de audiência pública, com o objetivo de discutir a proposta de criação e/ou implementação da Área de Proteção Ambiental (APA) Pau Ferro, especialmente no que se refere aos seus impactos sobre a atividade agropecuária, a segurança jurídica dos produtores rurais, o uso e ocupação do solo e o desenvolvimento econômico local. Proponho para a audiência a presença dos seguintes convidados: • representante da Prefeitura Municipal de BOSSOROCA - RS; • representante da Prefeitura Municipal de ITACURUBI - RS; • representante da Prefeitura Municipal de SANTIAGO - RS; • representante da Prefeitura Municipal de SANTO ANTONIO DAS MISSÕES - RS; • representante da Prefeitura Municipal de UNISTALDA - RS; • representante do Instituto Chico Mendes de Conservação da Biodiversidade (ICMBio); • representante do Ministério da Agricultura, Pecuária e Abastecimento; • representante da Secretaria de Agricultura, Pecuária e Irrigação do RS; • representante do Sindicato Rural de SANTIAGO, UNISTALDA e CAPÃO DO CIPÓ; • representante do Sindicato Rural de BOSSOROCA; • representante do Sindicato Rural de SÃO LUIZ GONZAGA e Coordenadora da Regional 12 da FARSUL; • representante do SIndicato Rural de ITACURUBI; • representante do Sindicato dos Trabalhadores Rurais de SANTIAGO, UNISTALDA e CAPÃO DO CIPÓ; • representante do Sindicato Rural de SANTO ANTÔNIO DAS MISSÕES. | R71: |E11|E12|
A72: REQ 45/2026 | B72: Câmara dos Deputados | C72: Requerimento | D72: — | G72: 2026 | H72: 2026-04-09 | I72: E11 | J72: E11, E12 | K72: Médio-alta | L72: 10 | M72: Assistência técnica, extensão e carreira pública | N72: Afeta assistência técnica, extensão rural, formação técnica ou estrutura de carreira ligada ao setor agropecuário. | O72: Monitorar tramitação e avaliar posicionamento institucional. | P72: Consolidada · abr/2026 | Q72: Requer a designação de representação oficial da Comissão de Agricultura, Pecuária, Abastecimento e Desenvolvimento Rural para participar da 52ª Exposição Feira Agropecuária, Industrial e Comercial de Maringá (Expoingá 2026), no município de Maringá - PR. | R72: |E11|E12|
A73: REQ 91/2026 | B73: Câmara dos Deputados | C73: REQ | D73: — | G73: 2026 | H73: 06/08/2026 | I73: E8 | J73: E8 | K73: Média | L73: 10 | P73: Varredura · ago/2026 | Q73: Requer a realização de Seminário sobre os desafios à proteção dos territórios, do patrimônio socioambiental e dos direitos dos povos e comunidades tradicionais no Vale do Jequitinhonha, com especial atenção à concessão do Parque Estadual do Biribiri, aos processos de licenciamento ambiental que impactam comunidades tradicionais e à expansão da mineração na região. | R73: |E8|
A74: RIC 2190/2026 | B74: Câmara dos Deputados | C74: RIC | D74: — | G74: 2026 | H74: 13/07/2026 | I74: E1 | J74: E1 | K74: Média | L74: 10 | P74: Varredura · ago/2026 | Q74: Requer informações ao Senhor Ministro de Estado do Meio Ambiente e Mudança do Clima sobre a comercialização de créditos de carbono jurisdicionais pelo Estado do Acre — estoque do Acre Carbon Standard (ACS) e programa ART TREES — e sobre a supervisão federal exercida pela CONAREDD+ e por esse Ministério. | R74: |E1|
A75: RIC 2196/2026 | B75: Câmara dos Deputados | C75: RIC | D75: — | G75: 2026 | H75: 15/07/2026 | I75: E4 | J75: E4 | K75: Média | L75: 10 | P75: Varredura · ago/2026 | Q75: Requer informações ao Ministério da Justiça e Segurança Pública acerca da capacitação de operadores de drones, da aquisição de aeronaves remotamente pilotadas (drones) e das políticas públicas voltadas ao fortalecimento da capacidade tecnológica dos órgãos de segurança pública no enfrentamento ao crime organizado. | R75: |E4|
A76: RIC 2237/2026 | B76: Câmara dos Deputados | C76: RIC | D76: — | G76: 2026 | H76: 23/07/2026 | I76: E4 | J76: E4 | K76: Média | L76: 10 | P76: Varredura · ago/2026 | Q76: Solicita informações ao Senhor Ministro de Estado do Trabalho e Emprego, acerca do Termo de Fomento celebrado com o Instituto Brasileiro de Administração Pública e Apoio Universitário do Rio de Janeiro – IBAP/RJ para execução de curso de capacitação em operação de aeronaves remotamente pilotadas (drones), financiado com recursos da União. | R76: |E4|
A77: RIC 2241/2026 | B77: Câmara dos Deputados | C77: RIC | D77: — | G77: 2026 | H77: 28/07/2026 | I77: E4 | J77: E4 | K77: Média | L77: 10 | P77: Varredura · ago/2026 | Q77: Requer informações a Senhora Ministra-Chefe da Casa Civil da Presidência da República acerca da regulamentação da Lei nº 15.070, de 23 de dezembro de 2024 (Marco Regulatório dos Bioinsumos). | R77: |E4|
A78: RIC 2260/2026 | B78: Câmara dos Deputados | C78: RIC | D78: — | G78: 2026 | H78: 29/07/2026 | I78: E4 | J78: E4 | K78: Média | L78: 10 | P78: Varredura · ago/2026 | Q78: Solicita informações ao Senhor Ministro-Chefe da Casa Civil da Presidência da República acerca da regulamentação da Lei nº 15.070, de 23 de dezembro de 2024 (Marco Regulatório dos Bioinsumos). | R78: |E4|
A79: RIC 2264/2026 | B79: Câmara dos Deputados | C79: RIC | D79: — | G79: 2026 | H79: 29/07/2026 | I79: E4 | J79: E4 | K79: Média | L79: 10 | P79: Varredura · ago/2026 | Q79: Solicita informações ao Senhor Ministro-Chefe da Casa Civil da Presidência da República acerca da regulamentação da Lei nº 15.070, de 23 de dezembro de 2024 (Marco Regulatório dos Bioinsumos). | R79: |E4|
A80: RIC 2265/2026 | B80: Câmara dos Deputados | C80: RIC | D80: — | G80: 2026 | H80: 29/07/2026 | I80: E4 | J80: E4 | K80: Média | L80: 10 | P80: Varredura · ago/2026 | Q80: Solicita ao Ministério do Trabalho e Emprego informações acerca de Termo de Fomento destinado à capacitação de moradores de comunidades de baixa renda do Rio de Janeiro para a operação profissional de drones. | R80: |E4|
A81: INC 126/2026 | B81: Câmara dos Deputados | C81: Indicação | D81: — | G81: 2026 | H81: 2026-02-27 | I81: E12 | J81: E12, E2 | K81: Médio-alta | L81: 8 | M81: Produção agropecuária e cadeias produtivas | N81: Incide sobre produção agropecuária, cadeias produtivas ou atividades de interesse direto das modalidades registradas no CFTA. | O81: Acompanhar tramitação e classificar impacto setorial para o CFTA. | P81: Consolidada · abr/2026 | Q81: Sugere ao Poder Executivo, especificamente ao Ministério das Mulheres, Ministério dos Direitos Humanos e da Cidadania, Ministério da Agricultura e Pecuária, Ministério da Justiça e da Segurança Pública, Ministério da Saúde, Ministério dos Transportes, Ministério do Trabalho e Emprego, Ministério do Desenvolvimento Agrário e Agricultura Familiar, Ministério da Integração e do Desenvolvimento Regional, Ministério do Desenvolvimento e Assistência Social, Família e Combate à Fome, Ministério das Cidades e Ministério da Fazenda, visando abertura de crédito extraordinário destinado ao apoio estratégico à Zona da Mata no estado de Minas Gerais. | R81: |E12|E2|
A82: PL 1621/2026 | B82: Câmara dos Deputados | C82: Projeto de lei | D82: — | G82: 2026 | H82: 2026-04-07 | I82: E12 | J82: E12 | K82: Médio-alta | L82: 5 | M82: Produção agropecuária e cadeias produtivas | N82: Incide sobre produção agropecuária, cadeias produtivas ou atividades de interesse direto das modalidades registradas no CFTA. | O82: Acompanhar tramitação e classificar impacto setorial para o CFTA. | P82: Consolidada · abr/2026 | Q82: Institui o Programa Nacional de Armazenagem e Secagem da Produção Agropecuária – PNAS, com o objetivo de reduzir perdas, ampliar a capacidade de estocagem e fortalecer a infraestrutura produtiva no meio rural. | R82: |E12|
A83: MPV 1346/2026 | B83: Câmara dos Deputados | C83: Medida provisória | D83: — | G83: 2026 | H83: 2026-03-27 | I83: E2 | J83: E2 | K83: Médio-alta | L83: 3 | M83: Produção agropecuária e cadeias produtivas | N83: Incide sobre produção agropecuária, cadeias produtivas ou atividades de interesse direto das modalidades registradas no CFTA. | O83: Acompanhar tramitação e classificar impacto setorial para o CFTA. | P83: Consolidada · abr/2026 | Q83: Abre crédito extraordinário, em favor do Ministério do Desenvolvimento Agrário e Agricultura Familiar e de Operações Oficiais de Crédito, no valor de R$ 20.429.000,00, para os fins que especifica. | R83: |E2|
A84: MPV 1346/2026 | B84: Congresso Nacional | C84: Medida provisória | D84: Presidência da República | G84: 2026 | H84: 2026-03-26 | I84: E2 | J84: E2 | K84: Médio-alta | L84: 3 | M84: Produção agropecuária e cadeias produtivas | N84: Incide sobre produção agropecuária, cadeias produtivas ou atividades de interesse direto das modalidades registradas no CFTA. | O84: Acompanhar tramitação e classificar impacto setorial para o CFTA. | P84: Consolidada · abr/2026 | Q84: Abre crédito extraordinário, em favor do Ministério do Desenvolvimento Agrário e Agricultura Familiar e de Operações Oficiais de Crédito, no valor de R$ 20.429.000,00, para os fins que especifica. | R84: |E2|
A85: PL 1154/2026 | B85: Câmara dos Deputados | C85: Projeto de lei | D85: — | G85: 2026 | H85: 2026-03-13 | I85: E2 | J85: E2 | K85: Médio-alta | L85: 3 | M85: Produção agropecuária e cadeias produtivas | N85: Incide sobre produção agropecuária, cadeias produtivas ou atividades de interesse direto das modalidades registradas no CFTA. | O85: Acompanhar tramitação e classificar impacto setorial para o CFTA. | P85: Consolidada · abr/2026 | Q85: Altera a Lei nº 15.223, de 2025, e a Lei nº 8.171, de 1991, para institucionalizar garantias de crédito e transparência orçamentária para mulheres e jovens da agricultura familiar. | R85: |E2|
A86: PL 1202/2026 | B86: Câmara dos Deputados | C86: Projeto de lei | D86: — | G86: 2026 | H86: 2026-03-17 | I86: E2 | J86: E2 | K86: Alta | L86: 3 | M86: Produção agropecuária e cadeias produtivas | N86: Incide sobre produção agropecuária, cadeias produtivas ou atividades de interesse direto das modalidades registradas no CFTA. | O86: Acompanhar tramitação e classificar impacto setorial para o CFTA. | P86: Consolidada · abr/2026 | Q86: Institui a Política Nacional de Incentivo à Irrigação para a Agricultura Familiar e para os Pequenos e Médios Produtores Rurais, com o objetivo de ampliar o acesso ao crédito para implantação de sistemas de irrigação por pivô central, perfuração de poços artesianos e outras infraestruturas hídricas destinadas à mitigação dos efeitos da estiagem e à redução das perdas produtivas no campo. e dá outras providências. | R86: |E2|
A87: RIC 109/2026 | B87: Câmara dos Deputados | C87: Requerimento de informação | D87: — | G87: 2026 | H87: 2026-02-04 | I87: E2 | J87: E2 | K87: Médio-alta | L87: 3 | M87: Produção agropecuária e cadeias produtivas | N87: Incide sobre produção agropecuária, cadeias produtivas ou atividades de interesse direto das modalidades registradas no CFTA. | O87: Acompanhar tramitação e classificar impacto setorial para o CFTA. | P87: Consolidada · abr/2026 | Q87: Requer que sejam prestadas, pelo Senhor Luiz Paulo Teixeira, Ministro de Estado do Desenvolvimento Agrário e Agricultura Familiar – MDA, informações sobre a tramitação interna do PRONARA, bem como os pareceres, resoluções e manifestações do Conselho Gestor. | R87: |E2|
A88: PL 1156/2026 | B88: Câmara dos Deputados | C88: Projeto de lei | D88: — | G88: 2026 | H88: 2026-03-13 | K88: Média | L88: 0 | M88: Produção agropecuária e cadeias produtivas | N88: Incide sobre produção agropecuária, cadeias produtivas ou atividades de interesse direto das modalidades registradas no CFTA. | O88: Acompanhar tramitação e classificar impacto setorial para o CFTA. | P88: Consolidada · abr/2026 | Q88: Altera a Lei nº 8.184, de 10 de maio de 1991, que dispõe sobre os períodos censitários dos Censos Demográficos e Agropecuários, e a Lei nº 6.938, de 31 de agosto de 1981, para incluir a obrigatoriedade de levantamento de dados sobre animais domésticos nos Censos Demográficos realizados pelo Instituto Brasileiro de Geografia e Estatística (IBGE), e dá outras providências. | R88: |
A89: PL 1248/2026 | B89: Câmara dos Deputados | C89: Projeto de lei | D89: — | G89: 2026 | H89: 2026-03-18 | K89: Média | L89: 0 | M89: Produção agropecuária e cadeias produtivas | N89: Incide sobre produção agropecuária, cadeias produtivas ou atividades de interesse direto das modalidades registradas no CFTA. | O89: Acompanhar tramitação e classificar impacto setorial para o CFTA. | P89: Consolidada · abr/2026 | Q89: Altera a Lei nº 10.883 e a Lei nº 10.826 para reconhecer como atividade de risco as atribuições desempenhadas pelos integrantes da Carreira de Auditor Fiscal Federal Agropecuário e autorizar o porte de arma de fogo, e dá outras providências. | R89: |
A90: PL 79/2026 | B90: Câmara dos Deputados | C90: Projeto de lei | D90: — | G90: 2026 | H90: 2026-02-02 | K90: Média | L90: 0 | M90: Agrotóxicos, fiscalização e biossegurança | N90: Relaciona-se à fiscalização, biossegurança, fitossanidade e execução técnica em ambiente regulado. | O90: Priorizar monitoramento e avaliar nota técnica regulatória. | P90: Consolidada · abr/2026 | Q90: Altera a Lei nº 7.678, de 8 de novembro de 1988, para flexibilizar o percentual de matéria-prima própria exigido para a produção de vinho colonial em territórios sob pressão do agronegócio extensivo ou afetados por deriva de defensivos agrícolas. | R90: |
A91: PLP 34/2026 | B91: Câmara dos Deputados | C91: Projeto de lei complementar | D91: — | G91: 2026 | H91: 2026-02-24 | K91: Média | L91: 0 | M91: Produção agropecuária e cadeias produtivas | N91: Incide sobre produção agropecuária, cadeias produtivas ou atividades de interesse direto das modalidades registradas no CFTA. | O91: Acompanhar tramitação e classificar impacto setorial para o CFTA. | P91: Consolidada · abr/2026 | Q91: Altera a Lei Complementar nº 224, de dezembro de 2025, para ajustar os incentivos ao setor agropecuário. | R91: |

Sheet Federais monitoradas
A1: Proposição | B1: Casa | C1: Autoria | D1: Apresentação | E1: Tema | F1: Comissão/órgão | G1: Estágio processual | H1: Última movimentação | I1: Data | J1: Prioridade | K1: Eixos | L1: Observações | M1: Ementa | N1: Chave
A2: PL 1648/2024 | B2: Senado | C2: Senador Jayme Campos (UNIÃO/MT) | D2: 2024-05-07 | E2: ITR — responsabilidade técnica e emendas do CFTA | F2: CAE | G2: Pronta para pauta | H2: PRONTA PARA A PAUTA NA COMISSÃO. | I2: 2026-08-10 | J2: Urgente | K2: E11, E1 | M2: Altera a Lei nº 9.393/1996 (ITR) e a Lei nº 11.250/2005. | N2: |E11|E1|
A3: PL 1905/2023 | B3: Senado | C3: Câmara dos Deputados (Dep. Dr. Jaziel) | D3: 2025-12-22 | E3: Reurb-E e Termo de Responsabilidade Técnica | F3: CCJ | G3: Parecer aprovado | H3: APROVADO PARECER NA COMISSÃO. | I3: 2026-08-06 | J3: Urgente | K3: E7, E1 | L3: Acompanhar conexão com regularização fundiária e georreferenciamento. Incluir os técnicos agrícolas como agentes aptos a realizar levantamentos planialtimétricos e georreferenciamentos para fins de Reurb. | M3: Altera a Lei nº 13.465/2017 para incluir instituições religiosas, de assistência social e sem fins lucrativos na Reurb-E e o Termo de Responsabilidade Técnica entre os documentos exigidos. | N3: |E7|E1|
A4: PL 1968/2022 | B4: Senado | C4: Senador Jorge Kajuru (PODEMOS/GO) | D4: 2022-07-10 | E4: Transparência da taxa de registro (ART) | F4: CAS | G4: Pronta para pauta | H4: PRONTA PARA A PAUTA NA COMISSÃO. | I4: 2026-05-21 | J4: Alta | K4: E1, E10 | M4: Altera a Lei nº 6.496/1977 para dar transparência ao contratante sobre os valores recolhidos a título de taxa de registro (ART). | N4: |E1|E10|
A5: PL 4926/2023 | B5: Senado | C5: Senador Zequinha Marinho (PODEMOS/PA) | D5: 2023-10-09 | E5: Isenção de anuidade de conselhos para pessoas idosas | F5: CAE | G5: Pronta para pauta | H5: PRONTA PARA A PAUTA NA COMISSÃO. | I5: 2026-07-16 | J5: Urgente | K5: E10 | M5: Acrescenta o art. 26-A à Lei nº 10.741/2003 para isentar pessoas idosas do pagamento de contribuições aos conselhos de fiscalização profissional. | N5: |E10|
A6: PEC 381/2017 | B6: Câmara | C6: André Figueiredo | D6: 2017-11-09 | E6: Impedimento a ocupantes de cargos na Magistratura | F6: CCJC | G6: Relator designado | H6: Designado Relator, Dep. Félix Mendonça Júnior (PDT-BA). | I6: 2025-04-03 | J6: Baixa | M6: Acrescenta inciso VI ao parágrafo único do art. 95 da CF (impedimento a ocupantes de cargos na Magistratura). | N6: |
A7: PL 1367/2022 | B7: Câmara | C7: Laercio Oliveira | D7: 2013-08-14 | E7: Controle integrado de vetores e pragas urbanas | F7: CCJC | G7: Relator designado | H7: Designado Relator, Dep. José Rocha (UNIÃO-BA). | I7: 2026-05-07 | J7: Alta | K7: E3, E1 | L7: Consta como demanda de atuação direta na CCJC. Aguardando apreciação das emendas do Senado pela CCJC. Relatório OK. | M7: Dispõe sobre a prestação dos serviços de controle integrado de vetores e pragas urbanas por empresas especializadas. | N7: |E3|E1|
A8: PL 1648/2020 | B8: Senado | C8: Senador Confúcio Moura (MDB/RO) | D8: 2020-04-06 | E8: Benefícios previdenciários e relações de trabalho | F8: CAS | G8: Com a relatoria | H8: MATÉRIA COM A RELATORIA. | I8: 2025-10-20 | J8: Media | K8: E10 | M8: Altera a Lei nº 8.213/1990 (Planos de Benefícios da Previdência Social) e a CLT. | N8: |E10|
A9: PL 1822/2025 | B9: Câmara | C9: Romero Rodrigues | D9: 2025-04-23 | E9: Segurança na aplicação aeroagrícola por drones | F9: CVT | G9: Relator designado | H9: Designado Relator, Dep. Jonas Donizette (PSB-SP). | I9: 2026-02-24 | J9: Alta | K9: E4, E1 | L9: Impacto em tecnologia rural e segurança operacional. | M9: Dispõe sobre a segurança na aplicação aeroagrícola de agrotóxicos, adjuvantes, fertilizantes, corretivos, bioinsumos e sementes com aeronaves remotamente pilotadas. | N9: |E4|E1|
A10: PL 1882/2023 | B10: Senado | C10: Senador Zequinha Marinho (PL/PA) | D10: 2023-04-13 | E10: Mandatos em entidades de classe e conselhos | F10: CAS | G10: Com a relatoria | H10: MATÉRIA COM A RELATORIA. | I10: 2026-06-30 | J10: Alta | K10: E10 | M10: Disciplina os mandatos de membros de entidades de classe e de organizações de interesse público. | N10: |E10|
A11: PL 225/2024 | B11: Câmara | C11: Delegada Adriana Accorsi | D11: 2024-02-07 | E11: Produção familiar de cachaça e aguardente | F11: CDC | G11: Relator designado | H11: Designado Relator, Dep. Charles Fernandes (PSD-BA). | I11: 2026-03-17 | J11: Alta | K11: E5 | L11: Pode compor cruzamento de agroindústria artesanal. | M11: Dispõe sobre a produção de cachaça e aguardente de cana-de-açúcar por estabelecimento familiar rural. | N11: |E5|
A12: PL 3584/2015 | B12: Câmara | C12: Evair de Melo | D12: 2015-11-11 | E12: Política Nacional de Incentivo às Agroindústrias | F12: CCJC | G12: Retirado de pauta | H12: Retirado de pauta, de ofício, em razão da ausência do Relator. | I12: 2026-07-15 | J12: Urgente | K12: E5, E1 | L12: Um dos projetos mais próximos de avanço. Aprovado na CDEIC (2016) e na CAPADR (2016). Na CCJC, conclusiva, aguardava o parecer do relator Dep. Pedro Lupion. Trabalhar o relatório no Senado. | M12: Institui a Política Nacional de Incentivo às Agroindústrias. | N12: |E5|E1|
A13: PL 3665/2024 | B13: Senado | C13: Senador Hamilton Mourão (REPUBLICANOS/RS) | D13: 2024-09-22 | E13: Regulamentação das análises clínicas animais | F13: CMA | G13: Com a relatoria | H13: MATÉRIA COM A RELATORIA. | I13: 2025-03-12 | J13: Media | K13: E12, E1 | M13: Dispõe sobre a regulamentação das análises clínicas animais no Brasil. | N13: |E12|E1|
A14: PL 3692/2025 | B14: Câmara | C14: Domingos Neto | D14: 2025-08-04 | E14: Saúde dos trabalhadores rurais e agrotóxicos | F14: CAPADR | G14: Relator designado | H14: Designado Relator, Dep. Tião Medeiros (PP-PR). | I14: 2025-12-02 | J14: Urgente | K14: E4, E6 | L14: Prioridade 1 nas anotações. | M14: Dispõe sobre a proteção da saúde e da integridade dos trabalhadores rurais no tratamento e revestimento de sementes. | N14: |E4|E6|
A15: PL 4187/2025 | B15: Câmara | C15: Clodoaldo Magalhães | D15: 2025-08-22 | E15: Sistema Nacional de Sementes e Mudas | F15: CMADS | G15: Relator designado | H15: Designado Relator, Dep. Coronel Chrisóstomo (PL-RO). | I15: 2026-05-19 | J15: Alta | K15: E6 | L15: Tema estratégico para sementes e mudas. | M15: Altera a Lei nº 10.711/2003, que dispõe sobre o Sistema Nacional de Sementes e Mudas. | N15: |E6|
A16: PL 4444/2021 | B16: Câmara | C16: Isnaldo Bulhões Jr. | D16: 2021-12-15 | E16: Gestão eficiente do patrimônio imobiliário federal | F16: PLEN | G16: Relator designado | H16: Designado Relator, Dep. José Priante (MDB-PA). | I16: 2022-02-24 | J16: Media | K16: E7 | L16: Relaciona-se a gestão imobiliária pública. | M16: Cria o Programa Nacional de Gestão Eficiente do Patrimônio Imobiliário Federal e altera a Lei nº 9.636/1998. | N16: |E7|
A17: PL 4718/2020 | B17: Senado | C17: Senador Marcos Rogério (DEM/RO) | D17: 2020-09-23 | E17: Regularização fundiária na Amazônia Legal | F17: CRA | G17: Com a relatoria | H17: MATÉRIA COM A RELATORIA. | I17: 2025-12-08 | J17: Alta | K17: E7 | M17: Altera a Lei nº 11.952/2009 (regularização fundiária de ocupações em terras da União na Amazônia Legal). | N17: |E7|
A18: PL 5269/2023 | B18: Câmara | C18: André Fernandes | D18: 2023-10-30 | E18: Tipificação do estelionato | F18: CCJC | G18: Relator designado | H18: Designado Relator, Dep. Marcelo Crivella (REPUBLIC-RJ), para o PL 1300/2022, ao qual esta proposição está apensada. | I18: 2024-08-27 | J18: Baixa | K18: E10 | M18: Altera o Decreto-Lei nº 2.848/1940 no capítulo do estelionato e outras fraudes. | N18: |E10|
A19: PL 6348/2019 | B19: Câmara | C19: Vilson da Fetaemg | D19: 2019-12-10 | E19: Denominação “Cachaça Artesanal” | F19: CICS | G19: Retirado de pauta | H19: Retirado de pauta, de ofício, em razão da ausência do Relator. | I19: 2026-07-14 | J19: Alta | K19: E5, E3 | L19: Incluído a partir da demanda prioritária do usuário. | M19: Cria a denominação “Cachaça Artesanal” e disciplina sua produção, fiscalização, controle e comercialização. | N19: |E5|E3|
A20: PL 8407/2017 | B20: Câmara | C20: Roberto de Lucena | D20: 2017-08-30 | E20: Exercício da profissão de médico-veterinário | F20: CCJC | G20: Relator designado | H20: Designado Relator, Dep. Hugo Leal (PSD-RJ). | I20: 2025-11-25 | J20: Alta | K20: E1, E12 | L20: Mencionado no áudio como demanda urgente. | M20: Acrescenta parágrafo único à alínea “e” do art. 5º da Lei nº 5.517/1968 (exercício da profissão de médico-veterinário). | N20: |E1|E12|
A21: PL 2190/2023 | B21: Câmara | C21: Tadeu Veneri | D21: 2023-04-26 | E21: Comercialização de sementes e mudas crioulas | F21: CCJC | G21: Relatoria devolvida | H21: Devolvida pelo Relator sem manifestação. | I21: 2026-02-13 | J21: Alta | K21: E6, E2 | L21: Projeto listado como central na agenda da CCJC. Aprovado na CAPADR em 23/04/2024 (relator Dep. Daniel Agrobom). Na CCJC, conclusiva, solicitada relatoria ao Dep. Rafael Prudente. | M21: Altera a Lei nº 10.711/2003 para dispor sobre livre multiplicação, troca e comercialização de sementes e mudas de cultivar local, tradicional ou crioula. | N21: |E6|E2|
A22: PL 3913/2019 | B22: Senado | C22: CPI de Brumadinho | D22: 2019-07-04 | E22: Licenciamento e segurança de barragens de rejeitos | F22: CCJ | G22: Aguardando relator | H22: AGUARDANDO DESIGNAÇÃO DO RELATOR. | I22: 2025-02-18 | J22: Media | K22: E8 | M22: Proíbe o licenciamento ambiental de novas barragens de rejeitos e de resíduos industriais e estabelece regras de segurança. | N22: |E8|
A23: PL 3958/2019 | B23: Senado | C23: Senador Luis Carlos Heinze (PP/RS) | D23: 2019-07-08 | E23: Inspeção industrial e sanitária de produtos de origem animal | F23: CCJ | G23: Aguardando relator | H23: AGUARDANDO DESIGNAÇÃO DO RELATOR. | I23: 2025-08-18 | J23: Alta | K23: E3, E5 | M23: Altera a Lei nº 1.283/1950, que dispõe sobre a inspeção industrial e sanitária dos produtos de origem animal. | N23: |E3|E5|
A24: PL 3979/2019 | B24: Câmara | C24: Eduardo Bismarck | D24: 2019-07-09 | E24: Conselhos de Classes de Profissões Regulamentadas | F24: CTRAB | G24: Relatoria devolvida | H24: Devolvida pelo Relator sem manifestação. | I24: 2026-03-05 | J24: Alta | K24: E10 | L24: Tema sensível para conselhos profissionais. | M24: Regulamenta a atuação das autarquias especiais — os conselhos de fiscalização de profissões regulamentadas. | N24: |E10|
A25: PL 4110/2024 | B25: Câmara | C25: Juarez Costa | D25: 2024-10-29 | E25: Documento de responsabilidade técnica em imóveis rurais | F25: MESA | G25: Prazo recursal encerrado | H25: Encerramento automático do prazo de recurso em 08/07/2026. Não foram apresentados recursos. | I25: 2026-07-08 | J25: Urgente | K25: E7, E1 | L25: Um dos projetos mais estratégicos para atuação imediata. | M25: Altera a Lei nº 6.015/1973 para dispor sobre o documento de responsabilidade técnica no desmembramento, parcelamento ou remembramento de imóveis rurais. | N25: |E7|E1|
A26: PL 510/2021 | B26: Senado | C26: Senador Irajá (PSD/TO) | D26: 2021-02-21 | E26: Regularização fundiária — emendas apresentadas a pedido do CFTA | F26: CRA | G26: Aguardando relator | H26: AGUARDANDO DESIGNAÇÃO DO RELATOR. | I26: 2023-11-13 | J26: Urgente | K26: E7 | L26: Emenda de Plenário nº 13 apresentada pelo Sen. Eduardo Gomes a pedido do CFTA; emendas nºs 133 a 137 apresentadas pelo Sen. Jaime Bagattoli a pedido do Conselho. Tramita em conjunto com o PL 2633/2020. | M26: Altera a Lei nº 11.952/2009 e outras normas para ampliar o alcance da regularização fundiária. | N26: |E7|
A27: PLP 125/2023 | B27: Câmara | C27: Jorge Goetten | D27: 2023-05-24 | E27: Alteração do Simples Nacional | F27: CPASF | G27: Relatoria devolvida | H27: Devolvida pelo Relator sem manifestação. | I27: 2026-04-15 | J27: Urgente | K27: E11 | L27: Prioridade 2 nas anotações; precisa decisão estratégica do CFTA. | M27: Altera a LC nº 123/2006, a Lei nº 12.592/2012 e a LC nº 116/2003. | N27: |E11|
A28: PDL 443/2025 | B28: Câmara | C28: Rodolfo Nogueira | D28: 2025-07-07 | E28: Sustação do decreto de redução de agrotóxicos | F28: CCJC | G28: Recebido em comissão | H28: Recebimento pela CCJC. | I28: 2026-05-14 | J28: Alta | K28: E4 | M28: Susta o Decreto nº 12.538/2025, que institui o Programa Nacional de Redução de Agrotóxicos. | N28: |E4|
A29: PL 1531/2023 | B29: Câmara | C29: Silvio Costa Filho | D29: 2023-03-30 | E29: Isenção de anuidade para doentes graves | F29: CFT | G29: Recebido em comissão | H29: Recebimento pela CFT. | I29: 2025-09-18 | J29: Alta | K29: E10 | L29: Mencionado no áudio como demanda da semana. | M29: Dispõe sobre a isenção da anuidade devida aos Conselhos de Arquitetura e Urbanismo por profissionais com doença grave. | N29: |E10|
A30: PL 2477/2023 | B30: Câmara | C30: Amom Mandel | D30: 2023-05-10 | E30: Conceito de nascente e APP | F30: CCP | G30: Parecer publicado | H30: Encaminhada à publicação. Parecer da CMADS publicado no DCD de 15/10/2025, Letra A. | I30: 2025-10-14 | J30: Alta | K30: E8 | L30: Tema ambiental sensível para contenção qualificada. | M30: Altera a Lei nº 12.651/2012 para ampliar o conceito de nascente e de Área de Preservação Permanente. | N30: |E8|
A31: PL 2782/2019 | B31: Câmara | C31: Giovani Cherini | D31: 2019-05-09 | E31: Técnicos agrícolas no Minha Casa Minha Vida | F31: CCJC | G31: Recebido em comissão | H31: Recebimento pela CCJC. | I31: 2026-05-29 | J31: Alta | K31: E7, E1 | L31: Projeto com aderência direta à atuação profissional em habitação rural. | M31: Acrescenta o art. 11-A à Lei nº 11.977/2009 (PMCMV) para incluir os técnicos agrícolas. | N31: |E7|E1|
A32: PL 2925/2025 | B32: Câmara | C32: Dal Barreto | D32: 2025-06-17 | E32: Agrônomos, veterinários e zootecnistas no Pronater | F32: CCP | G32: Parecer publicado | H32: Encaminhada à publicação. Parecer da CAPADR publicado no DCD de 14/10/2025, Letra A. | I32: 2025-10-13 | J32: Urgente | K32: E2, E1 | L32: Risco corporativo; precisa de atenção. | M32: Altera a Lei nº 12.188/2010 para estabelecer a presença de engenheiros agrônomos, médicos veterinários ou zootecnistas nas equipes do Pronater. | N32: |E2|E1|
A33: PL 3280/2021 | B33: Câmara | C33: Heitor Schuch | D33: 2021-09-22 | E33: Regularização documental de imóveis rurais | F33: CASP | G33: Prazo de emendas encerrado | H33: Encerrado o prazo de emendas ao substitutivo (09/04 a 22/04/2026). Não foram apresentadas emendas. | I33: 2026-04-22 | J33: Alta | K33: E7 | M33: Dispõe sobre a regularização documental de imóveis em áreas rurais de domínio particular fora da Amazônia Legal. | N33: |E7|
A34: PL 3291/2019 | B34: Câmara | C34: Gil Cutrim | D34: 2019-06-04 | E34: Recuperação ambiental dos rios maranhenses | F34: CFT | G34: Recebido em comissão | H34: Recebimento pela CFT. | I34: 2024-12-09 | J34: Alta | K34: E8 | L34: Mencionado como demanda urgente da semana. | M34: Cria o Programa de Recuperação Ambiental Proteção das Águas dos Rios Maranhenses. | N34: |E8|
A35: PL 3820/2021 | B35: Câmara | C35: Senado Federal — CPI da Pandemia | D35: 2021-12-20 | E35: Livro dos Heróis da Pandemia | F35: CCP | G35: Parecer publicado | H35: Encaminhada à publicação. Parecer da CCJC publicado em avulso e no DCD de 25/03/2026, Letra B. | I35: 2026-03-24 | J35: Urgente | L35: Projeto pronto para pauta. | M35: Institui o Livro dos Heróis e Heroínas da Pandemia de Covid-19. | N35: |
A36: PL 4012/2025 | B36: Câmara | C36: Marcelo Queiroz | D36: 2025-08-14 | E36: Seguro de Responsabilidade Técnica (SRT-ART) | F36: CTRAB | G36: Recebido em comissão | H36: Recebimento pela CTRAB. | I36: 2025-09-16 | J36: Alta | K36: E1, E10 | L36: Atenção a efeitos sobre conselhos profissionais. | M36: Institui o Seguro de Responsabilidade Técnica (SRT-ART) vinculado à Anotação de Responsabilidade Técnica. | N36: |E1|E10|
A37: PL 4013/2025 | B37: Câmara | C37: Marcelo Queiroz | D37: 2025-08-14 | E37: Remuneração técnica Engenharia/Agronomia | F37: CTRAB | G37: Recebido em comissão | H37: Recebimento pela CTRAB. | I37: 2025-09-16 | J37: Alta | K37: E1, E10 | L37: Conecta com estratégia de proteção da arquitetura institucional dos conselhos. | M37: Estabelece remuneração técnica proporcional para profissionais da Engenharia e Agronomia no exercício da responsabilidade técnica. | N37: |E1|E10|
A38: PL 4074/2021 | B38: Câmara | C38: Airton Faleiro | D38: 2021-11-17 | E38: Agricultura urbana em programas habitacionais | F38: CCP | G38: Parecer publicado | H38: Encaminhada à publicação. Parecer da CDU publicado no DCD de 11/10/2025, Letra B. | I38: 2025-10-10 | J38: Alta | K38: E5, E9 | L38: Mencionado no áudio como projeto na CCP. Aprovado na CAPADR e na CDU (relator Dep. Ícaro de Valmir). Na CCJC, trabalhar relator. | M38: Dispõe sobre a reserva de áreas para sistemas produtivos de agricultura urbana ou periurbana em programas habitacionais públicos federais. | N38: |E5|E9|
A39: PL 4110/2025 | B39: Câmara | C39: Aline Gurgel | D39: 2025-08-19 | E39: Competências na aquicultura e na pesca | F39: CCP | G39: Recebido em comissão | H39: Recebimento pela CMADS. | I39: 2025-12-02 | J39: Media | K39: E12, E1 | M39: Altera a Lei nº 11.959/2009 (Política Nacional de Desenvolvimento Sustentável da Aquicultura e da Pesca) para incluir competências. | N39: |E12|E1|
A40: PL 4158/2025 | B40: Câmara | C40: Mersinho Lucena | D40: 2025-08-21 | E40: Regulamentação da atividade de arborista | F40: CCP | G40: Parecer publicado | H40: Encaminhada à publicação. Parecer da Comissão de Trabalho publicado no DCD de 17/04/2026, Letra A. | I40: 2026-04-16 | J40: Alta | K40: E1, E9 | L40: Mencionado no áudio como pendente na CCP. | M40: Dispõe sobre a atividade profissional de arborista. | N40: |E1|E9|
A41: PL 4239/2024 | B41: Câmara | C41: Yury do Paredão | D41: 2024-11-04 | E41: Abrigos de cães e gatos | F41: CMADS | G41: Prazo de emendas encerrado | H41: Encerrado o prazo de emendas (27/11 a 11/12/2025). Não foram apresentadas emendas. | I41: 2025-12-11 | J41: Media | K41: E12 | L41: Monitoramento seletivo. | M41: Institui abrigos de cães e gatos em municípios com população igual ou superior a 50.000 habitantes. | N41: |E12|
A42: PL 4257/2025 | B42: Câmara | C42: Enfermeira Rejane | D42: 2025-08-27 | E42: Combate ao racismo nos conselhos profissionais | F42: CCP | G42: Parecer publicado | H42: Encaminhada à publicação. Parecer da CDHMIR publicado no DCD de 22/05/2026, Letra A. | I42: 2026-05-21 | J42: Alta | K42: E10 | L42: Mencionado no áudio como pendente na CCP. | M42: Obriga a inclusão de normas de prevenção ao racismo e promoção da igualdade racial nos códigos de ética profissionais. | N42: |E10|
A43: PL 4681/2023 | B43: Câmara | C43: Marcelo Queiroz | D43: 2023-09-26 | E43: Destinação de animais mortos | F43: CCP | G43: Parecer publicado | H43: Encaminhada à publicação. Publicação inicial no DCD de 06/10/2023. | I43: 2023-10-05 | J43: Alta | K43: E3 | L43: Entrar na lista de conferência junto à CCP. | M43: Dispõe sobre recolha, transporte, armazenagem, manuseio e destinação final de animais mortos. | N43: |E3|
A44: PL 4805/2024 | B44: Câmara | C44: Max Lemos | D44: 2024-12-10 | E44: Destinação de 1% do ITR para qualificação profissional | F44: CCP | G44: Parecer publicado | H44: Encaminhada à publicação. Parecer da CAPADR publicado no DCD de 22/10/2025, Letra A. | I44: 2025-10-21 | J44: Alta | K44: E11, E9 | L44: Mencionado como pendente na CCP. | M44: Altera a Lei nº 9.393/1996 para destinar 1% da arrecadação do ITR a programas de qualificação profissional. | N44: |E11|E9|
A45: PL 5407/2025 | B45: Câmara | C45: Greyce Elias | D45: 2025-10-24 | E45: Reaproveitamento de rejeitos da mineração | F45: CME | G45: Recebido em comissão | H45: Recebimento pela CME. | I45: 2026-02-04 | J45: Media | K45: E8 | L45: Monitoramento. | M45: Dispõe sobre o aproveitamento de estéreis e rejeitos da atividade minerária para recuperação de áreas degradadas. | N45: |E8|
A46: PL 5862/2023 | B46: Câmara | C46: João Daniel | D46: 2023-12-05 | E46: Serviço voluntário | F46: CCJC | G46: Recebido em comissão | H46: Recebimento pela CCJC. | I46: 2025-10-29 | J46: Baixa | K46: E9 | M46: Altera a Lei nº 9.608/1998, que dispõe sobre o serviço voluntário. | N46: |E9|
A47: PL 6093/2023 | B47: Câmara | C47: Coronel Fernanda | D47: 2023-12-19 | E47: Demarcação de terras indígenas | F47: CPOVOS | G47: Prazo de emendas encerrado | H47: Encerrado o prazo de emendas (18/09 a 01/10/2025). Não foram apresentadas emendas. | I47: 2025-10-01 | J47: Media | K47: E7 | L47: Monitoramento seletivo. | M47: Regulamenta o art. 231 da CF e dispõe sobre o procedimento administrativo de demarcação de terras indígenas. | N47: |E7|
A48: PL 1024/2020 | B48: Câmara | C48: Poder Executivo | D48: 2020-03-25 | E48: Regulação das profissões de Engenheiro, Arquiteto e Engenheiro-Agrônomo | F48: MESA | G48: Remetido ao Senado | H48: Remessa ao Senado Federal por meio do Of. nº 315/2026/PS-GSE. | I48: 2026-05-06 | J48: Alta | K48: E1, E10 | L48: Tema de fronteira profissional. | M48: Altera a Lei nº 5.194/1966, que regula o exercício das profissões de Engenheiro, Arquiteto e Engenheiro-Agrônomo. | N48: |E1|E10|
A49: PL 1942/2022 | B49: Câmara | C49: Coronel Armando | D49: 2022-07-07 | E49: Titulação de terras quilombolas | F49: MESA | G49: Movimentação processual | H49: Apresentação do REQ nº 1994/2026 de redistribuição à CPOVOS. | I49: 2026-04-09 | J49: Media | K49: E7 | L49: Monitoramento. | M49: Dispõe sobre identificação, delimitação, reconhecimento e titulação das terras de remanescentes de quilombos. | N49: |E7|
A50: PL 2283/2021 | B50: Câmara | C50: Fausto Pinato | D50: 2021-06-22 | E50: Avaliação de imóveis públicos federais | F50: CASP | G50: Movimentação processual | H50: Aprovado o REQ nº 67/2025, do Dep. Reimont, para realização de audiência pública. | I50: 2025-08-12 | J50: Urgente | K50: E7, E1 | L50: Projeto próximo de avanço. | M50: Dispõe sobre procedimentos nas avaliações de imóveis destinados a órgãos e entidades públicas federais. | N50: |E7|E1|
A51: PL 4993/2024 | B51: Câmara | C51: Duda Salabert | D51: 2024-12-19 | E51: Política Nacional de Segurança de Barragens | F51: CMADS | G51: Em tramitação | H51: Parecer do Relator, Dep. Nilto Tatto (PT-SP), pela aprovação com emenda e rejeição das Emendas 1 a 4/25. | I51: 2026-05-27 | J51: Urgente | K51: E8 | L51: Pronto para pauta; atuação imediata. | M51: Altera a Lei nº 12.334/2010 (Política Nacional de Segurança de Barragens). | N51: |E8|
A52: PL 5269/2019 | B52: Câmara | C52: Dra. Soraya Manato | D52: 2019-09-26 | E52: Usucapião extrajudicial | F52: MESA | G52: Movimentação processual | H52: Apensação do PL 4701/2025 ao PL 5921/2019. | I52: 2025-11-06 | J52: Alta | K52: E7 | L52: Demanda de porta em porta na CCJC. | M52: Altera a Lei nº 6.015/1973, que dispõe sobre os registros públicos. | N52: |E7|
A53: PL 6176/2013 | B53: Câmara | C53: Padre João | D53: 2013-08-23 | E53: Bancos comunitários de sementes e mudas crioulas | F53: MESA | G53: Remetido ao Senado | H53: Remessa ao Senado Federal por meio do Of. nº 884/2025/SGM-P. | I53: 2025-12-19 | J53: Media | K53: E6, E2 | M53: Institui a Política Nacional de Incentivo à Formação de Bancos Comunitários de Sementes e Mudas de variedades locais, tradicionais ou crioulas. | N53: |E6|E2|
A54: PL 699/2023 | B54: Câmara | C54: Senado Federal — Laércio Oliveira | D54: 2024-03-21 | E54: Profert — Programa de Desenvolvimento da Indústria de Fertilizantes | F54: MESA | G54: Remetido ao Senado | H54: Remessa ao Senado Federal por meio do Of. nº 141/2026/SGM-P. | I54: 2026-06-24 | J54: Alta | K54: E4, E11 | M54: Institui o Programa de Desenvolvimento da Indústria de Fertilizantes (Profert). | N54: |E4|E11|
A55: PLS 168/2018 | B55: Senado | C55: Senador Acir Gurgacz (PDT/RO) | D55: 2018-04-09 | E55: Licenciamento ambiental e avaliação ambiental estratégica | F55: CCJ | G55: Desarquivada | H55: DESARQUIVADA — RISF art. 332, § 1º. | I55: 2023-04-11 | J55: Media | K55: E8 | M55: Regulamenta o licenciamento ambiental previsto no art. 225, § 1º, IV, da CF e dispõe sobre avaliação ambiental estratégica. | N55: |E8|
A56: Pauta 2615340 — PRL 2 | B56: Câmara | C56: Laura Carneiro | D56: 2026-04-10 | E56: Parecer ao PL 82/2025 — pessoas com deficiência | F56: CPASF | G56: Em tramitação | H56: Parecer da Relatora, Dep. Laura Carneiro (PSD-RJ). | I56: 2026-04-10 | J56: Baixa | M56: Parecer da Relatora pela aprovação do PL 82/2025, na forma do substitutivo da Comissão de Defesa dos Direitos das Pessoas com Deficiência. | N56: |
A57: REQ 1/2026 — CDIR | B57: Senado | C57: Senador Irajá (PSD/TO) | D57: 2026-01-01 | E57: Requerimento de missão oficial | F57: CDIR | G57: Tramitação encerrada | H57: TRAMITAÇÃO ENCERRADA. | I57: 2026-03-13 | J57: Baixa | M57: Requer licença para desempenhar missão oficial no ICE Barcelona 2026. | N57: |

Sheet Marco normativo
A1: Norma | B1: Eixo | C1: Competência correlacionada
A2: Decreto nº 12.858/2026 | B2: E4 | C2: Agrotóxicos, bioinsumos e fertilizantes
A3: Decreto nº 90.922/1985 | B3: E1 | C3: Exercício profissional e responsabilidade técnica
A4: IN MAPA nº 53/2013 | B4: E4 | C4: Agrotóxicos, bioinsumos e fertilizantes
A5: Lei nº 1.283/1950 | B5: E3 | C5: Defesa agropecuária, inspeção e sanidade
A6: Lei nº 10.267/2001 | B6: E7 | C6: Regularização fundiária e georreferenciamento
A7: Lei nº 10.711/2003 | B7: E6 | C7: Sementes, mudas e material propagativo
A8: Lei nº 10.741/2003 | B8: E10 | C8: Conselhos profissionais, anuidades e fiscalização
A9: Lei nº 11.788/2008 | B9: E9 | C9: Formação, ensino técnico e qualificação profissional
A10: Lei nº 11.892/2008 | B10: E9 | C10: Formação, ensino técnico e qualificação profissional
A11: Lei nº 11.952/2009 | B11: E7 | C11: Regularização fundiária e georreferenciamento
A12: Lei nº 11.959/2009 | B12: E12 | C12: Produção animal, aquicultura e cadeias específicas
... A37: Lei nº 9.712/1998 | B37: E3 | C37: Defesa agropecuária, inspeção e sanidade

Sheet Triagem
A1: Base | B1: Etapa | C1: Registros
A2: Base consolidada — 30/04/2026 | B2: Registros importados e triados | C2: 3147
A3: Base consolidada — 30/04/2026 | B3: Selecionados como de interesse | C3: 213
A4: Varredura — 11/08/2026 | B4: Registros importados | C4: 5000
A5: Varredura — 11/08/2026 | B5: Descartados por critério formal | C5: 1092
A6: Varredura — 11/08/2026 | B6: Descartados por ausência de aderência temática | C6: 3743
A7: Varredura — 11/08/2026 | B7: Descartados por aderência abaixo do corte | C7: 98
A8: Varredura — 11/08/2026 | B8: Selecionados | C8: 67
A9: Varredura — 11/08/2026 | B9: Selecionados inéditos (após remoção de duplicatas) | C9: 67
A10: Consolidado | B10: Total de registros triados nas duas bases | C10: 8147
A11: Consolidado | B11: Total de matérias selecionadas | C11: 280
A12: Consolidado | B12: Proposições estaduais | C12: 190
A13: Consolidado | B13: Novas matérias federais | C13: 90
A14: Consolidado | B14: Matérias federais já monitoradas no Governor | C14: 56
